[
  {
    "InstanceId": "5970247746965900ac9f9f52",
    "Name": "Weight",
    "OwnerId": 19,
    "Owner": "KingDedede",
    "Value": "119 ",
    "Links": [
      {
        "Rel": "self",
        "Href": "http://beta-api-kuroganehammer.azurewebsites.net/api/movements/5970247746965900ac9f9f52"
      },
      {
        "Rel": "character",
        "Href": "http://beta-api-kuroganehammer.azurewebsites.net/api/characters/name/KingDedede"
      }
    ]
  },
  {
    "InstanceId": "5970247746965900ac9f9f53",
    "Name": "Max Jumps",
    "OwnerId": 19,
    "Owner": "KingDedede",
    "Value": "5",
    "Links": [
      {
        "Rel": "self",
        "Href": "http://beta-api-kuroganehammer.azurewebsites.net/api/movements/5970247746965900ac9f9f53"
      },
      {
        "Rel": "character",
        "Href": "http://beta-api-kuroganehammer.azurewebsites.net/api/characters/name/KingDedede"
      }
    ]
  },
  {
    "InstanceId": "5970247746965900ac9f9f54",
    "Name": "Run Speed",
    "OwnerId": 19,
    "Owner": "KingDedede",
    "Value": "1.36 ",
    "Links": [
      {
        "Rel": "self",
        "Href": "http://beta-api-kuroganehammer.azurewebsites.net/api/movements/5970247746965900ac9f9f54"
      },
      {
        "Rel": "character",
        "Href": "http://beta-api-kuroganehammer.azurewebsites.net/api/characters/name/KingDedede"
      }
    ]
  },
  {
    "InstanceId": "5970247746965900ac9f9f55",
    "Name": "Wall Jump",
    "OwnerId": 19,
    "Owner": "KingDedede",
    "Value": "No",
    "Links": [
      {
        "Rel": "self",
        "Href": "http://beta-api-kuroganehammer.azurewebsites.net/api/movements/5970247746965900ac9f9f55"
      },
      {
        "Rel": "character",
        "Href": "http://beta-api-kuroganehammer.azurewebsites.net/api/characters/name/KingDedede"
      }
    ]
  },
  {
    "InstanceId": "5970247746965900ac9f9f56",
    "Name": "Walk Speed",
    "OwnerId": 19,
    "Owner": "KingDedede",
    "Value": "0.98 ",
    "Links": [
      {
        "Rel": "self",
        "Href": "http://beta-api-kuroganehammer.azurewebsites.net/api/movements/5970247746965900ac9f9f56"
      },
      {
        "Rel": "character",
        "Href": "http://beta-api-kuroganehammer.azurewebsites.net/api/characters/name/KingDedede"
      }
    ]
  },
  {
    "InstanceId": "5970247746965900ac9f9f57",
    "Name": "Wall Cling",
    "OwnerId": 19,
    "Owner": "KingDedede",
    "Value": "No",
    "Links": [
      {
        "Rel": "self",
        "Href": "http://beta-api-kuroganehammer.azurewebsites.net/api/movements/5970247746965900ac9f9f57"
      },
      {
        "Rel": "character",
        "Href": "http://beta-api-kuroganehammer.azurewebsites.net/api/characters/name/KingDedede"
      }
    ]
  },
  {
    "InstanceId": "5970247746965900ac9f9f58",
    "Name": "Air Speed",
    "OwnerId": 19,
    "Owner": "KingDedede",
    "Value": "0.63 ",
    "Links": [
      {
        "Rel": "self",
        "Href": "http://beta-api-kuroganehammer.azurewebsites.net/api/movements/5970247746965900ac9f9f58"
      },
      {
        "Rel": "character",
        "Href": "http://beta-api-kuroganehammer.azurewebsites.net/api/characters/name/KingDedede"
      }
    ]
  },
  {
    "InstanceId": "5970247746965900ac9f9f59",
    "Name": "Crawl",
    "OwnerId": 19,
    "Owner": "KingDedede",
    "Value": "No",
    "Links": [
      {
        "Rel": "self",
        "Href": "http://beta-api-kuroganehammer.azurewebsites.net/api/movements/5970247746965900ac9f9f59"
      },
      {
        "Rel": "character",
        "Href": "http://beta-api-kuroganehammer.azurewebsites.net/api/characters/name/KingDedede"
      }
    ]
  },
  {
    "InstanceId": "5970247746965900ac9f9f5a",
    "Name": "Fall Speed",
    "OwnerId": 19,
    "Owner": "KingDedede",
    "Value": "1.95 ",
    "Links": [
      {
        "Rel": "self",
        "Href": "http://beta-api-kuroganehammer.azurewebsites.net/api/movements/5970247746965900ac9f9f5a"
      },
      {
        "Rel": "character",
        "Href": "http://beta-api-kuroganehammer.azurewebsites.net/api/characters/name/KingDedede"
      }
    ]
  },
  {
    "InstanceId": "5970247746965900ac9f9f5b",
    "Name": "Tether",
    "OwnerId": 19,
    "Owner": "KingDedede",
    "Value": "No",
    "Links": [
      {
        "Rel": "self",
        "Href": "http://beta-api-kuroganehammer.azurewebsites.net/api/movements/5970247746965900ac9f9f5b"
      },
      {
        "Rel": "character",
        "Href": "http://beta-api-kuroganehammer.azurewebsites.net/api/characters/name/KingDedede"
      }
    ]
  },
  {
    "InstanceId": "5970247746965900ac9f9f5c",
    "Name": "Fast Fall Speed",
    "OwnerId": 19,
    "Owner": "KingDedede",
    "Value": "3.12 ",
    "Links": [
      {
        "Rel": "self",
        "Href": "http://beta-api-kuroganehammer.azurewebsites.net/api/movements/5970247746965900ac9f9f5c"
      },
      {
        "Rel": "character",
        "Href": "http://beta-api-kuroganehammer.azurewebsites.net/api/characters/name/KingDedede"
      }
    ]
  },
  {
    "InstanceId": "5970247746965900ac9f9f5d",
    "Name": "Jumpsquat",
    "OwnerId": 19,
    "Owner": "KingDedede",
    "Value": "6 frames",
    "Links": [
      {
        "Rel": "self",
        "Href": "http://beta-api-kuroganehammer.azurewebsites.net/api/movements/5970247746965900ac9f9f5d"
      },
      {
        "Rel": "character",
        "Href": "http://beta-api-kuroganehammer.azurewebsites.net/api/characters/name/KingDedede"
      }
    ]
  },
  {
    "InstanceId": "5970247746965900ac9f9f5e",
    "Name": "Air Acceleration",
    "OwnerId": 19,
    "Owner": "KingDedede",
    "Value": "0.04",
    "Links": [
      {
        "Rel": "self",
        "Href": "http://beta-api-kuroganehammer.azurewebsites.net/api/movements/5970247746965900ac9f9f5e"
      },
      {
        "Rel": "character",
        "Href": "http://beta-api-kuroganehammer.azurewebsites.net/api/characters/name/KingDedede"
      }
    ]
  },
  {
    "InstanceId": "5970247746965900ac9f9f5f",
    "Name": "Soft Landing Lag",
    "OwnerId": 19,
    "Owner": "KingDedede",
    "Value": "2 frames",
    "Links": [
      {
        "Rel": "self",
        "Href": "http://beta-api-kuroganehammer.azurewebsites.net/api/movements/5970247746965900ac9f9f5f"
      },
      {
        "Rel": "character",
        "Href": "http://beta-api-kuroganehammer.azurewebsites.net/api/characters/name/KingDedede"
      }
    ]
  },
  {
    "InstanceId": "5970247746965900ac9f9f60",
    "Name": "Gravity",
    "OwnerId": 19,
    "Owner": "KingDedede",
    "Value": "0.08788",
    "Links": [
      {
        "Rel": "self",
        "Href": "http://beta-api-kuroganehammer.azurewebsites.net/api/movements/5970247746965900ac9f9f60"
      },
      {
        "Rel": "character",
        "Href": "http://beta-api-kuroganehammer.azurewebsites.net/api/characters/name/KingDedede"
      }
    ]
  },
  {
    "InstanceId": "5970247746965900ac9f9f61",
    "Name": "Hard Landing Lag",
    "OwnerId": 19,
    "Owner": "KingDedede",
    "Value": "6 frames",
    "Links": [
      {
        "Rel": "self",
        "Href": "http://beta-api-kuroganehammer.azurewebsites.net/api/movements/5970247746965900ac9f9f61"
      },
      {
        "Rel": "character",
        "Href": "http://beta-api-kuroganehammer.azurewebsites.net/api/characters/name/KingDedede"
      }
    ]
  },
  {
    "InstanceId": "5970247746965900ac9f9f62",
    "Name": "SH Air Time",
    "OwnerId": 19,
    "Owner": "KingDedede",
    "Value": "38 frames",
    "Links": [
      {
        "Rel": "self",
        "Href": "http://beta-api-kuroganehammer.azurewebsites.net/api/movements/5970247746965900ac9f9f62"
      },
      {
        "Rel": "character",
        "Href": "http://beta-api-kuroganehammer.azurewebsites.net/api/characters/name/KingDedede"
      }
    ]
  },
  {
    "InstanceId": "5970247746965900ac9f9f63",
    "Name": "FH Air Time",
    "OwnerId": 19,
    "Owner": "KingDedede",
    "Value": "55 frames",
    "Links": [
      {
        "Rel": "self",
        "Href": "http://beta-api-kuroganehammer.azurewebsites.net/api/movements/5970247746965900ac9f9f63"
      },
      {
        "Rel": "character",
        "Href": "http://beta-api-kuroganehammer.azurewebsites.net/api/characters/name/KingDedede"
      }
    ]
  }
]