[
  {
    "InstanceId": "598e3ffc46965919a42805bc",
    "Name": "Jab 1",
    "OwnerId": 53,
    "Owner": "Villager",
    "HitboxActive": "3-4",
    "FirstActionableFrame": "22",
    "BaseDamage": "3",
    "Angle": "60/80",
    "BaseKnockBackSetKnockback": "10",
    "LandingLag": null,
    "AutoCancel": null,
    "KnockbackGrowth": "80",
    "MoveType": "ground",
    "IsWeightDependent": false,
    "Links": [
      {
        "Rel": "self",
        "Href": "http://beta-api-kuroganehammer.azurewebsites.net/api/moves/598e3ffc46965919a42805bc"
      },
      {
        "Rel": "character",
        "Href": "http://beta-api-kuroganehammer.azurewebsites.net/api/characters/name/Villager"
      }
    ]
  },
  {
    "InstanceId": "598e3ffc46965919a42805bd",
    "Name": "Jab 2",
    "OwnerId": 53,
    "Owner": "Villager",
    "HitboxActive": "3-4",
    "FirstActionableFrame": "24",
    "BaseDamage": "3",
    "Angle": "60/80",
    "BaseKnockBackSetKnockback": "20",
    "LandingLag": null,
    "AutoCancel": null,
    "KnockbackGrowth": "120",
    "MoveType": "ground",
    "IsWeightDependent": false,
    "Links": [
      {
        "Rel": "self",
        "Href": "http://beta-api-kuroganehammer.azurewebsites.net/api/moves/598e3ffc46965919a42805bd"
      },
      {
        "Rel": "character",
        "Href": "http://beta-api-kuroganehammer.azurewebsites.net/api/characters/name/Villager"
      }
    ]
  },
  {
    "InstanceId": "598e3ffc46965919a42805be",
    "Name": "Dash Attack",
    "OwnerId": 53,
    "Owner": "Villager",
    "HitboxActive": "14-19",
    "FirstActionableFrame": "55",
    "BaseDamage": "10",
    "Angle": "70",
    "BaseKnockBackSetKnockback": "65",
    "LandingLag": null,
    "AutoCancel": null,
    "KnockbackGrowth": "60",
    "MoveType": "ground",
    "IsWeightDependent": false,
    "Links": [
      {
        "Rel": "self",
        "Href": "http://beta-api-kuroganehammer.azurewebsites.net/api/moves/598e3ffc46965919a42805be"
      },
      {
        "Rel": "character",
        "Href": "http://beta-api-kuroganehammer.azurewebsites.net/api/characters/name/Villager"
      }
    ]
  },
  {
    "InstanceId": "598e3ffc46965919a42805bf",
    "Name": "Dash Attack (Late)",
    "OwnerId": 53,
    "Owner": "Villager",
    "HitboxActive": "20-28",
    "FirstActionableFrame": "-",
    "BaseDamage": "6",
    "Angle": "70",
    "BaseKnockBackSetKnockback": "65",
    "LandingLag": null,
    "AutoCancel": null,
    "KnockbackGrowth": "60",
    "MoveType": "ground",
    "IsWeightDependent": false,
    "Links": [
      {
        "Rel": "self",
        "Href": "http://beta-api-kuroganehammer.azurewebsites.net/api/moves/598e3ffc46965919a42805bf"
      },
      {
        "Rel": "character",
        "Href": "http://beta-api-kuroganehammer.azurewebsites.net/api/characters/name/Villager"
      }
    ]
  },
  {
    "InstanceId": "598e3ffc46965919a42805c0",
    "Name": "Ftilt",
    "OwnerId": 53,
    "Owner": "Villager",
    "HitboxActive": "8-11",
    "FirstActionableFrame": "37",
    "BaseDamage": "9",
    "Angle": "361",
    "BaseKnockBackSetKnockback": "30",
    "LandingLag": null,
    "AutoCancel": null,
    "KnockbackGrowth": "90",
    "MoveType": "ground",
    "IsWeightDependent": false,
    "Links": [
      {
        "Rel": "self",
        "Href": "http://beta-api-kuroganehammer.azurewebsites.net/api/moves/598e3ffc46965919a42805c0"
      },
      {
        "Rel": "character",
        "Href": "http://beta-api-kuroganehammer.azurewebsites.net/api/characters/name/Villager"
      }
    ]
  },
  {
    "InstanceId": "598e3ffc46965919a42805c1",
    "Name": "Utilt (Hit 1)",
    "OwnerId": 53,
    "Owner": "Villager",
    "HitboxActive": "7-20",
    "FirstActionableFrame": "50",
    "BaseDamage": "6",
    "Angle": "105/105/96",
    "BaseKnockBackSetKnockback": "W: 60/60/12",
    "LandingLag": null,
    "AutoCancel": null,
    "KnockbackGrowth": "100",
    "MoveType": "ground",
    "IsWeightDependent": false,
    "Links": [
      {
        "Rel": "self",
        "Href": "http://beta-api-kuroganehammer.azurewebsites.net/api/moves/598e3ffc46965919a42805c1"
      },
      {
        "Rel": "character",
        "Href": "http://beta-api-kuroganehammer.azurewebsites.net/api/characters/name/Villager"
      }
    ]
  },
  {
    "InstanceId": "598e3ffc46965919a42805c2",
    "Name": "Utilt (Hit 2)",
    "OwnerId": 53,
    "Owner": "Villager",
    "HitboxActive": "24-27",
    "FirstActionableFrame": "-",
    "BaseDamage": "5",
    "Angle": "80",
    "BaseKnockBackSetKnockback": "50",
    "LandingLag": null,
    "AutoCancel": null,
    "KnockbackGrowth": "160",
    "MoveType": "ground",
    "IsWeightDependent": false,
    "Links": [
      {
        "Rel": "self",
        "Href": "http://beta-api-kuroganehammer.azurewebsites.net/api/moves/598e3ffc46965919a42805c2"
      },
      {
        "Rel": "character",
        "Href": "http://beta-api-kuroganehammer.azurewebsites.net/api/characters/name/Villager"
      }
    ]
  },
  {
    "InstanceId": "598e3ffc46965919a42805c3",
    "Name": "Dtilt",
    "OwnerId": 53,
    "Owner": "Villager",
    "HitboxActive": "9-10",
    "FirstActionableFrame": "35",
    "BaseDamage": "13/8",
    "Angle": "80/70",
    "BaseKnockBackSetKnockback": "40",
    "LandingLag": null,
    "AutoCancel": null,
    "KnockbackGrowth": "90",
    "MoveType": "ground",
    "IsWeightDependent": false,
    "Links": [
      {
        "Rel": "self",
        "Href": "http://beta-api-kuroganehammer.azurewebsites.net/api/moves/598e3ffc46965919a42805c3"
      },
      {
        "Rel": "character",
        "Href": "http://beta-api-kuroganehammer.azurewebsites.net/api/characters/name/Villager"
      }
    ]
  },
  {
    "InstanceId": "598e3ffc46965919a42805c4",
    "Name": "Fsmash (Flat Ground)",
    "OwnerId": 53,
    "Owner": "Villager",
    "HitboxActive": "25-29",
    "FirstActionableFrame": "50",
    "BaseDamage": "15",
    "Angle": "45",
    "BaseKnockBackSetKnockback": "70",
    "LandingLag": null,
    "AutoCancel": null,
    "KnockbackGrowth": "100",
    "MoveType": "ground",
    "IsWeightDependent": false,
    "Links": [
      {
        "Rel": "self",
        "Href": "http://beta-api-kuroganehammer.azurewebsites.net/api/moves/598e3ffc46965919a42805c4"
      },
      {
        "Rel": "character",
        "Href": "http://beta-api-kuroganehammer.azurewebsites.net/api/characters/name/Villager"
      }
    ]
  },
  {
    "InstanceId": "598e3ffc46965919a42805c5",
    "Name": "Fsmash (Off Ledge)",
    "OwnerId": 53,
    "Owner": "Villager",
    "HitboxActive": "25-29",
    "FirstActionableFrame": "-",
    "BaseDamage": "15",
    "Angle": "45",
    "BaseKnockBackSetKnockback": "70",
    "LandingLag": null,
    "AutoCancel": null,
    "KnockbackGrowth": "100",
    "MoveType": "ground",
    "IsWeightDependent": false,
    "Links": [
      {
        "Rel": "self",
        "Href": "http://beta-api-kuroganehammer.azurewebsites.net/api/moves/598e3ffc46965919a42805c5"
      },
      {
        "Rel": "character",
        "Href": "http://beta-api-kuroganehammer.azurewebsites.net/api/characters/name/Villager"
      }
    ]
  },
  {
    "InstanceId": "598e3ffc46965919a42805c6",
    "Name": "Fsmash (Off Ledge, Late)",
    "OwnerId": 53,
    "Owner": "Villager",
    "HitboxActive": "30-",
    "FirstActionableFrame": "-",
    "BaseDamage": "17",
    "Angle": "45",
    "BaseKnockBackSetKnockback": "70",
    "LandingLag": null,
    "AutoCancel": null,
    "KnockbackGrowth": "100",
    "MoveType": "ground",
    "IsWeightDependent": false,
    "Links": [
      {
        "Rel": "self",
        "Href": "http://beta-api-kuroganehammer.azurewebsites.net/api/moves/598e3ffc46965919a42805c6"
      },
      {
        "Rel": "character",
        "Href": "http://beta-api-kuroganehammer.azurewebsites.net/api/characters/name/Villager"
      }
    ]
  },
  {
    "InstanceId": "598e3ffc46965919a42805c7",
    "Name": "Usmash (Hit 1)",
    "OwnerId": 53,
    "Owner": "Villager",
    "HitboxActive": "12-13",
    "FirstActionableFrame": "54",
    "BaseDamage": "3",
    "Angle": "95",
    "BaseKnockBackSetKnockback": "W: 140",
    "LandingLag": null,
    "AutoCancel": null,
    "KnockbackGrowth": "100",
    "MoveType": "ground",
    "IsWeightDependent": false,
    "Links": [
      {
        "Rel": "self",
        "Href": "http://beta-api-kuroganehammer.azurewebsites.net/api/moves/598e3ffc46965919a42805c7"
      },
      {
        "Rel": "character",
        "Href": "http://beta-api-kuroganehammer.azurewebsites.net/api/characters/name/Villager"
      }
    ]
  },
  {
    "InstanceId": "598e3ffc46965919a42805c8",
    "Name": "Usmash (Hit 2-5)",
    "OwnerId": 53,
    "Owner": "Villager",
    "HitboxActive": "17-18, 21-22, 25-26, 29-30",
    "FirstActionableFrame": "-",
    "BaseDamage": "1",
    "Angle": "100",
    "BaseKnockBackSetKnockback": "30",
    "LandingLag": null,
    "AutoCancel": null,
    "KnockbackGrowth": "80",
    "MoveType": "ground",
    "IsWeightDependent": false,
    "Links": [
      {
        "Rel": "self",
        "Href": "http://beta-api-kuroganehammer.azurewebsites.net/api/moves/598e3ffc46965919a42805c8"
      },
      {
        "Rel": "character",
        "Href": "http://beta-api-kuroganehammer.azurewebsites.net/api/characters/name/Villager"
      }
    ]
  },
  {
    "InstanceId": "598e3ffc46965919a42805c9",
    "Name": "Usmash (Hit 6)",
    "OwnerId": 53,
    "Owner": "Villager",
    "HitboxActive": "33-34",
    "FirstActionableFrame": "-",
    "BaseDamage": "4",
    "Angle": "90",
    "BaseKnockBackSetKnockback": "30",
    "LandingLag": null,
    "AutoCancel": null,
    "KnockbackGrowth": "205",
    "MoveType": "ground",
    "IsWeightDependent": false,
    "Links": [
      {
        "Rel": "self",
        "Href": "http://beta-api-kuroganehammer.azurewebsites.net/api/moves/598e3ffc46965919a42805c9"
      },
      {
        "Rel": "character",
        "Href": "http://beta-api-kuroganehammer.azurewebsites.net/api/characters/name/Villager"
      }
    ]
  },
  {
    "InstanceId": "598e3ffc46965919a42805ca",
    "Name": "Dsmash (Hit 1)",
    "OwnerId": 53,
    "Owner": "Villager",
    "HitboxActive": "8",
    "FirstActionableFrame": "48",
    "BaseDamage": "6",
    "Angle": "70",
    "BaseKnockBackSetKnockback": "0",
    "LandingLag": null,
    "AutoCancel": null,
    "KnockbackGrowth": "80",
    "MoveType": "ground",
    "IsWeightDependent": false,
    "Links": [
      {
        "Rel": "self",
        "Href": "http://beta-api-kuroganehammer.azurewebsites.net/api/moves/598e3ffc46965919a42805ca"
      },
      {
        "Rel": "character",
        "Href": "http://beta-api-kuroganehammer.azurewebsites.net/api/characters/name/Villager"
      }
    ]
  },
  {
    "InstanceId": "598e3ffc46965919a42805cb",
    "Name": "Dsmash (Hit 1, Late)",
    "OwnerId": 53,
    "Owner": "Villager",
    "HitboxActive": "9-10 (Ground Only)",
    "FirstActionableFrame": "-",
    "BaseDamage": "3",
    "Angle": "70",
    "BaseKnockBackSetKnockback": "0",
    "LandingLag": null,
    "AutoCancel": null,
    "KnockbackGrowth": "50",
    "MoveType": "ground",
    "IsWeightDependent": false,
    "Links": [
      {
        "Rel": "self",
        "Href": "http://beta-api-kuroganehammer.azurewebsites.net/api/moves/598e3ffc46965919a42805cb"
      },
      {
        "Rel": "character",
        "Href": "http://beta-api-kuroganehammer.azurewebsites.net/api/characters/name/Villager"
      }
    ]
  },
  {
    "InstanceId": "598e3ffc46965919a42805cc",
    "Name": "Dsmash (Hit 2)",
    "OwnerId": 53,
    "Owner": "Villager",
    "HitboxActive": "29",
    "FirstActionableFrame": "-",
    "BaseDamage": "6",
    "Angle": "70",
    "BaseKnockBackSetKnockback": "0",
    "LandingLag": null,
    "AutoCancel": null,
    "KnockbackGrowth": "80",
    "MoveType": "ground",
    "IsWeightDependent": false,
    "Links": [
      {
        "Rel": "self",
        "Href": "http://beta-api-kuroganehammer.azurewebsites.net/api/moves/598e3ffc46965919a42805cc"
      },
      {
        "Rel": "character",
        "Href": "http://beta-api-kuroganehammer.azurewebsites.net/api/characters/name/Villager"
      }
    ]
  },
  {
    "InstanceId": "598e3ffc46965919a42805cd",
    "Name": "Dsmash (Hit 2, Late)",
    "OwnerId": 53,
    "Owner": "Villager",
    "HitboxActive": "30-31 (Ground Only)",
    "FirstActionableFrame": "-",
    "BaseDamage": "3",
    "Angle": "70",
    "BaseKnockBackSetKnockback": "0",
    "LandingLag": null,
    "AutoCancel": null,
    "KnockbackGrowth": "50",
    "MoveType": "ground",
    "IsWeightDependent": false,
    "Links": [
      {
        "Rel": "self",
        "Href": "http://beta-api-kuroganehammer.azurewebsites.net/api/moves/598e3ffc46965919a42805cd"
      },
      {
        "Rel": "character",
        "Href": "http://beta-api-kuroganehammer.azurewebsites.net/api/characters/name/Villager"
      }
    ]
  },
  {
    "InstanceId": "598e3ffc46965919a42805ce",
    "Name": "Standing Grab",
    "OwnerId": 53,
    "Owner": "Villager",
    "HitboxActive": "15-16",
    "FirstActionableFrame": "56",
    "BaseDamage": "",
    "Angle": "",
    "BaseKnockBackSetKnockback": "",
    "LandingLag": null,
    "AutoCancel": null,
    "KnockbackGrowth": "",
    "MoveType": "ground",
    "IsWeightDependent": false,
    "Links": [
      {
        "Rel": "self",
        "Href": "http://beta-api-kuroganehammer.azurewebsites.net/api/moves/598e3ffc46965919a42805ce"
      },
      {
        "Rel": "character",
        "Href": "http://beta-api-kuroganehammer.azurewebsites.net/api/characters/name/Villager"
      }
    ]
  },
  {
    "InstanceId": "598e3ffc46965919a42805cf",
    "Name": "Dash Grab",
    "OwnerId": 53,
    "Owner": "Villager",
    "HitboxActive": "16-17",
    "FirstActionableFrame": "70",
    "BaseDamage": "",
    "Angle": "",
    "BaseKnockBackSetKnockback": "",
    "LandingLag": null,
    "AutoCancel": null,
    "KnockbackGrowth": "",
    "MoveType": "ground",
    "IsWeightDependent": false,
    "Links": [
      {
        "Rel": "self",
        "Href": "http://beta-api-kuroganehammer.azurewebsites.net/api/moves/598e3ffc46965919a42805cf"
      },
      {
        "Rel": "character",
        "Href": "http://beta-api-kuroganehammer.azurewebsites.net/api/characters/name/Villager"
      }
    ]
  },
  {
    "InstanceId": "598e3ffc46965919a42805d0",
    "Name": "Pivot Grab",
    "OwnerId": 53,
    "Owner": "Villager",
    "HitboxActive": "17-18",
    "FirstActionableFrame": "66",
    "BaseDamage": "",
    "Angle": "",
    "BaseKnockBackSetKnockback": "",
    "LandingLag": null,
    "AutoCancel": null,
    "KnockbackGrowth": "",
    "MoveType": "ground",
    "IsWeightDependent": false,
    "Links": [
      {
        "Rel": "self",
        "Href": "http://beta-api-kuroganehammer.azurewebsites.net/api/moves/598e3ffc46965919a42805d0"
      },
      {
        "Rel": "character",
        "Href": "http://beta-api-kuroganehammer.azurewebsites.net/api/characters/name/Villager"
      }
    ]
  },
  {
    "InstanceId": "598e3ffc46965919a42805d1",
    "Name": "Spotdodge",
    "OwnerId": 53,
    "Owner": "Villager",
    "HitboxActive": "3-18",
    "FirstActionableFrame": "28",
    "BaseDamage": "",
    "Angle": "",
    "BaseKnockBackSetKnockback": "",
    "LandingLag": null,
    "AutoCancel": null,
    "KnockbackGrowth": "",
    "MoveType": "ground",
    "IsWeightDependent": false,
    "Links": [
      {
        "Rel": "self",
        "Href": "http://beta-api-kuroganehammer.azurewebsites.net/api/moves/598e3ffc46965919a42805d1"
      },
      {
        "Rel": "character",
        "Href": "http://beta-api-kuroganehammer.azurewebsites.net/api/characters/name/Villager"
      }
    ]
  },
  {
    "InstanceId": "598e3ffc46965919a42805d2",
    "Name": "Forward Roll",
    "OwnerId": 53,
    "Owner": "Villager",
    "HitboxActive": "4-17",
    "FirstActionableFrame": "31",
    "BaseDamage": "",
    "Angle": "",
    "BaseKnockBackSetKnockback": "",
    "LandingLag": null,
    "AutoCancel": null,
    "KnockbackGrowth": "",
    "MoveType": "ground",
    "IsWeightDependent": false,
    "Links": [
      {
        "Rel": "self",
        "Href": "http://beta-api-kuroganehammer.azurewebsites.net/api/moves/598e3ffc46965919a42805d2"
      },
      {
        "Rel": "character",
        "Href": "http://beta-api-kuroganehammer.azurewebsites.net/api/characters/name/Villager"
      }
    ]
  },
  {
    "InstanceId": "598e3ffc46965919a42805d3",
    "Name": "Back Roll",
    "OwnerId": 53,
    "Owner": "Villager",
    "HitboxActive": "4-17",
    "FirstActionableFrame": "31",
    "BaseDamage": "",
    "Angle": "",
    "BaseKnockBackSetKnockback": "",
    "LandingLag": null,
    "AutoCancel": null,
    "KnockbackGrowth": "",
    "MoveType": "ground",
    "IsWeightDependent": false,
    "Links": [
      {
        "Rel": "self",
        "Href": "http://beta-api-kuroganehammer.azurewebsites.net/api/moves/598e3ffc46965919a42805d3"
      },
      {
        "Rel": "character",
        "Href": "http://beta-api-kuroganehammer.azurewebsites.net/api/characters/name/Villager"
      }
    ]
  },
  {
    "InstanceId": "598e3ffc46965919a42805d4",
    "Name": "Airdodge",
    "OwnerId": 53,
    "Owner": "Villager",
    "HitboxActive": "3-28",
    "FirstActionableFrame": "34",
    "BaseDamage": "",
    "Angle": "",
    "BaseKnockBackSetKnockback": "",
    "LandingLag": null,
    "AutoCancel": null,
    "KnockbackGrowth": "",
    "MoveType": "ground",
    "IsWeightDependent": false,
    "Links": [
      {
        "Rel": "self",
        "Href": "http://beta-api-kuroganehammer.azurewebsites.net/api/moves/598e3ffc46965919a42805d4"
      },
      {
        "Rel": "character",
        "Href": "http://beta-api-kuroganehammer.azurewebsites.net/api/characters/name/Villager"
      }
    ]
  },
  {
    "InstanceId": "598e3ffc46965919a42805d5",
    "Name": "Nair",
    "OwnerId": 53,
    "Owner": "Villager",
    "HitboxActive": "3-10",
    "FirstActionableFrame": "36",
    "BaseDamage": "9",
    "Angle": "361",
    "BaseKnockBackSetKnockback": "20",
    "LandingLag": "14",
    "AutoCancel": "1-2, 27&gt;",
    "KnockbackGrowth": "100",
    "MoveType": "aerial",
    "IsWeightDependent": false,
    "Links": [
      {
        "Rel": "self",
        "Href": "http://beta-api-kuroganehammer.azurewebsites.net/api/moves/598e3ffc46965919a42805d5"
      },
      {
        "Rel": "character",
        "Href": "http://beta-api-kuroganehammer.azurewebsites.net/api/characters/name/Villager"
      }
    ]
  },
  {
    "InstanceId": "598e3ffc46965919a42805d6",
    "Name": "Nair (Late)",
    "OwnerId": 53,
    "Owner": "Villager",
    "HitboxActive": "11-23",
    "FirstActionableFrame": "-",
    "BaseDamage": "5",
    "Angle": "361",
    "BaseKnockBackSetKnockback": "20",
    "LandingLag": "-",
    "AutoCancel": "-",
    "KnockbackGrowth": "100",
    "MoveType": "aerial",
    "IsWeightDependent": false,
    "Links": [
      {
        "Rel": "self",
        "Href": "http://beta-api-kuroganehammer.azurewebsites.net/api/moves/598e3ffc46965919a42805d6"
      },
      {
        "Rel": "character",
        "Href": "http://beta-api-kuroganehammer.azurewebsites.net/api/characters/name/Villager"
      }
    ]
  },
  {
    "InstanceId": "598e3ffc46965919a42805d7",
    "Name": "Fair (Early)",
    "OwnerId": 53,
    "Owner": "Villager",
    "HitboxActive": "10-11",
    "FirstActionableFrame": "40",
    "BaseDamage": "7",
    "Angle": "361",
    "BaseKnockBackSetKnockback": "55",
    "LandingLag": "23",
    "AutoCancel": "1-7, 30&gt;",
    "KnockbackGrowth": "100",
    "MoveType": "aerial",
    "IsWeightDependent": false,
    "Links": [
      {
        "Rel": "self",
        "Href": "http://beta-api-kuroganehammer.azurewebsites.net/api/moves/598e3ffc46965919a42805d7"
      },
      {
        "Rel": "character",
        "Href": "http://beta-api-kuroganehammer.azurewebsites.net/api/characters/name/Villager"
      }
    ]
  },
  {
    "InstanceId": "598e3ffc46965919a42805d8",
    "Name": "Fair",
    "OwnerId": 53,
    "Owner": "Villager",
    "HitboxActive": "12-17",
    "FirstActionableFrame": "-",
    "BaseDamage": "4",
    "Angle": "361",
    "BaseKnockBackSetKnockback": "10",
    "LandingLag": "-",
    "AutoCancel": "-",
    "KnockbackGrowth": "100",
    "MoveType": "aerial",
    "IsWeightDependent": false,
    "Links": [
      {
        "Rel": "self",
        "Href": "http://beta-api-kuroganehammer.azurewebsites.net/api/moves/598e3ffc46965919a42805d8"
      },
      {
        "Rel": "character",
        "Href": "http://beta-api-kuroganehammer.azurewebsites.net/api/characters/name/Villager"
      }
    ]
  },
  {
    "InstanceId": "598e3ffc46965919a42805d9",
    "Name": "Fair (Late)",
    "OwnerId": 53,
    "Owner": "Villager",
    "HitboxActive": "18-23",
    "FirstActionableFrame": "-",
    "BaseDamage": "2.5",
    "Angle": "361",
    "BaseKnockBackSetKnockback": "10",
    "LandingLag": "-",
    "AutoCancel": "-",
    "KnockbackGrowth": "100",
    "MoveType": "aerial",
    "IsWeightDependent": false,
    "Links": [
      {
        "Rel": "self",
        "Href": "http://beta-api-kuroganehammer.azurewebsites.net/api/moves/598e3ffc46965919a42805d9"
      },
      {
        "Rel": "character",
        "Href": "http://beta-api-kuroganehammer.azurewebsites.net/api/characters/name/Villager"
      }
    ]
  },
  {
    "InstanceId": "598e3ffc46965919a42805da",
    "Name": "Bair (Early)",
    "OwnerId": 53,
    "Owner": "Villager",
    "HitboxActive": "13-14",
    "FirstActionableFrame": "36",
    "BaseDamage": "9",
    "Angle": "361",
    "BaseKnockBackSetKnockback": "55",
    "LandingLag": "23",
    "AutoCancel": "1-9, 25&gt;",
    "KnockbackGrowth": "100",
    "MoveType": "aerial",
    "IsWeightDependent": false,
    "Links": [
      {
        "Rel": "self",
        "Href": "http://beta-api-kuroganehammer.azurewebsites.net/api/moves/598e3ffc46965919a42805da"
      },
      {
        "Rel": "character",
        "Href": "http://beta-api-kuroganehammer.azurewebsites.net/api/characters/name/Villager"
      }
    ]
  },
  {
    "InstanceId": "598e3ffc46965919a42805db",
    "Name": "Bair",
    "OwnerId": 53,
    "Owner": "Villager",
    "HitboxActive": "15-20",
    "FirstActionableFrame": "-",
    "BaseDamage": "5",
    "Angle": "361",
    "BaseKnockBackSetKnockback": "10",
    "LandingLag": "-",
    "AutoCancel": "-",
    "KnockbackGrowth": "100",
    "MoveType": "aerial",
    "IsWeightDependent": false,
    "Links": [
      {
        "Rel": "self",
        "Href": "http://beta-api-kuroganehammer.azurewebsites.net/api/moves/598e3ffc46965919a42805db"
      },
      {
        "Rel": "character",
        "Href": "http://beta-api-kuroganehammer.azurewebsites.net/api/characters/name/Villager"
      }
    ]
  },
  {
    "InstanceId": "598e3ffc46965919a42805dc",
    "Name": "Bair (Late)",
    "OwnerId": 53,
    "Owner": "Villager",
    "HitboxActive": "21-26",
    "FirstActionableFrame": "-",
    "BaseDamage": "3",
    "Angle": "361",
    "BaseKnockBackSetKnockback": "10",
    "LandingLag": "-",
    "AutoCancel": "-",
    "KnockbackGrowth": "100",
    "MoveType": "aerial",
    "IsWeightDependent": false,
    "Links": [
      {
        "Rel": "self",
        "Href": "http://beta-api-kuroganehammer.azurewebsites.net/api/moves/598e3ffc46965919a42805dc"
      },
      {
        "Rel": "character",
        "Href": "http://beta-api-kuroganehammer.azurewebsites.net/api/characters/name/Villager"
      }
    ]
  },
  {
    "InstanceId": "598e3ffc46965919a42805dd",
    "Name": "Uair (Triple)",
    "OwnerId": 53,
    "Owner": "Villager",
    "HitboxActive": "6-7",
    "FirstActionableFrame": "43",
    "BaseDamage": "13",
    "Angle": "85",
    "BaseKnockBackSetKnockback": "30",
    "LandingLag": "15",
    "AutoCancel": "1-5, 39&gt;",
    "KnockbackGrowth": "100",
    "MoveType": "aerial",
    "IsWeightDependent": false,
    "Links": [
      {
        "Rel": "self",
        "Href": "http://beta-api-kuroganehammer.azurewebsites.net/api/moves/598e3ffc46965919a42805dd"
      },
      {
        "Rel": "character",
        "Href": "http://beta-api-kuroganehammer.azurewebsites.net/api/characters/name/Villager"
      }
    ]
  },
  {
    "InstanceId": "598e3ffc46965919a42805de",
    "Name": "Uair (Triple, Late)",
    "OwnerId": 53,
    "Owner": "Villager",
    "HitboxActive": "8-31",
    "FirstActionableFrame": "-",
    "BaseDamage": "6",
    "Angle": "85",
    "BaseKnockBackSetKnockback": "30",
    "LandingLag": "-",
    "AutoCancel": "-",
    "KnockbackGrowth": "100",
    "MoveType": "aerial",
    "IsWeightDependent": false,
    "Links": [
      {
        "Rel": "self",
        "Href": "http://beta-api-kuroganehammer.azurewebsites.net/api/moves/598e3ffc46965919a42805de"
      },
      {
        "Rel": "character",
        "Href": "http://beta-api-kuroganehammer.azurewebsites.net/api/characters/name/Villager"
      }
    ]
  },
  {
    "InstanceId": "598e3ffc46965919a42805df",
    "Name": "Uair (Double)",
    "OwnerId": 53,
    "Owner": "Villager",
    "HitboxActive": "6-7",
    "FirstActionableFrame": "-",
    "BaseDamage": "10",
    "Angle": "85",
    "BaseKnockBackSetKnockback": "30",
    "LandingLag": "-",
    "AutoCancel": "-",
    "KnockbackGrowth": "100",
    "MoveType": "aerial",
    "IsWeightDependent": false,
    "Links": [
      {
        "Rel": "self",
        "Href": "http://beta-api-kuroganehammer.azurewebsites.net/api/moves/598e3ffc46965919a42805df"
      },
      {
        "Rel": "character",
        "Href": "http://beta-api-kuroganehammer.azurewebsites.net/api/characters/name/Villager"
      }
    ]
  },
  {
    "InstanceId": "598e3ffc46965919a42805e0",
    "Name": "Uair (Double, Late)",
    "OwnerId": 53,
    "Owner": "Villager",
    "HitboxActive": "8-31",
    "FirstActionableFrame": "-",
    "BaseDamage": "5",
    "Angle": "85",
    "BaseKnockBackSetKnockback": "30",
    "LandingLag": "-",
    "AutoCancel": "-",
    "KnockbackGrowth": "100",
    "MoveType": "aerial",
    "IsWeightDependent": false,
    "Links": [
      {
        "Rel": "self",
        "Href": "http://beta-api-kuroganehammer.azurewebsites.net/api/moves/598e3ffc46965919a42805e0"
      },
      {
        "Rel": "character",
        "Href": "http://beta-api-kuroganehammer.azurewebsites.net/api/characters/name/Villager"
      }
    ]
  },
  {
    "InstanceId": "598e3ffc46965919a42805e1",
    "Name": "Uair (Single)",
    "OwnerId": 53,
    "Owner": "Villager",
    "HitboxActive": "6-7",
    "FirstActionableFrame": "-",
    "BaseDamage": "8",
    "Angle": "85",
    "BaseKnockBackSetKnockback": "30",
    "LandingLag": "-",
    "AutoCancel": "-",
    "KnockbackGrowth": "100",
    "MoveType": "aerial",
    "IsWeightDependent": false,
    "Links": [
      {
        "Rel": "self",
        "Href": "http://beta-api-kuroganehammer.azurewebsites.net/api/moves/598e3ffc46965919a42805e1"
      },
      {
        "Rel": "character",
        "Href": "http://beta-api-kuroganehammer.azurewebsites.net/api/characters/name/Villager"
      }
    ]
  },
  {
    "InstanceId": "598e3ffc46965919a42805e2",
    "Name": "Uair (Single, Late)",
    "OwnerId": 53,
    "Owner": "Villager",
    "HitboxActive": "8-31",
    "FirstActionableFrame": "-",
    "BaseDamage": "4",
    "Angle": "85",
    "BaseKnockBackSetKnockback": "30",
    "LandingLag": "-",
    "AutoCancel": "-",
    "KnockbackGrowth": "100",
    "MoveType": "aerial",
    "IsWeightDependent": false,
    "Links": [
      {
        "Rel": "self",
        "Href": "http://beta-api-kuroganehammer.azurewebsites.net/api/moves/598e3ffc46965919a42805e2"
      },
      {
        "Rel": "character",
        "Href": "http://beta-api-kuroganehammer.azurewebsites.net/api/characters/name/Villager"
      }
    ]
  },
  {
    "InstanceId": "598e3ffc46965919a42805e3",
    "Name": "Dair (Triple)",
    "OwnerId": 53,
    "Owner": "Villager",
    "HitboxActive": "8-9",
    "FirstActionableFrame": "46",
    "BaseDamage": "13",
    "Angle": "270/45",
    "BaseKnockBackSetKnockback": "20/30",
    "LandingLag": "15",
    "AutoCancel": "1-7, 39&gt;",
    "KnockbackGrowth": "80/100",
    "MoveType": "aerial",
    "IsWeightDependent": false,
    "Links": [
      {
        "Rel": "self",
        "Href": "http://beta-api-kuroganehammer.azurewebsites.net/api/moves/598e3ffc46965919a42805e3"
      },
      {
        "Rel": "character",
        "Href": "http://beta-api-kuroganehammer.azurewebsites.net/api/characters/name/Villager"
      }
    ]
  },
  {
    "InstanceId": "598e3ffc46965919a42805e4",
    "Name": "Dair (Triple, Late)",
    "OwnerId": 53,
    "Owner": "Villager",
    "HitboxActive": "10-31",
    "FirstActionableFrame": "-",
    "BaseDamage": "6",
    "Angle": "45",
    "BaseKnockBackSetKnockback": "30",
    "LandingLag": "-",
    "AutoCancel": "-",
    "KnockbackGrowth": "100",
    "MoveType": "aerial",
    "IsWeightDependent": false,
    "Links": [
      {
        "Rel": "self",
        "Href": "http://beta-api-kuroganehammer.azurewebsites.net/api/moves/598e3ffc46965919a42805e4"
      },
      {
        "Rel": "character",
        "Href": "http://beta-api-kuroganehammer.azurewebsites.net/api/characters/name/Villager"
      }
    ]
  },
  {
    "InstanceId": "598e3ffc46965919a42805e5",
    "Name": "Dair (Double)",
    "OwnerId": 53,
    "Owner": "Villager",
    "HitboxActive": "8-9",
    "FirstActionableFrame": "-",
    "BaseDamage": "10",
    "Angle": "45",
    "BaseKnockBackSetKnockback": "30",
    "LandingLag": "-",
    "AutoCancel": "-",
    "KnockbackGrowth": "100",
    "MoveType": "aerial",
    "IsWeightDependent": false,
    "Links": [
      {
        "Rel": "self",
        "Href": "http://beta-api-kuroganehammer.azurewebsites.net/api/moves/598e3ffc46965919a42805e5"
      },
      {
        "Rel": "character",
        "Href": "http://beta-api-kuroganehammer.azurewebsites.net/api/characters/name/Villager"
      }
    ]
  },
  {
    "InstanceId": "598e3ffc46965919a42805e6",
    "Name": "Dair (Double, Late)",
    "OwnerId": 53,
    "Owner": "Villager",
    "HitboxActive": "10-31",
    "FirstActionableFrame": "-",
    "BaseDamage": "5",
    "Angle": "45",
    "BaseKnockBackSetKnockback": "30",
    "LandingLag": "-",
    "AutoCancel": "-",
    "KnockbackGrowth": "100",
    "MoveType": "aerial",
    "IsWeightDependent": false,
    "Links": [
      {
        "Rel": "self",
        "Href": "http://beta-api-kuroganehammer.azurewebsites.net/api/moves/598e3ffc46965919a42805e6"
      },
      {
        "Rel": "character",
        "Href": "http://beta-api-kuroganehammer.azurewebsites.net/api/characters/name/Villager"
      }
    ]
  },
  {
    "InstanceId": "598e3ffc46965919a42805e7",
    "Name": "Dair (Single)",
    "OwnerId": 53,
    "Owner": "Villager",
    "HitboxActive": "8-9",
    "FirstActionableFrame": "-",
    "BaseDamage": "8",
    "Angle": "45",
    "BaseKnockBackSetKnockback": "30",
    "LandingLag": "-",
    "AutoCancel": "-",
    "KnockbackGrowth": "100",
    "MoveType": "aerial",
    "IsWeightDependent": false,
    "Links": [
      {
        "Rel": "self",
        "Href": "http://beta-api-kuroganehammer.azurewebsites.net/api/moves/598e3ffc46965919a42805e7"
      },
      {
        "Rel": "character",
        "Href": "http://beta-api-kuroganehammer.azurewebsites.net/api/characters/name/Villager"
      }
    ]
  },
  {
    "InstanceId": "598e3ffc46965919a42805e8",
    "Name": "Dair (Single, Late)",
    "OwnerId": 53,
    "Owner": "Villager",
    "HitboxActive": "10-31",
    "FirstActionableFrame": "-",
    "BaseDamage": "4",
    "Angle": "45",
    "BaseKnockBackSetKnockback": "30",
    "LandingLag": "-",
    "AutoCancel": "-",
    "KnockbackGrowth": "100",
    "MoveType": "aerial",
    "IsWeightDependent": false,
    "Links": [
      {
        "Rel": "self",
        "Href": "http://beta-api-kuroganehammer.azurewebsites.net/api/moves/598e3ffc46965919a42805e8"
      },
      {
        "Rel": "character",
        "Href": "http://beta-api-kuroganehammer.azurewebsites.net/api/characters/name/Villager"
      }
    ]
  },
  {
    "InstanceId": "598e3ffc46965919a42805e9",
    "Name": "Pocket",
    "OwnerId": 53,
    "Owner": "Villager",
    "HitboxActive": "Grabs: 8- (Intangible: 5-23)",
    "FirstActionableFrame": "51",
    "BaseDamage": "-",
    "Angle": "-",
    "BaseKnockBackSetKnockback": "-",
    "LandingLag": null,
    "AutoCancel": null,
    "KnockbackGrowth": "-",
    "MoveType": "special",
    "IsWeightDependent": false,
    "Links": [
      {
        "Rel": "self",
        "Href": "http://beta-api-kuroganehammer.azurewebsites.net/api/moves/598e3ffc46965919a42805e9"
      },
      {
        "Rel": "character",
        "Href": "http://beta-api-kuroganehammer.azurewebsites.net/api/characters/name/Villager"
      }
    ]
  },
  {
    "InstanceId": "598e3ffc46965919a42805ea",
    "Name": "Lloid Rocket",
    "OwnerId": 53,
    "Owner": "Villager",
    "HitboxActive": "52-",
    "FirstActionableFrame": "38",
    "BaseDamage": "7",
    "Angle": "55",
    "BaseKnockBackSetKnockback": "30",
    "LandingLag": null,
    "AutoCancel": null,
    "KnockbackGrowth": "100",
    "MoveType": "special",
    "IsWeightDependent": false,
    "Links": [
      {
        "Rel": "self",
        "Href": "http://beta-api-kuroganehammer.azurewebsites.net/api/moves/598e3ffc46965919a42805ea"
      },
      {
        "Rel": "character",
        "Href": "http://beta-api-kuroganehammer.azurewebsites.net/api/characters/name/Villager"
      }
    ]
  },
  {
    "InstanceId": "598e3ffc46965919a42805eb",
    "Name": "Lloid Rocket (Late)",
    "OwnerId": 53,
    "Owner": "Villager",
    "HitboxActive": "?",
    "FirstActionableFrame": "-",
    "BaseDamage": "5",
    "Angle": "361",
    "BaseKnockBackSetKnockback": "20",
    "LandingLag": null,
    "AutoCancel": null,
    "KnockbackGrowth": "80",
    "MoveType": "special",
    "IsWeightDependent": false,
    "Links": [
      {
        "Rel": "self",
        "Href": "http://beta-api-kuroganehammer.azurewebsites.net/api/moves/598e3ffc46965919a42805eb"
      },
      {
        "Rel": "character",
        "Href": "http://beta-api-kuroganehammer.azurewebsites.net/api/characters/name/Villager"
      }
    ]
  },
  {
    "InstanceId": "598e3ffc46965919a42805ec",
    "Name": "Lloid Rocket (Ride)",
    "OwnerId": 53,
    "Owner": "Villager",
    "HitboxActive": "-",
    "FirstActionableFrame": "-",
    "BaseDamage": "16",
    "Angle": "-",
    "BaseKnockBackSetKnockback": "-",
    "LandingLag": null,
    "AutoCancel": null,
    "KnockbackGrowth": "-",
    "MoveType": "special",
    "IsWeightDependent": false,
    "Links": [
      {
        "Rel": "self",
        "Href": "http://beta-api-kuroganehammer.azurewebsites.net/api/moves/598e3ffc46965919a42805ec"
      },
      {
        "Rel": "character",
        "Href": "http://beta-api-kuroganehammer.azurewebsites.net/api/characters/name/Villager"
      }
    ]
  },
  {
    "InstanceId": "598e3ffc46965919a42805ed",
    "Name": "Lloid Rocket (Ride, Late)",
    "OwnerId": 53,
    "Owner": "Villager",
    "HitboxActive": "-",
    "FirstActionableFrame": "-",
    "BaseDamage": "11",
    "Angle": "-",
    "BaseKnockBackSetKnockback": "-",
    "LandingLag": null,
    "AutoCancel": null,
    "KnockbackGrowth": "-",
    "MoveType": "special",
    "IsWeightDependent": false,
    "Links": [
      {
        "Rel": "self",
        "Href": "http://beta-api-kuroganehammer.azurewebsites.net/api/moves/598e3ffc46965919a42805ed"
      },
      {
        "Rel": "character",
        "Href": "http://beta-api-kuroganehammer.azurewebsites.net/api/characters/name/Villager"
      }
    ]
  },
  {
    "InstanceId": "598e3ffc46965919a42805ee",
    "Name": "Balloon Trip",
    "OwnerId": 53,
    "Owner": "Villager",
    "HitboxActive": "-",
    "FirstActionableFrame": "-",
    "BaseDamage": "-",
    "Angle": "-",
    "BaseKnockBackSetKnockback": "-",
    "LandingLag": null,
    "AutoCancel": null,
    "KnockbackGrowth": "-",
    "MoveType": "special",
    "IsWeightDependent": false,
    "Links": [
      {
        "Rel": "self",
        "Href": "http://beta-api-kuroganehammer.azurewebsites.net/api/moves/598e3ffc46965919a42805ee"
      },
      {
        "Rel": "character",
        "Href": "http://beta-api-kuroganehammer.azurewebsites.net/api/characters/name/Villager"
      }
    ]
  },
  {
    "InstanceId": "598e3ffc46965919a42805ef",
    "Name": "Timber (Planting)",
    "OwnerId": 53,
    "Owner": "Villager",
    "HitboxActive": "Planted on:",
    "FirstActionableFrame": "44",
    "BaseDamage": "-",
    "Angle": "-",
    "BaseKnockBackSetKnockback": "-",
    "LandingLag": null,
    "AutoCancel": null,
    "KnockbackGrowth": "-",
    "MoveType": "special",
    "IsWeightDependent": false,
    "Links": [
      {
        "Rel": "self",
        "Href": "http://beta-api-kuroganehammer.azurewebsites.net/api/moves/598e3ffc46965919a42805ef"
      },
      {
        "Rel": "character",
        "Href": "http://beta-api-kuroganehammer.azurewebsites.net/api/characters/name/Villager"
      }
    ]
  },
  {
    "InstanceId": "598e3ffc46965919a42805f0",
    "Name": "Timber (Watering Can)",
    "OwnerId": 53,
    "Owner": "Villager",
    "HitboxActive": "-",
    "FirstActionableFrame": "55",
    "BaseDamage": "0",
    "Angle": "55",
    "BaseKnockBackSetKnockback": "W: 60",
    "LandingLag": null,
    "AutoCancel": null,
    "KnockbackGrowth": "100",
    "MoveType": "special",
    "IsWeightDependent": false,
    "Links": [
      {
        "Rel": "self",
        "Href": "http://beta-api-kuroganehammer.azurewebsites.net/api/moves/598e3ffc46965919a42805f0"
      },
      {
        "Rel": "character",
        "Href": "http://beta-api-kuroganehammer.azurewebsites.net/api/characters/name/Villager"
      }
    ]
  },
  {
    "InstanceId": "598e3ffc46965919a42805f1",
    "Name": "Timber (Axe)",
    "OwnerId": 53,
    "Owner": "Villager",
    "HitboxActive": "6-8",
    "FirstActionableFrame": "48",
    "BaseDamage": "14 (+6)",
    "Angle": "361",
    "BaseKnockBackSetKnockback": "30",
    "LandingLag": null,
    "AutoCancel": null,
    "KnockbackGrowth": "100",
    "MoveType": "special",
    "IsWeightDependent": false,
    "Links": [
      {
        "Rel": "self",
        "Href": "http://beta-api-kuroganehammer.azurewebsites.net/api/moves/598e3ffc46965919a42805f1"
      },
      {
        "Rel": "character",
        "Href": "http://beta-api-kuroganehammer.azurewebsites.net/api/characters/name/Villager"
      }
    ]
  },
  {
    "InstanceId": "598e3ffc46965919a42805f2",
    "Name": "Timber (Chop)",
    "OwnerId": 53,
    "Owner": "Villager",
    "HitboxActive": "-",
    "FirstActionableFrame": "51",
    "BaseDamage": "-",
    "Angle": "-",
    "BaseKnockBackSetKnockback": "-",
    "LandingLag": null,
    "AutoCancel": null,
    "KnockbackGrowth": "-",
    "MoveType": "special",
    "IsWeightDependent": false,
    "Links": [
      {
        "Rel": "self",
        "Href": "http://beta-api-kuroganehammer.azurewebsites.net/api/moves/598e3ffc46965919a42805f2"
      },
      {
        "Rel": "character",
        "Href": "http://beta-api-kuroganehammer.azurewebsites.net/api/characters/name/Villager"
      }
    ]
  },
  {
    "InstanceId": "598e3ffc46965919a42805f3",
    "Name": "Timber (Growing)",
    "OwnerId": 53,
    "Owner": "Villager",
    "HitboxActive": "13-18 (Low Priority)",
    "FirstActionableFrame": "-",
    "BaseDamage": "18 (+6)",
    "Angle": "80",
    "BaseKnockBackSetKnockback": "30",
    "LandingLag": null,
    "AutoCancel": null,
    "KnockbackGrowth": "100",
    "MoveType": "special",
    "IsWeightDependent": false,
    "Links": [
      {
        "Rel": "self",
        "Href": "http://beta-api-kuroganehammer.azurewebsites.net/api/moves/598e3ffc46965919a42805f3"
      },
      {
        "Rel": "character",
        "Href": "http://beta-api-kuroganehammer.azurewebsites.net/api/characters/name/Villager"
      }
    ]
  },
  {
    "InstanceId": "598e3ffc46965919a42805f4",
    "Name": "Timber (Growing, Late)",
    "OwnerId": 53,
    "Owner": "Villager",
    "HitboxActive": "19-39 (Low Priority)",
    "FirstActionableFrame": "-",
    "BaseDamage": "13 (+6)",
    "Angle": "80",
    "BaseKnockBackSetKnockback": "30",
    "LandingLag": null,
    "AutoCancel": null,
    "KnockbackGrowth": "100",
    "MoveType": "special",
    "IsWeightDependent": false,
    "Links": [
      {
        "Rel": "self",
        "Href": "http://beta-api-kuroganehammer.azurewebsites.net/api/moves/598e3ffc46965919a42805f4"
      },
      {
        "Rel": "character",
        "Href": "http://beta-api-kuroganehammer.azurewebsites.net/api/characters/name/Villager"
      }
    ]
  },
  {
    "InstanceId": "598e3ffc46965919a42805f5",
    "Name": "Timber (Falling)",
    "OwnerId": 53,
    "Owner": "Villager",
    "HitboxActive": "14- (Low Priority)",
    "FirstActionableFrame": "-",
    "BaseDamage": "25 (+6)",
    "Angle": "60",
    "BaseKnockBackSetKnockback": "30",
    "LandingLag": null,
    "AutoCancel": null,
    "KnockbackGrowth": "100",
    "MoveType": "special",
    "IsWeightDependent": false,
    "Links": [
      {
        "Rel": "self",
        "Href": "http://beta-api-kuroganehammer.azurewebsites.net/api/moves/598e3ffc46965919a42805f5"
      },
      {
        "Rel": "character",
        "Href": "http://beta-api-kuroganehammer.azurewebsites.net/api/characters/name/Villager"
      }
    ]
  },
  {
    "InstanceId": "598e3ffc46965919a42805f6",
    "Name": "Fthrow",
    "OwnerId": 53,
    "Owner": "Villager",
    "HitboxActive": null,
    "FirstActionableFrame": null,
    "BaseDamage": "9",
    "Angle": "45",
    "BaseKnockBackSetKnockback": "102",
    "LandingLag": null,
    "AutoCancel": null,
    "KnockbackGrowth": "10",
    "MoveType": "throw",
    "IsWeightDependent": true,
    "Links": [
      {
        "Rel": "self",
        "Href": "http://beta-api-kuroganehammer.azurewebsites.net/api/moves/598e3ffc46965919a42805f6"
      },
      {
        "Rel": "character",
        "Href": "http://beta-api-kuroganehammer.azurewebsites.net/api/characters/name/Villager"
      }
    ]
  },
  {
    "InstanceId": "598e3ffc46965919a42805f7",
    "Name": "Bthrow",
    "OwnerId": 53,
    "Owner": "Villager",
    "HitboxActive": null,
    "FirstActionableFrame": null,
    "BaseDamage": "11",
    "Angle": "135",
    "BaseKnockBackSetKnockback": "18",
    "LandingLag": null,
    "AutoCancel": null,
    "KnockbackGrowth": "110",
    "MoveType": "throw",
    "IsWeightDependent": true,
    "Links": [
      {
        "Rel": "self",
        "Href": "http://beta-api-kuroganehammer.azurewebsites.net/api/moves/598e3ffc46965919a42805f7"
      },
      {
        "Rel": "character",
        "Href": "http://beta-api-kuroganehammer.azurewebsites.net/api/characters/name/Villager"
      }
    ]
  },
  {
    "InstanceId": "598e3ffc46965919a42805f8",
    "Name": "Uthrow",
    "OwnerId": 53,
    "Owner": "Villager",
    "HitboxActive": null,
    "FirstActionableFrame": null,
    "BaseDamage": "10",
    "Angle": "90",
    "BaseKnockBackSetKnockback": "105",
    "LandingLag": null,
    "AutoCancel": null,
    "KnockbackGrowth": "40",
    "MoveType": "throw",
    "IsWeightDependent": true,
    "Links": [
      {
        "Rel": "self",
        "Href": "http://beta-api-kuroganehammer.azurewebsites.net/api/moves/598e3ffc46965919a42805f8"
      },
      {
        "Rel": "character",
        "Href": "http://beta-api-kuroganehammer.azurewebsites.net/api/characters/name/Villager"
      }
    ]
  },
  {
    "InstanceId": "598e3ffc46965919a42805f9",
    "Name": "Dthrow",
    "OwnerId": 53,
    "Owner": "Villager",
    "HitboxActive": null,
    "FirstActionableFrame": null,
    "BaseDamage": "6",
    "Angle": "70",
    "BaseKnockBackSetKnockback": "60",
    "LandingLag": null,
    "AutoCancel": null,
    "KnockbackGrowth": "80",
    "MoveType": "throw",
    "IsWeightDependent": true,
    "Links": [
      {
        "Rel": "self",
        "Href": "http://beta-api-kuroganehammer.azurewebsites.net/api/moves/598e3ffc46965919a42805f9"
      },
      {
        "Rel": "character",
        "Href": "http://beta-api-kuroganehammer.azurewebsites.net/api/characters/name/Villager"
      }
    ]
  }
]