[
  {
    "InstanceId": "59716e304696592eec783c62",
    "Name": "Weight",
    "OwnerId": 16,
    "Owner": "Greninja",
    "Value": "94 ",
    "Links": [
      {
        "Rel": "self",
        "Href": "http://beta-api-kuroganehammer.azurewebsites.net/api/movements/59716e304696592eec783c62"
      },
      {
        "Rel": "character",
        "Href": "http://beta-api-kuroganehammer.azurewebsites.net/api/characters/name/Greninja"
      }
    ]
  },
  {
    "InstanceId": "59716e304696592eec783c63",
    "Name": "Max Jumps",
    "OwnerId": 16,
    "Owner": "Greninja",
    "Value": "2",
    "Links": [
      {
        "Rel": "self",
        "Href": "http://beta-api-kuroganehammer.azurewebsites.net/api/movements/59716e304696592eec783c63"
      },
      {
        "Rel": "character",
        "Href": "http://beta-api-kuroganehammer.azurewebsites.net/api/characters/name/Greninja"
      }
    ]
  },
  {
    "InstanceId": "59716e304696592eec783c64",
    "Name": "Run Speed",
    "OwnerId": 16,
    "Owner": "Greninja",
    "Value": "2.08 ",
    "Links": [
      {
        "Rel": "self",
        "Href": "http://beta-api-kuroganehammer.azurewebsites.net/api/movements/59716e304696592eec783c64"
      },
      {
        "Rel": "character",
        "Href": "http://beta-api-kuroganehammer.azurewebsites.net/api/characters/name/Greninja"
      }
    ]
  },
  {
    "InstanceId": "59716e304696592eec783c65",
    "Name": "Wall Jump",
    "OwnerId": 16,
    "Owner": "Greninja",
    "Value": "Yes",
    "Links": [
      {
        "Rel": "self",
        "Href": "http://beta-api-kuroganehammer.azurewebsites.net/api/movements/59716e304696592eec783c65"
      },
      {
        "Rel": "character",
        "Href": "http://beta-api-kuroganehammer.azurewebsites.net/api/characters/name/Greninja"
      }
    ]
  },
  {
    "InstanceId": "59716e304696592eec783c66",
    "Name": "Walk Speed",
    "OwnerId": 16,
    "Owner": "Greninja",
    "Value": "1.43 ",
    "Links": [
      {
        "Rel": "self",
        "Href": "http://beta-api-kuroganehammer.azurewebsites.net/api/movements/59716e304696592eec783c66"
      },
      {
        "Rel": "character",
        "Href": "http://beta-api-kuroganehammer.azurewebsites.net/api/characters/name/Greninja"
      }
    ]
  },
  {
    "InstanceId": "59716e304696592eec783c67",
    "Name": "Wall Cling",
    "OwnerId": 16,
    "Owner": "Greninja",
    "Value": "Yes",
    "Links": [
      {
        "Rel": "self",
        "Href": "http://beta-api-kuroganehammer.azurewebsites.net/api/movements/59716e304696592eec783c67"
      },
      {
        "Rel": "character",
        "Href": "http://beta-api-kuroganehammer.azurewebsites.net/api/characters/name/Greninja"
      }
    ]
  },
  {
    "InstanceId": "59716e304696592eec783c68",
    "Name": "Air Speed",
    "OwnerId": 16,
    "Owner": "Greninja",
    "Value": "1.18 ",
    "Links": [
      {
        "Rel": "self",
        "Href": "http://beta-api-kuroganehammer.azurewebsites.net/api/movements/59716e304696592eec783c68"
      },
      {
        "Rel": "character",
        "Href": "http://beta-api-kuroganehammer.azurewebsites.net/api/characters/name/Greninja"
      }
    ]
  },
  {
    "InstanceId": "59716e304696592eec783c69",
    "Name": "Crawl",
    "OwnerId": 16,
    "Owner": "Greninja",
    "Value": "Yes",
    "Links": [
      {
        "Rel": "self",
        "Href": "http://beta-api-kuroganehammer.azurewebsites.net/api/movements/59716e304696592eec783c69"
      },
      {
        "Rel": "character",
        "Href": "http://beta-api-kuroganehammer.azurewebsites.net/api/characters/name/Greninja"
      }
    ]
  },
  {
    "InstanceId": "59716e304696592eec783c6a",
    "Name": "Fall Speed",
    "OwnerId": 16,
    "Owner": "Greninja",
    "Value": "1.85 ",
    "Links": [
      {
        "Rel": "self",
        "Href": "http://beta-api-kuroganehammer.azurewebsites.net/api/movements/59716e304696592eec783c6a"
      },
      {
        "Rel": "character",
        "Href": "http://beta-api-kuroganehammer.azurewebsites.net/api/characters/name/Greninja"
      }
    ]
  },
  {
    "InstanceId": "59716e304696592eec783c6b",
    "Name": "Tether",
    "OwnerId": 16,
    "Owner": "Greninja",
    "Value": "No",
    "Links": [
      {
        "Rel": "self",
        "Href": "http://beta-api-kuroganehammer.azurewebsites.net/api/movements/59716e304696592eec783c6b"
      },
      {
        "Rel": "character",
        "Href": "http://beta-api-kuroganehammer.azurewebsites.net/api/characters/name/Greninja"
      }
    ]
  },
  {
    "InstanceId": "59716e304696592eec783c6c",
    "Name": "Fast Fall Speed",
    "OwnerId": 16,
    "Owner": "Greninja",
    "Value": "2.96 ",
    "Links": [
      {
        "Rel": "self",
        "Href": "http://beta-api-kuroganehammer.azurewebsites.net/api/movements/59716e304696592eec783c6c"
      },
      {
        "Rel": "character",
        "Href": "http://beta-api-kuroganehammer.azurewebsites.net/api/characters/name/Greninja"
      }
    ]
  },
  {
    "InstanceId": "59716e304696592eec783c6d",
    "Name": "Jumpsquat",
    "OwnerId": 16,
    "Owner": "Greninja",
    "Value": "4 frames",
    "Links": [
      {
        "Rel": "self",
        "Href": "http://beta-api-kuroganehammer.azurewebsites.net/api/movements/59716e304696592eec783c6d"
      },
      {
        "Rel": "character",
        "Href": "http://beta-api-kuroganehammer.azurewebsites.net/api/characters/name/Greninja"
      }
    ]
  },
  {
    "InstanceId": "59716e304696592eec783c6e",
    "Name": "Air Acceleration",
    "OwnerId": 16,
    "Owner": "Greninja",
    "Value": "0.07",
    "Links": [
      {
        "Rel": "self",
        "Href": "http://beta-api-kuroganehammer.azurewebsites.net/api/movements/59716e304696592eec783c6e"
      },
      {
        "Rel": "character",
        "Href": "http://beta-api-kuroganehammer.azurewebsites.net/api/characters/name/Greninja"
      }
    ]
  },
  {
    "InstanceId": "59716e304696592eec783c6f",
    "Name": "Soft Landing Lag",
    "OwnerId": 16,
    "Owner": "Greninja",
    "Value": "2 frames",
    "Links": [
      {
        "Rel": "self",
        "Href": "http://beta-api-kuroganehammer.azurewebsites.net/api/movements/59716e304696592eec783c6f"
      },
      {
        "Rel": "character",
        "Href": "http://beta-api-kuroganehammer.azurewebsites.net/api/characters/name/Greninja"
      }
    ]
  },
  {
    "InstanceId": "59716e304696592eec783c70",
    "Name": "Gravity",
    "OwnerId": 16,
    "Owner": "Greninja",
    "Value": "0.18",
    "Links": [
      {
        "Rel": "self",
        "Href": "http://beta-api-kuroganehammer.azurewebsites.net/api/movements/59716e304696592eec783c70"
      },
      {
        "Rel": "character",
        "Href": "http://beta-api-kuroganehammer.azurewebsites.net/api/characters/name/Greninja"
      }
    ]
  },
  {
    "InstanceId": "59716e304696592eec783c71",
    "Name": "Hard Landing Lag",
    "OwnerId": 16,
    "Owner": "Greninja",
    "Value": "4 frames",
    "Links": [
      {
        "Rel": "self",
        "Href": "http://beta-api-kuroganehammer.azurewebsites.net/api/movements/59716e304696592eec783c71"
      },
      {
        "Rel": "character",
        "Href": "http://beta-api-kuroganehammer.azurewebsites.net/api/characters/name/Greninja"
      }
    ]
  },
  {
    "InstanceId": "59716e304696592eec783c72",
    "Name": "SH Air Time",
    "OwnerId": 16,
    "Owner": "Greninja",
    "Value": "32 frames",
    "Links": [
      {
        "Rel": "self",
        "Href": "http://beta-api-kuroganehammer.azurewebsites.net/api/movements/59716e304696592eec783c72"
      },
      {
        "Rel": "character",
        "Href": "http://beta-api-kuroganehammer.azurewebsites.net/api/characters/name/Greninja"
      }
    ]
  },
  {
    "InstanceId": "59716e304696592eec783c73",
    "Name": "FH Air Time",
    "OwnerId": 16,
    "Owner": "Greninja",
    "Value": "52 frames",
    "Links": [
      {
        "Rel": "self",
        "Href": "http://beta-api-kuroganehammer.azurewebsites.net/api/movements/59716e304696592eec783c73"
      },
      {
        "Rel": "character",
        "Href": "http://beta-api-kuroganehammer.azurewebsites.net/api/characters/name/Greninja"
      }
    ]
  }
]