[
  {
    "InstanceId": "5970245746965900ac9f9ba2",
    "Name": "AerialJump",
    "OwnerId": 7,
    "Owner": "Corrin",
    "Values": [
      {
        "Value": "31",
        "Owner": "Corrin",
        "OwnerId": 7,
        "Name": "HEIGHT"
      }
    ],
    "Links": [
      {
        "Rel": "self",
        "Href": "http://beta-api-kuroganehammer.azurewebsites.net/api/characterattributes/5970245746965900ac9f9ba2"
      },
      {
        "Rel": "character",
        "Href": "http://beta-api-kuroganehammer.azurewebsites.net/api/characters/name/Corrin"
      }
    ]
  },
  {
    "InstanceId": "5970245746965900ac9f9ba3",
    "Name": "Counters",
    "OwnerId": 7,
    "Owner": "Corrin",
    "Values": [
      {
        "Value": "7-24",
        "Owner": "Corrin",
        "OwnerId": 7,
        "Name": "COUNTER FRAMES"
      },
      {
        "Value": "6-7",
        "Owner": "Corrin",
        "OwnerId": 7,
        "Name": "INTANGIBLE ON"
      },
      {
        "Value": "64",
        "Owner": "Corrin",
        "OwnerId": 7,
        "Name": "FAF"
      },
      {
        "Value": "1.2&#215;",
        "Owner": "Corrin",
        "OwnerId": 7,
        "Name": "DAMAGE (MULTIPLIER)"
      },
      {
        "Value": "90 | 74",
        "Owner": "Corrin",
        "OwnerId": 7,
        "Name": "BKB | KBG"
      }
    ],
    "Links": [
      {
        "Rel": "self",
        "Href": "http://beta-api-kuroganehammer.azurewebsites.net/api/characterattributes/5970245746965900ac9f9ba3"
      },
      {
        "Rel": "character",
        "Href": "http://beta-api-kuroganehammer.azurewebsites.net/api/characters/name/Corrin"
      }
    ]
  },
  {
    "InstanceId": "5970245746965900ac9f9ba4",
    "Name": "AirAcceleration",
    "OwnerId": 7,
    "Owner": "Corrin",
    "Values": [
      {
        "Value": "0.04",
        "Owner": "Corrin",
        "OwnerId": 7,
        "Name": "VALUE"
      }
    ],
    "Links": [
      {
        "Rel": "self",
        "Href": "http://beta-api-kuroganehammer.azurewebsites.net/api/characterattributes/5970245746965900ac9f9ba4"
      },
      {
        "Rel": "character",
        "Href": "http://beta-api-kuroganehammer.azurewebsites.net/api/characters/name/Corrin"
      }
    ]
  },
  {
    "InstanceId": "5970245746965900ac9f9ba5",
    "Name": "AirDeceleration",
    "OwnerId": 7,
    "Owner": "Corrin",
    "Values": [
      {
        "Value": "0.01",
        "Owner": "Corrin",
        "OwnerId": 7,
        "Name": "VALUE"
      }
    ],
    "Links": [
      {
        "Rel": "self",
        "Href": "http://beta-api-kuroganehammer.azurewebsites.net/api/characterattributes/5970245746965900ac9f9ba5"
      },
      {
        "Rel": "character",
        "Href": "http://beta-api-kuroganehammer.azurewebsites.net/api/characters/name/Corrin"
      }
    ]
  },
  {
    "InstanceId": "5970245746965900ac9f9ba6",
    "Name": "AirFriction",
    "OwnerId": 7,
    "Owner": "Corrin",
    "Values": [
      {
        "Value": "0.009",
        "Owner": "Corrin",
        "OwnerId": 7,
        "Name": "VALUE"
      }
    ],
    "Links": [
      {
        "Rel": "self",
        "Href": "http://beta-api-kuroganehammer.azurewebsites.net/api/characterattributes/5970245746965900ac9f9ba6"
      },
      {
        "Rel": "character",
        "Href": "http://beta-api-kuroganehammer.azurewebsites.net/api/characters/name/Corrin"
      }
    ]
  },
  {
    "InstanceId": "5970245746965900ac9f9ba7",
    "Name": "DashLength",
    "OwnerId": 7,
    "Owner": "Corrin",
    "Values": [
      {
        "Value": "8",
        "Owner": "Corrin",
        "OwnerId": 7,
        "Name": "LENGTH IN FRAMES"
      }
    ],
    "Links": [
      {
        "Rel": "self",
        "Href": "http://beta-api-kuroganehammer.azurewebsites.net/api/characterattributes/5970245746965900ac9f9ba7"
      },
      {
        "Rel": "character",
        "Href": "http://beta-api-kuroganehammer.azurewebsites.net/api/characters/name/Corrin"
      }
    ]
  },
  {
    "InstanceId": "5970245746965900ac9f9ba8",
    "Name": "FallSpeed",
    "OwnerId": 7,
    "Owner": "Corrin",
    "Values": [
      {
        "Value": "1.65",
        "Owner": "Corrin",
        "OwnerId": 7,
        "Name": "MAX FALL SPEED"
      },
      {
        "Value": "2.64",
        "Owner": "Corrin",
        "OwnerId": 7,
        "Name": "FAST FALL SPEED"
      },
      {
        "Value": "60%",
        "Owner": "Corrin",
        "OwnerId": 7,
        "Name": "SPEED INCREASE"
      }
    ],
    "Links": [
      {
        "Rel": "self",
        "Href": "http://beta-api-kuroganehammer.azurewebsites.net/api/characterattributes/5970245746965900ac9f9ba8"
      },
      {
        "Rel": "character",
        "Href": "http://beta-api-kuroganehammer.azurewebsites.net/api/characters/name/Corrin"
      }
    ]
  },
  {
    "InstanceId": "5970245746965900ac9f9ba9",
    "Name": "FullHop",
    "OwnerId": 7,
    "Owner": "Corrin",
    "Values": [
      {
        "Value": "33",
        "Owner": "Corrin",
        "OwnerId": 7,
        "Name": "HEIGHT"
      }
    ],
    "Links": [
      {
        "Rel": "self",
        "Href": "http://beta-api-kuroganehammer.azurewebsites.net/api/characterattributes/5970245746965900ac9f9ba9"
      },
      {
        "Rel": "character",
        "Href": "http://beta-api-kuroganehammer.azurewebsites.net/api/characters/name/Corrin"
      }
    ]
  },
  {
    "InstanceId": "5970245746965900ac9f9baa",
    "Name": "Gravity",
    "OwnerId": 7,
    "Owner": "Corrin",
    "Values": [
      {
        "Value": "0.092",
        "Owner": "Corrin",
        "OwnerId": 7,
        "Name": "VALUE"
      }
    ],
    "Links": [
      {
        "Rel": "self",
        "Href": "http://beta-api-kuroganehammer.azurewebsites.net/api/characterattributes/5970245746965900ac9f9baa"
      },
      {
        "Rel": "character",
        "Href": "http://beta-api-kuroganehammer.azurewebsites.net/api/characters/name/Corrin"
      }
    ]
  },
  {
    "InstanceId": "5970245746965900ac9f9bab",
    "Name": "JumpSquat",
    "OwnerId": 7,
    "Owner": "Corrin",
    "Values": [
      {
        "Value": "6",
        "Owner": "Corrin",
        "OwnerId": 7,
        "Name": "VALUE"
      }
    ],
    "Links": [
      {
        "Rel": "self",
        "Href": "http://beta-api-kuroganehammer.azurewebsites.net/api/characterattributes/5970245746965900ac9f9bab"
      },
      {
        "Rel": "character",
        "Href": "http://beta-api-kuroganehammer.azurewebsites.net/api/characters/name/Corrin"
      }
    ]
  },
  {
    "InstanceId": "5970245746965900ac9f9bac",
    "Name": "LedgeHop",
    "OwnerId": 7,
    "Owner": "Corrin",
    "Values": [
      {
        "Value": "36.5",
        "Owner": "Corrin",
        "OwnerId": 7,
        "Name": "HEIGHT"
      }
    ],
    "Links": [
      {
        "Rel": "self",
        "Href": "http://beta-api-kuroganehammer.azurewebsites.net/api/characterattributes/5970245746965900ac9f9bac"
      },
      {
        "Rel": "character",
        "Href": "http://beta-api-kuroganehammer.azurewebsites.net/api/characters/name/Corrin"
      }
    ]
  },
  {
    "InstanceId": "5970245746965900ac9f9bad",
    "Name": "ShortHop",
    "OwnerId": 7,
    "Owner": "Corrin",
    "Values": [
      {
        "Value": "16",
        "Owner": "Corrin",
        "OwnerId": 7,
        "Name": "HEIGHT"
      }
    ],
    "Links": [
      {
        "Rel": "self",
        "Href": "http://beta-api-kuroganehammer.azurewebsites.net/api/characterattributes/5970245746965900ac9f9bad"
      },
      {
        "Rel": "character",
        "Href": "http://beta-api-kuroganehammer.azurewebsites.net/api/characters/name/Corrin"
      }
    ]
  },
  {
    "InstanceId": "5970245746965900ac9f9bae",
    "Name": "Spotdodge",
    "OwnerId": 7,
    "Owner": "Corrin",
    "Values": [
      {
        "Value": "3-17",
        "Owner": "Corrin",
        "OwnerId": 7,
        "Name": "INTANGIBLE"
      },
      {
        "Value": "27",
        "Owner": "Corrin",
        "OwnerId": 7,
        "Name": "FAF"
      }
    ],
    "Links": [
      {
        "Rel": "self",
        "Href": "http://beta-api-kuroganehammer.azurewebsites.net/api/characterattributes/5970245746965900ac9f9bae"
      },
      {
        "Rel": "character",
        "Href": "http://beta-api-kuroganehammer.azurewebsites.net/api/characters/name/Corrin"
      }
    ]
  },
  {
    "InstanceId": "5970245746965900ac9f9baf",
    "Name": "Traction",
    "OwnerId": 7,
    "Owner": "Corrin",
    "Values": [
      {
        "Value": "0.065",
        "Owner": "Corrin",
        "OwnerId": 7,
        "Name": "VALUE"
      }
    ],
    "Links": [
      {
        "Rel": "self",
        "Href": "http://beta-api-kuroganehammer.azurewebsites.net/api/characterattributes/5970245746965900ac9f9baf"
      },
      {
        "Rel": "character",
        "Href": "http://beta-api-kuroganehammer.azurewebsites.net/api/characters/name/Corrin"
      }
    ]
  },
  {
    "InstanceId": "5970245746965900ac9f9bb0",
    "Name": "WalkSpeed",
    "OwnerId": 7,
    "Owner": "Corrin",
    "Values": [
      {
        "Value": "1.15",
        "Owner": "Corrin",
        "OwnerId": 7,
        "Name": "MAX WALK SPEED VALUE"
      }
    ],
    "Links": [
      {
        "Rel": "self",
        "Href": "http://beta-api-kuroganehammer.azurewebsites.net/api/characterattributes/5970245746965900ac9f9bb0"
      },
      {
        "Rel": "character",
        "Href": "http://beta-api-kuroganehammer.azurewebsites.net/api/characters/name/Corrin"
      }
    ]
  },
  {
    "InstanceId": "5970245746965900ac9f9bb1",
    "Name": "AirSpeed",
    "OwnerId": 7,
    "Owner": "Corrin",
    "Values": [
      {
        "Value": "0.97",
        "Owner": "Corrin",
        "OwnerId": 7,
        "Name": "MAX AIR SPEED VALUE"
      }
    ],
    "Links": [
      {
        "Rel": "self",
        "Href": "http://beta-api-kuroganehammer.azurewebsites.net/api/characterattributes/5970245746965900ac9f9bb1"
      },
      {
        "Rel": "character",
        "Href": "http://beta-api-kuroganehammer.azurewebsites.net/api/characters/name/Corrin"
      }
    ]
  },
  {
    "InstanceId": "5970245746965900ac9f9bb2",
    "Name": "AirDodge",
    "OwnerId": 7,
    "Owner": "Corrin",
    "Values": [
      {
        "Value": "3-27",
        "Owner": "Corrin",
        "OwnerId": 7,
        "Name": "INTANGIBLE"
      },
      {
        "Value": "33",
        "Owner": "Corrin",
        "OwnerId": 7,
        "Name": "FAF"
      }
    ],
    "Links": [
      {
        "Rel": "self",
        "Href": "http://beta-api-kuroganehammer.azurewebsites.net/api/characterattributes/5970245746965900ac9f9bb2"
      },
      {
        "Rel": "character",
        "Href": "http://beta-api-kuroganehammer.azurewebsites.net/api/characters/name/Corrin"
      }
    ]
  }
]