[
  {
    "InstanceId": "59812ae94696593ccc99ce7e",
    "Name": "Jab 1",
    "OwnerId": 38,
    "Owner": "PAC-MAN",
    "HitboxActive": "4-6",
    "FirstActionableFrame": "20",
    "BaseDamage": "3",
    "Angle": "80/361",
    "BaseKnockBackSetKnockback": "W: 22/16",
    "LandingLag": null,
    "AutoCancel": null,
    "KnockbackGrowth": "100",
    "MoveType": "ground",
    "IsWeightDependent": false,
    "Links": [
      {
        "Rel": "self",
        "Href": "http://beta-api-kuroganehammer.azurewebsites.net/api/moves/59812ae94696593ccc99ce7e"
      },
      {
        "Rel": "character",
        "Href": "http://beta-api-kuroganehammer.azurewebsites.net/api/characters/name/PAC-MAN"
      }
    ]
  },
  {
    "InstanceId": "59812ae94696593ccc99ce7f",
    "Name": "Jab 2",
    "OwnerId": 38,
    "Owner": "PAC-MAN",
    "HitboxActive": "4-6",
    "FirstActionableFrame": "22",
    "BaseDamage": "2",
    "Angle": "80/361",
    "BaseKnockBackSetKnockback": "W: 26/15",
    "LandingLag": null,
    "AutoCancel": null,
    "KnockbackGrowth": "100",
    "MoveType": "ground",
    "IsWeightDependent": false,
    "Links": [
      {
        "Rel": "self",
        "Href": "http://beta-api-kuroganehammer.azurewebsites.net/api/moves/59812ae94696593ccc99ce7f"
      },
      {
        "Rel": "character",
        "Href": "http://beta-api-kuroganehammer.azurewebsites.net/api/characters/name/PAC-MAN"
      }
    ]
  },
  {
    "InstanceId": "59812ae94696593ccc99ce80",
    "Name": "Jab 3",
    "OwnerId": 38,
    "Owner": "PAC-MAN",
    "HitboxActive": "4-7",
    "FirstActionableFrame": "34",
    "BaseDamage": "4",
    "Angle": "361",
    "BaseKnockBackSetKnockback": "45",
    "LandingLag": null,
    "AutoCancel": null,
    "KnockbackGrowth": "106",
    "MoveType": "ground",
    "IsWeightDependent": false,
    "Links": [
      {
        "Rel": "self",
        "Href": "http://beta-api-kuroganehammer.azurewebsites.net/api/moves/59812ae94696593ccc99ce80"
      },
      {
        "Rel": "character",
        "Href": "http://beta-api-kuroganehammer.azurewebsites.net/api/characters/name/PAC-MAN"
      }
    ]
  },
  {
    "InstanceId": "59812ae94696593ccc99ce81",
    "Name": "Dash Attack (Windbox)",
    "OwnerId": 38,
    "Owner": "PAC-MAN",
    "HitboxActive": "3-9",
    "FirstActionableFrame": "42",
    "BaseDamage": "0",
    "Angle": "361",
    "BaseKnockBackSetKnockback": "W: 12",
    "LandingLag": null,
    "AutoCancel": null,
    "KnockbackGrowth": "100",
    "MoveType": "ground",
    "IsWeightDependent": false,
    "Links": [
      {
        "Rel": "self",
        "Href": "http://beta-api-kuroganehammer.azurewebsites.net/api/moves/59812ae94696593ccc99ce81"
      },
      {
        "Rel": "character",
        "Href": "http://beta-api-kuroganehammer.azurewebsites.net/api/characters/name/PAC-MAN"
      }
    ]
  },
  {
    "InstanceId": "59812ae94696593ccc99ce82",
    "Name": "Dash Attack (Hits 1-2)",
    "OwnerId": 38,
    "Owner": "PAC-MAN",
    "HitboxActive": "10-11, 20-21",
    "FirstActionableFrame": "-",
    "BaseDamage": "2",
    "Angle": "12",
    "BaseKnockBackSetKnockback": "45",
    "LandingLag": null,
    "AutoCancel": null,
    "KnockbackGrowth": "15",
    "MoveType": "ground",
    "IsWeightDependent": false,
    "Links": [
      {
        "Rel": "self",
        "Href": "http://beta-api-kuroganehammer.azurewebsites.net/api/moves/59812ae94696593ccc99ce82"
      },
      {
        "Rel": "character",
        "Href": "http://beta-api-kuroganehammer.azurewebsites.net/api/characters/name/PAC-MAN"
      }
    ]
  },
  {
    "InstanceId": "59812ae94696593ccc99ce83",
    "Name": "Dash Attack (Hit 3)",
    "OwnerId": 38,
    "Owner": "PAC-MAN",
    "HitboxActive": "30",
    "FirstActionableFrame": "-",
    "BaseDamage": "5",
    "Angle": "60",
    "BaseKnockBackSetKnockback": "100",
    "LandingLag": null,
    "AutoCancel": null,
    "KnockbackGrowth": "60",
    "MoveType": "ground",
    "IsWeightDependent": false,
    "Links": [
      {
        "Rel": "self",
        "Href": "http://beta-api-kuroganehammer.azurewebsites.net/api/moves/59812ae94696593ccc99ce83"
      },
      {
        "Rel": "character",
        "Href": "http://beta-api-kuroganehammer.azurewebsites.net/api/characters/name/PAC-MAN"
      }
    ]
  },
  {
    "InstanceId": "59812ae94696593ccc99ce84",
    "Name": "Ftilt (All Angles)",
    "OwnerId": 38,
    "Owner": "PAC-MAN",
    "HitboxActive": "5-7",
    "FirstActionableFrame": "31",
    "BaseDamage": "8",
    "Angle": "361",
    "BaseKnockBackSetKnockback": "20",
    "LandingLag": null,
    "AutoCancel": null,
    "KnockbackGrowth": "100",
    "MoveType": "ground",
    "IsWeightDependent": false,
    "Links": [
      {
        "Rel": "self",
        "Href": "http://beta-api-kuroganehammer.azurewebsites.net/api/moves/59812ae94696593ccc99ce84"
      },
      {
        "Rel": "character",
        "Href": "http://beta-api-kuroganehammer.azurewebsites.net/api/characters/name/PAC-MAN"
      }
    ]
  },
  {
    "InstanceId": "59812ae94696593ccc99ce85",
    "Name": "Utilt",
    "OwnerId": 38,
    "Owner": "PAC-MAN",
    "HitboxActive": "7-10 (Head Intangible: 6-10)",
    "FirstActionableFrame": "34",
    "BaseDamage": "7",
    "Angle": "96",
    "BaseKnockBackSetKnockback": "50",
    "LandingLag": null,
    "AutoCancel": null,
    "KnockbackGrowth": "100",
    "MoveType": "ground",
    "IsWeightDependent": false,
    "Links": [
      {
        "Rel": "self",
        "Href": "http://beta-api-kuroganehammer.azurewebsites.net/api/moves/59812ae94696593ccc99ce85"
      },
      {
        "Rel": "character",
        "Href": "http://beta-api-kuroganehammer.azurewebsites.net/api/characters/name/PAC-MAN"
      }
    ]
  },
  {
    "InstanceId": "59812ae94696593ccc99ce86",
    "Name": "Dtilt",
    "OwnerId": 38,
    "Owner": "PAC-MAN",
    "HitboxActive": "7-9",
    "FirstActionableFrame": "29",
    "BaseDamage": "6",
    "Angle": "45",
    "BaseKnockBackSetKnockback": "50",
    "LandingLag": null,
    "AutoCancel": null,
    "KnockbackGrowth": "80",
    "MoveType": "ground",
    "IsWeightDependent": false,
    "Links": [
      {
        "Rel": "self",
        "Href": "http://beta-api-kuroganehammer.azurewebsites.net/api/moves/59812ae94696593ccc99ce86"
      },
      {
        "Rel": "character",
        "Href": "http://beta-api-kuroganehammer.azurewebsites.net/api/characters/name/PAC-MAN"
      }
    ]
  },
  {
    "InstanceId": "59812ae94696593ccc99ce87",
    "Name": "Fsmash",
    "OwnerId": 38,
    "Owner": "PAC-MAN",
    "HitboxActive": "18-20",
    "FirstActionableFrame": "53",
    "BaseDamage": "16/15",
    "Angle": "361",
    "BaseKnockBackSetKnockback": "25",
    "LandingLag": null,
    "AutoCancel": null,
    "KnockbackGrowth": "99",
    "MoveType": "ground",
    "IsWeightDependent": false,
    "Links": [
      {
        "Rel": "self",
        "Href": "http://beta-api-kuroganehammer.azurewebsites.net/api/moves/59812ae94696593ccc99ce87"
      },
      {
        "Rel": "character",
        "Href": "http://beta-api-kuroganehammer.azurewebsites.net/api/characters/name/PAC-MAN"
      }
    ]
  },
  {
    "InstanceId": "59812ae94696593ccc99ce88",
    "Name": "Fsmash (Late)",
    "OwnerId": 38,
    "Owner": "PAC-MAN",
    "HitboxActive": "21-28",
    "FirstActionableFrame": "-",
    "BaseDamage": "9",
    "Angle": "361",
    "BaseKnockBackSetKnockback": "25",
    "LandingLag": null,
    "AutoCancel": null,
    "KnockbackGrowth": "102",
    "MoveType": "ground",
    "IsWeightDependent": false,
    "Links": [
      {
        "Rel": "self",
        "Href": "http://beta-api-kuroganehammer.azurewebsites.net/api/moves/59812ae94696593ccc99ce88"
      },
      {
        "Rel": "character",
        "Href": "http://beta-api-kuroganehammer.azurewebsites.net/api/characters/name/PAC-MAN"
      }
    ]
  },
  {
    "InstanceId": "59812ae94696593ccc99ce89",
    "Name": "Usmash (Hit 1)",
    "OwnerId": 38,
    "Owner": "PAC-MAN",
    "HitboxActive": "13",
    "FirstActionableFrame": "50",
    "BaseDamage": "3",
    "Angle": "115",
    "BaseKnockBackSetKnockback": "95",
    "LandingLag": null,
    "AutoCancel": null,
    "KnockbackGrowth": "20",
    "MoveType": "ground",
    "IsWeightDependent": false,
    "Links": [
      {
        "Rel": "self",
        "Href": "http://beta-api-kuroganehammer.azurewebsites.net/api/moves/59812ae94696593ccc99ce89"
      },
      {
        "Rel": "character",
        "Href": "http://beta-api-kuroganehammer.azurewebsites.net/api/characters/name/PAC-MAN"
      }
    ]
  },
  {
    "InstanceId": "59812ae94696593ccc99ce8a",
    "Name": "Usmash (Hit 2)",
    "OwnerId": 38,
    "Owner": "PAC-MAN",
    "HitboxActive": "16-18",
    "FirstActionableFrame": "-",
    "BaseDamage": "14",
    "Angle": "83",
    "BaseKnockBackSetKnockback": "32",
    "LandingLag": null,
    "AutoCancel": null,
    "KnockbackGrowth": "97",
    "MoveType": "ground",
    "IsWeightDependent": false,
    "Links": [
      {
        "Rel": "self",
        "Href": "http://beta-api-kuroganehammer.azurewebsites.net/api/moves/59812ae94696593ccc99ce8a"
      },
      {
        "Rel": "character",
        "Href": "http://beta-api-kuroganehammer.azurewebsites.net/api/characters/name/PAC-MAN"
      }
    ]
  },
  {
    "InstanceId": "59812ae94696593ccc99ce8b",
    "Name": "Usmash (Hit 2, Late)",
    "OwnerId": 38,
    "Owner": "PAC-MAN",
    "HitboxActive": "19-26",
    "FirstActionableFrame": "-",
    "BaseDamage": "8",
    "Angle": "83",
    "BaseKnockBackSetKnockback": "32",
    "LandingLag": null,
    "AutoCancel": null,
    "KnockbackGrowth": "92",
    "MoveType": "ground",
    "IsWeightDependent": false,
    "Links": [
      {
        "Rel": "self",
        "Href": "http://beta-api-kuroganehammer.azurewebsites.net/api/moves/59812ae94696593ccc99ce8b"
      },
      {
        "Rel": "character",
        "Href": "http://beta-api-kuroganehammer.azurewebsites.net/api/characters/name/PAC-MAN"
      }
    ]
  },
  {
    "InstanceId": "59812ae94696593ccc99ce8c",
    "Name": "Dsmash",
    "OwnerId": 38,
    "Owner": "PAC-MAN",
    "HitboxActive": "18-20",
    "FirstActionableFrame": "55",
    "BaseDamage": "13",
    "Angle": "29",
    "BaseKnockBackSetKnockback": "30",
    "LandingLag": null,
    "AutoCancel": null,
    "KnockbackGrowth": "86",
    "MoveType": "ground",
    "IsWeightDependent": false,
    "Links": [
      {
        "Rel": "self",
        "Href": "http://beta-api-kuroganehammer.azurewebsites.net/api/moves/59812ae94696593ccc99ce8c"
      },
      {
        "Rel": "character",
        "Href": "http://beta-api-kuroganehammer.azurewebsites.net/api/characters/name/PAC-MAN"
      }
    ]
  },
  {
    "InstanceId": "59812ae94696593ccc99ce8d",
    "Name": "Dsmash (Late)",
    "OwnerId": 38,
    "Owner": "PAC-MAN",
    "HitboxActive": "21-28",
    "FirstActionableFrame": "-",
    "BaseDamage": "7",
    "Angle": "45",
    "BaseKnockBackSetKnockback": "40",
    "LandingLag": null,
    "AutoCancel": null,
    "KnockbackGrowth": "92",
    "MoveType": "ground",
    "IsWeightDependent": false,
    "Links": [
      {
        "Rel": "self",
        "Href": "http://beta-api-kuroganehammer.azurewebsites.net/api/moves/59812ae94696593ccc99ce8d"
      },
      {
        "Rel": "character",
        "Href": "http://beta-api-kuroganehammer.azurewebsites.net/api/characters/name/PAC-MAN"
      }
    ]
  },
  {
    "InstanceId": "59812ae94696593ccc99ce8e",
    "Name": "Useless Tractor Beams",
    "OwnerId": 38,
    "Owner": "PAC-MAN",
    "HitboxActive": "Hitbox Active",
    "FirstActionableFrame": "FAF",
    "BaseDamage": "",
    "Angle": "",
    "BaseKnockBackSetKnockback": "",
    "LandingLag": null,
    "AutoCancel": null,
    "KnockbackGrowth": "",
    "MoveType": "ground",
    "IsWeightDependent": false,
    "Links": [
      {
        "Rel": "self",
        "Href": "http://beta-api-kuroganehammer.azurewebsites.net/api/moves/59812ae94696593ccc99ce8e"
      },
      {
        "Rel": "character",
        "Href": "http://beta-api-kuroganehammer.azurewebsites.net/api/characters/name/PAC-MAN"
      }
    ]
  },
  {
    "InstanceId": "59812ae94696593ccc99ce8f",
    "Name": "Standing Grab",
    "OwnerId": 38,
    "Owner": "PAC-MAN",
    "HitboxActive": "12-14, 22-24, 32-39",
    "FirstActionableFrame": "76",
    "BaseDamage": "",
    "Angle": "",
    "BaseKnockBackSetKnockback": "",
    "LandingLag": null,
    "AutoCancel": null,
    "KnockbackGrowth": "",
    "MoveType": "ground",
    "IsWeightDependent": false,
    "Links": [
      {
        "Rel": "self",
        "Href": "http://beta-api-kuroganehammer.azurewebsites.net/api/moves/59812ae94696593ccc99ce8f"
      },
      {
        "Rel": "character",
        "Href": "http://beta-api-kuroganehammer.azurewebsites.net/api/characters/name/PAC-MAN"
      }
    ]
  },
  {
    "InstanceId": "59812ae94696593ccc99ce90",
    "Name": "Dash Grab",
    "OwnerId": 38,
    "Owner": "PAC-MAN",
    "HitboxActive": "12-14, 22-24, 32-39",
    "FirstActionableFrame": "76",
    "BaseDamage": "",
    "Angle": "",
    "BaseKnockBackSetKnockback": "",
    "LandingLag": null,
    "AutoCancel": null,
    "KnockbackGrowth": "",
    "MoveType": "ground",
    "IsWeightDependent": false,
    "Links": [
      {
        "Rel": "self",
        "Href": "http://beta-api-kuroganehammer.azurewebsites.net/api/moves/59812ae94696593ccc99ce90"
      },
      {
        "Rel": "character",
        "Href": "http://beta-api-kuroganehammer.azurewebsites.net/api/characters/name/PAC-MAN"
      }
    ]
  },
  {
    "InstanceId": "59812ae94696593ccc99ce91",
    "Name": "Pivot Grab",
    "OwnerId": 38,
    "Owner": "PAC-MAN",
    "HitboxActive": "12-14, 22-24, 32-39",
    "FirstActionableFrame": "76",
    "BaseDamage": "",
    "Angle": "",
    "BaseKnockBackSetKnockback": "",
    "LandingLag": null,
    "AutoCancel": null,
    "KnockbackGrowth": "",
    "MoveType": "ground",
    "IsWeightDependent": false,
    "Links": [
      {
        "Rel": "self",
        "Href": "http://beta-api-kuroganehammer.azurewebsites.net/api/moves/59812ae94696593ccc99ce91"
      },
      {
        "Rel": "character",
        "Href": "http://beta-api-kuroganehammer.azurewebsites.net/api/characters/name/PAC-MAN"
      }
    ]
  },
  {
    "InstanceId": "59812ae94696593ccc99ce92",
    "Name": "Spotdodge",
    "OwnerId": 38,
    "Owner": "PAC-MAN",
    "HitboxActive": "3-17",
    "FirstActionableFrame": "27",
    "BaseDamage": "",
    "Angle": "",
    "BaseKnockBackSetKnockback": "",
    "LandingLag": null,
    "AutoCancel": null,
    "KnockbackGrowth": "",
    "MoveType": "ground",
    "IsWeightDependent": false,
    "Links": [
      {
        "Rel": "self",
        "Href": "http://beta-api-kuroganehammer.azurewebsites.net/api/moves/59812ae94696593ccc99ce92"
      },
      {
        "Rel": "character",
        "Href": "http://beta-api-kuroganehammer.azurewebsites.net/api/characters/name/PAC-MAN"
      }
    ]
  },
  {
    "InstanceId": "59812ae94696593ccc99ce93",
    "Name": "Forward Roll",
    "OwnerId": 38,
    "Owner": "PAC-MAN",
    "HitboxActive": "4-16",
    "FirstActionableFrame": "30",
    "BaseDamage": "",
    "Angle": "",
    "BaseKnockBackSetKnockback": "",
    "LandingLag": null,
    "AutoCancel": null,
    "KnockbackGrowth": "",
    "MoveType": "ground",
    "IsWeightDependent": false,
    "Links": [
      {
        "Rel": "self",
        "Href": "http://beta-api-kuroganehammer.azurewebsites.net/api/moves/59812ae94696593ccc99ce93"
      },
      {
        "Rel": "character",
        "Href": "http://beta-api-kuroganehammer.azurewebsites.net/api/characters/name/PAC-MAN"
      }
    ]
  },
  {
    "InstanceId": "59812ae94696593ccc99ce94",
    "Name": "Back Roll",
    "OwnerId": 38,
    "Owner": "PAC-MAN",
    "HitboxActive": "4-16",
    "FirstActionableFrame": "30",
    "BaseDamage": "",
    "Angle": "",
    "BaseKnockBackSetKnockback": "",
    "LandingLag": null,
    "AutoCancel": null,
    "KnockbackGrowth": "",
    "MoveType": "ground",
    "IsWeightDependent": false,
    "Links": [
      {
        "Rel": "self",
        "Href": "http://beta-api-kuroganehammer.azurewebsites.net/api/moves/59812ae94696593ccc99ce94"
      },
      {
        "Rel": "character",
        "Href": "http://beta-api-kuroganehammer.azurewebsites.net/api/characters/name/PAC-MAN"
      }
    ]
  },
  {
    "InstanceId": "59812ae94696593ccc99ce95",
    "Name": "Airdodge",
    "OwnerId": 38,
    "Owner": "PAC-MAN",
    "HitboxActive": "3-27",
    "FirstActionableFrame": "33",
    "BaseDamage": "",
    "Angle": "",
    "BaseKnockBackSetKnockback": "",
    "LandingLag": null,
    "AutoCancel": null,
    "KnockbackGrowth": "",
    "MoveType": "ground",
    "IsWeightDependent": false,
    "Links": [
      {
        "Rel": "self",
        "Href": "http://beta-api-kuroganehammer.azurewebsites.net/api/moves/59812ae94696593ccc99ce95"
      },
      {
        "Rel": "character",
        "Href": "http://beta-api-kuroganehammer.azurewebsites.net/api/characters/name/PAC-MAN"
      }
    ]
  },
  {
    "InstanceId": "59812ae94696593ccc99ce96",
    "Name": "Nair (Early)",
    "OwnerId": 38,
    "Owner": "PAC-MAN",
    "HitboxActive": "3-5",
    "FirstActionableFrame": "52",
    "BaseDamage": "10",
    "Angle": "361",
    "BaseKnockBackSetKnockback": "20",
    "LandingLag": "12",
    "AutoCancel": "1-2, 48&gt;",
    "KnockbackGrowth": "100",
    "MoveType": "aerial",
    "IsWeightDependent": false,
    "Links": [
      {
        "Rel": "self",
        "Href": "http://beta-api-kuroganehammer.azurewebsites.net/api/moves/59812ae94696593ccc99ce96"
      },
      {
        "Rel": "character",
        "Href": "http://beta-api-kuroganehammer.azurewebsites.net/api/characters/name/PAC-MAN"
      }
    ]
  },
  {
    "InstanceId": "59812ae94696593ccc99ce97",
    "Name": "Nair",
    "OwnerId": 38,
    "Owner": "PAC-MAN",
    "HitboxActive": "6-9",
    "FirstActionableFrame": "-",
    "BaseDamage": "6",
    "Angle": "361",
    "BaseKnockBackSetKnockback": "13",
    "LandingLag": "-",
    "AutoCancel": "-",
    "KnockbackGrowth": "90",
    "MoveType": "aerial",
    "IsWeightDependent": false,
    "Links": [
      {
        "Rel": "self",
        "Href": "http://beta-api-kuroganehammer.azurewebsites.net/api/moves/59812ae94696593ccc99ce97"
      },
      {
        "Rel": "character",
        "Href": "http://beta-api-kuroganehammer.azurewebsites.net/api/characters/name/PAC-MAN"
      }
    ]
  },
  {
    "InstanceId": "59812ae94696593ccc99ce98",
    "Name": "Nair (Late)",
    "OwnerId": 38,
    "Owner": "PAC-MAN",
    "HitboxActive": "10-19",
    "FirstActionableFrame": "-",
    "BaseDamage": "3",
    "Angle": "361",
    "BaseKnockBackSetKnockback": "13",
    "LandingLag": "-",
    "AutoCancel": "-",
    "KnockbackGrowth": "90",
    "MoveType": "aerial",
    "IsWeightDependent": false,
    "Links": [
      {
        "Rel": "self",
        "Href": "http://beta-api-kuroganehammer.azurewebsites.net/api/moves/59812ae94696593ccc99ce98"
      },
      {
        "Rel": "character",
        "Href": "http://beta-api-kuroganehammer.azurewebsites.net/api/characters/name/PAC-MAN"
      }
    ]
  },
  {
    "InstanceId": "59812ae94696593ccc99ce99",
    "Name": "Fair",
    "OwnerId": 38,
    "Owner": "PAC-MAN",
    "HitboxActive": "5-8",
    "FirstActionableFrame": "26",
    "BaseDamage": "5.3",
    "Angle": "361",
    "BaseKnockBackSetKnockback": "7",
    "LandingLag": "16",
    "AutoCancel": "1, 43&gt;",
    "KnockbackGrowth": "90",
    "MoveType": "aerial",
    "IsWeightDependent": false,
    "Links": [
      {
        "Rel": "self",
        "Href": "http://beta-api-kuroganehammer.azurewebsites.net/api/moves/59812ae94696593ccc99ce99"
      },
      {
        "Rel": "character",
        "Href": "http://beta-api-kuroganehammer.azurewebsites.net/api/characters/name/PAC-MAN"
      }
    ]
  },
  {
    "InstanceId": "59812ae94696593ccc99ce9a",
    "Name": "Bair",
    "OwnerId": 38,
    "Owner": "PAC-MAN",
    "HitboxActive": "9-11",
    "FirstActionableFrame": "41",
    "BaseDamage": "11.8",
    "Angle": "361",
    "BaseKnockBackSetKnockback": "10",
    "LandingLag": "22",
    "AutoCancel": "1-8, 36&gt;",
    "KnockbackGrowth": "100",
    "MoveType": "aerial",
    "IsWeightDependent": false,
    "Links": [
      {
        "Rel": "self",
        "Href": "http://beta-api-kuroganehammer.azurewebsites.net/api/moves/59812ae94696593ccc99ce9a"
      },
      {
        "Rel": "character",
        "Href": "http://beta-api-kuroganehammer.azurewebsites.net/api/characters/name/PAC-MAN"
      }
    ]
  },
  {
    "InstanceId": "59812ae94696593ccc99ce9b",
    "Name": "Bair (Late)",
    "OwnerId": 38,
    "Owner": "PAC-MAN",
    "HitboxActive": "12-16",
    "FirstActionableFrame": "-",
    "BaseDamage": "7",
    "Angle": "361",
    "BaseKnockBackSetKnockback": "7",
    "LandingLag": "-",
    "AutoCancel": "-",
    "KnockbackGrowth": "90",
    "MoveType": "aerial",
    "IsWeightDependent": false,
    "Links": [
      {
        "Rel": "self",
        "Href": "http://beta-api-kuroganehammer.azurewebsites.net/api/moves/59812ae94696593ccc99ce9b"
      },
      {
        "Rel": "character",
        "Href": "http://beta-api-kuroganehammer.azurewebsites.net/api/characters/name/PAC-MAN"
      }
    ]
  },
  {
    "InstanceId": "59812ae94696593ccc99ce9c",
    "Name": "Uair",
    "OwnerId": 38,
    "Owner": "PAC-MAN",
    "HitboxActive": "9-16",
    "FirstActionableFrame": "37",
    "BaseDamage": "10",
    "Angle": "70",
    "BaseKnockBackSetKnockback": "13",
    "LandingLag": "16",
    "AutoCancel": "1, 32&gt;",
    "KnockbackGrowth": "100",
    "MoveType": "aerial",
    "IsWeightDependent": false,
    "Links": [
      {
        "Rel": "self",
        "Href": "http://beta-api-kuroganehammer.azurewebsites.net/api/moves/59812ae94696593ccc99ce9c"
      },
      {
        "Rel": "character",
        "Href": "http://beta-api-kuroganehammer.azurewebsites.net/api/characters/name/PAC-MAN"
      }
    ]
  },
  {
    "InstanceId": "59812ae94696593ccc99ce9d",
    "Name": "Dair (Hits 1-3)",
    "OwnerId": 38,
    "Owner": "PAC-MAN",
    "HitboxActive": "6-7, 14-15, 22-23",
    "FirstActionableFrame": "60",
    "BaseDamage": "1.5",
    "Angle": "100",
    "BaseKnockBackSetKnockback": "W: 10",
    "LandingLag": "20",
    "AutoCancel": "1, 56&gt;",
    "KnockbackGrowth": "100",
    "MoveType": "aerial",
    "IsWeightDependent": false,
    "Links": [
      {
        "Rel": "self",
        "Href": "http://beta-api-kuroganehammer.azurewebsites.net/api/moves/59812ae94696593ccc99ce9d"
      },
      {
        "Rel": "character",
        "Href": "http://beta-api-kuroganehammer.azurewebsites.net/api/characters/name/PAC-MAN"
      }
    ]
  },
  {
    "InstanceId": "59812ae94696593ccc99ce9e",
    "Name": "Dair (Hit 4)",
    "OwnerId": 38,
    "Owner": "PAC-MAN",
    "HitboxActive": "30-31",
    "FirstActionableFrame": "-",
    "BaseDamage": "6",
    "Angle": "65",
    "BaseKnockBackSetKnockback": "80",
    "LandingLag": "-",
    "AutoCancel": "-",
    "KnockbackGrowth": "90",
    "MoveType": "aerial",
    "IsWeightDependent": false,
    "Links": [
      {
        "Rel": "self",
        "Href": "http://beta-api-kuroganehammer.azurewebsites.net/api/moves/59812ae94696593ccc99ce9e"
      },
      {
        "Rel": "character",
        "Href": "http://beta-api-kuroganehammer.azurewebsites.net/api/characters/name/PAC-MAN"
      }
    ]
  },
  {
    "InstanceId": "59812ae94696593ccc99ce9f",
    "Name": "Bonus Fruit (Throw)",
    "OwnerId": 38,
    "Owner": "PAC-MAN",
    "HitboxActive": "12-",
    "FirstActionableFrame": "45",
    "BaseDamage": "-",
    "Angle": "-",
    "BaseKnockBackSetKnockback": "-",
    "LandingLag": null,
    "AutoCancel": null,
    "KnockbackGrowth": "-",
    "MoveType": "special",
    "IsWeightDependent": false,
    "Links": [
      {
        "Rel": "self",
        "Href": "http://beta-api-kuroganehammer.azurewebsites.net/api/moves/59812ae94696593ccc99ce9f"
      },
      {
        "Rel": "character",
        "Href": "http://beta-api-kuroganehammer.azurewebsites.net/api/characters/name/PAC-MAN"
      }
    ]
  },
  {
    "InstanceId": "59812ae94696593ccc99cea0",
    "Name": "Bonus Fruit (CHERRY)",
    "OwnerId": 38,
    "Owner": "PAC-MAN",
    "HitboxActive": "Fruit Generated: Frame 8",
    "FirstActionableFrame": "-",
    "BaseDamage": "4",
    "Angle": "55",
    "BaseKnockBackSetKnockback": "40",
    "LandingLag": null,
    "AutoCancel": null,
    "KnockbackGrowth": "80",
    "MoveType": "special",
    "IsWeightDependent": false,
    "Links": [
      {
        "Rel": "self",
        "Href": "http://beta-api-kuroganehammer.azurewebsites.net/api/moves/59812ae94696593ccc99cea0"
      },
      {
        "Rel": "character",
        "Href": "http://beta-api-kuroganehammer.azurewebsites.net/api/characters/name/PAC-MAN"
      }
    ]
  },
  {
    "InstanceId": "59812ae94696593ccc99cea1",
    "Name": "Bonus Fruit (STRAWBERRY)",
    "OwnerId": 38,
    "Owner": "PAC-MAN",
    "HitboxActive": "Fruit Generated: Frame 19",
    "FirstActionableFrame": "-",
    "BaseDamage": "6",
    "Angle": "55",
    "BaseKnockBackSetKnockback": "40",
    "LandingLag": null,
    "AutoCancel": null,
    "KnockbackGrowth": "80",
    "MoveType": "special",
    "IsWeightDependent": false,
    "Links": [
      {
        "Rel": "self",
        "Href": "http://beta-api-kuroganehammer.azurewebsites.net/api/moves/59812ae94696593ccc99cea1"
      },
      {
        "Rel": "character",
        "Href": "http://beta-api-kuroganehammer.azurewebsites.net/api/characters/name/PAC-MAN"
      }
    ]
  },
  {
    "InstanceId": "59812ae94696593ccc99cea2",
    "Name": "Bonus Fruit (ORANGE)",
    "OwnerId": 38,
    "Owner": "PAC-MAN",
    "HitboxActive": "Fruit Generated: Frame 30",
    "FirstActionableFrame": "-",
    "BaseDamage": "8",
    "Angle": "30",
    "BaseKnockBackSetKnockback": "50",
    "LandingLag": null,
    "AutoCancel": null,
    "KnockbackGrowth": "76",
    "MoveType": "special",
    "IsWeightDependent": false,
    "Links": [
      {
        "Rel": "self",
        "Href": "http://beta-api-kuroganehammer.azurewebsites.net/api/moves/59812ae94696593ccc99cea2"
      },
      {
        "Rel": "character",
        "Href": "http://beta-api-kuroganehammer.azurewebsites.net/api/characters/name/PAC-MAN"
      }
    ]
  },
  {
    "InstanceId": "59812ae94696593ccc99cea3",
    "Name": "Bonus Fruit (APPLE)",
    "OwnerId": 38,
    "Owner": "PAC-MAN",
    "HitboxActive": "Fruit Generated: Frame 54",
    "FirstActionableFrame": "-",
    "BaseDamage": "9",
    "Angle": "75",
    "BaseKnockBackSetKnockback": "60",
    "LandingLag": null,
    "AutoCancel": null,
    "KnockbackGrowth": "100",
    "MoveType": "special",
    "IsWeightDependent": false,
    "Links": [
      {
        "Rel": "self",
        "Href": "http://beta-api-kuroganehammer.azurewebsites.net/api/moves/59812ae94696593ccc99cea3"
      },
      {
        "Rel": "character",
        "Href": "http://beta-api-kuroganehammer.azurewebsites.net/api/characters/name/PAC-MAN"
      }
    ]
  },
  {
    "InstanceId": "59812ae94696593ccc99cea4",
    "Name": "Bonus Fruit (MELON)",
    "OwnerId": 38,
    "Owner": "PAC-MAN",
    "HitboxActive": "Fruit Generated: Frame 78",
    "FirstActionableFrame": "-",
    "BaseDamage": "12",
    "Angle": "55",
    "BaseKnockBackSetKnockback": "40",
    "LandingLag": null,
    "AutoCancel": null,
    "KnockbackGrowth": "100",
    "MoveType": "special",
    "IsWeightDependent": false,
    "Links": [
      {
        "Rel": "self",
        "Href": "http://beta-api-kuroganehammer.azurewebsites.net/api/moves/59812ae94696593ccc99cea4"
      },
      {
        "Rel": "character",
        "Href": "http://beta-api-kuroganehammer.azurewebsites.net/api/characters/name/PAC-MAN"
      }
    ]
  },
  {
    "InstanceId": "59812ae94696593ccc99cea5",
    "Name": "Bonus Fruit (GALAGA)",
    "OwnerId": 38,
    "Owner": "PAC-MAN",
    "HitboxActive": "Fruit Generated: Frame 102",
    "FirstActionableFrame": "-",
    "BaseDamage": "9",
    "Angle": "70",
    "BaseKnockBackSetKnockback": "40",
    "LandingLag": null,
    "AutoCancel": null,
    "KnockbackGrowth": "80",
    "MoveType": "special",
    "IsWeightDependent": false,
    "Links": [
      {
        "Rel": "self",
        "Href": "http://beta-api-kuroganehammer.azurewebsites.net/api/moves/59812ae94696593ccc99cea5"
      },
      {
        "Rel": "character",
        "Href": "http://beta-api-kuroganehammer.azurewebsites.net/api/characters/name/PAC-MAN"
      }
    ]
  },
  {
    "InstanceId": "59812ae94696593ccc99cea6",
    "Name": "Bonus Fruit (BELL)",
    "OwnerId": 38,
    "Owner": "PAC-MAN",
    "HitboxActive": "Fruit Generated: Frame 126",
    "FirstActionableFrame": "-",
    "BaseDamage": "8",
    "Angle": "55",
    "BaseKnockBackSetKnockback": "30",
    "LandingLag": null,
    "AutoCancel": null,
    "KnockbackGrowth": "120",
    "MoveType": "special",
    "IsWeightDependent": false,
    "Links": [
      {
        "Rel": "self",
        "Href": "http://beta-api-kuroganehammer.azurewebsites.net/api/moves/59812ae94696593ccc99cea6"
      },
      {
        "Rel": "character",
        "Href": "http://beta-api-kuroganehammer.azurewebsites.net/api/characters/name/PAC-MAN"
      }
    ]
  },
  {
    "InstanceId": "59812ae94696593ccc99cea7",
    "Name": "Bonus Fruit (KEY)",
    "OwnerId": 38,
    "Owner": "PAC-MAN",
    "HitboxActive": "Fruit Generated: Frame 150",
    "FirstActionableFrame": "-",
    "BaseDamage": "15",
    "Angle": "55",
    "BaseKnockBackSetKnockback": "40",
    "LandingLag": null,
    "AutoCancel": null,
    "KnockbackGrowth": "90",
    "MoveType": "special",
    "IsWeightDependent": false,
    "Links": [
      {
        "Rel": "self",
        "Href": "http://beta-api-kuroganehammer.azurewebsites.net/api/moves/59812ae94696593ccc99cea7"
      },
      {
        "Rel": "character",
        "Href": "http://beta-api-kuroganehammer.azurewebsites.net/api/characters/name/PAC-MAN"
      }
    ]
  },
  {
    "InstanceId": "59812ae94696593ccc99cea8",
    "Name": "Power Pellet",
    "OwnerId": 38,
    "Owner": "PAC-MAN",
    "HitboxActive": "23-",
    "FirstActionableFrame": "94",
    "BaseDamage": "10",
    "Angle": "45",
    "BaseKnockBackSetKnockback": "30",
    "LandingLag": null,
    "AutoCancel": null,
    "KnockbackGrowth": "90",
    "MoveType": "special",
    "IsWeightDependent": false,
    "Links": [
      {
        "Rel": "self",
        "Href": "http://beta-api-kuroganehammer.azurewebsites.net/api/moves/59812ae94696593ccc99cea8"
      },
      {
        "Rel": "character",
        "Href": "http://beta-api-kuroganehammer.azurewebsites.net/api/characters/name/PAC-MAN"
      }
    ]
  },
  {
    "InstanceId": "59812ae94696593ccc99cea9",
    "Name": "Power Pellet (Dash)",
    "OwnerId": 38,
    "Owner": "PAC-MAN",
    "HitboxActive": "?? (Super Armor: ??)",
    "FirstActionableFrame": "-",
    "BaseDamage": "1",
    "Angle": "50/361",
    "BaseKnockBackSetKnockback": "50/40",
    "LandingLag": null,
    "AutoCancel": null,
    "KnockbackGrowth": "108/66",
    "MoveType": "special",
    "IsWeightDependent": false,
    "Links": [
      {
        "Rel": "self",
        "Href": "http://beta-api-kuroganehammer.azurewebsites.net/api/moves/59812ae94696593ccc99cea9"
      },
      {
        "Rel": "character",
        "Href": "http://beta-api-kuroganehammer.azurewebsites.net/api/characters/name/PAC-MAN"
      }
    ]
  },
  {
    "InstanceId": "59812ae94696593ccc99ceaa",
    "Name": "Pac-Jump",
    "OwnerId": 38,
    "Owner": "PAC-MAN",
    "HitboxActive": "Trampoline From: 1-295 (Unblockable)",
    "FirstActionableFrame": "-",
    "BaseDamage": "-",
    "Angle": "-",
    "BaseKnockBackSetKnockback": "-",
    "LandingLag": null,
    "AutoCancel": null,
    "KnockbackGrowth": "-",
    "MoveType": "special",
    "IsWeightDependent": false,
    "Links": [
      {
        "Rel": "self",
        "Href": "http://beta-api-kuroganehammer.azurewebsites.net/api/moves/59812ae94696593ccc99ceaa"
      },
      {
        "Rel": "character",
        "Href": "http://beta-api-kuroganehammer.azurewebsites.net/api/characters/name/PAC-MAN"
      }
    ]
  },
  {
    "InstanceId": "59812ae94696593ccc99ceab",
    "Name": "Pac-Jump (Attack, Early)",
    "OwnerId": 38,
    "Owner": "PAC-MAN",
    "HitboxActive": "4-7",
    "FirstActionableFrame": "-",
    "BaseDamage": "7",
    "Angle": "92",
    "BaseKnockBackSetKnockback": "40",
    "LandingLag": null,
    "AutoCancel": null,
    "KnockbackGrowth": "90",
    "MoveType": "special",
    "IsWeightDependent": false,
    "Links": [
      {
        "Rel": "self",
        "Href": "http://beta-api-kuroganehammer.azurewebsites.net/api/moves/59812ae94696593ccc99ceab"
      },
      {
        "Rel": "character",
        "Href": "http://beta-api-kuroganehammer.azurewebsites.net/api/characters/name/PAC-MAN"
      }
    ]
  },
  {
    "InstanceId": "59812ae94696593ccc99ceac",
    "Name": "Pac-Jump (Attack)",
    "OwnerId": 38,
    "Owner": "PAC-MAN",
    "HitboxActive": "8-12",
    "FirstActionableFrame": "-",
    "BaseDamage": "6",
    "Angle": "86",
    "BaseKnockBackSetKnockback": "40",
    "LandingLag": null,
    "AutoCancel": null,
    "KnockbackGrowth": "90",
    "MoveType": "special",
    "IsWeightDependent": false,
    "Links": [
      {
        "Rel": "self",
        "Href": "http://beta-api-kuroganehammer.azurewebsites.net/api/moves/59812ae94696593ccc99ceac"
      },
      {
        "Rel": "character",
        "Href": "http://beta-api-kuroganehammer.azurewebsites.net/api/characters/name/PAC-MAN"
      }
    ]
  },
  {
    "InstanceId": "59812ae94696593ccc99cead",
    "Name": "Pac-Jump (Attack, Late)",
    "OwnerId": 38,
    "Owner": "PAC-MAN",
    "HitboxActive": "13-17",
    "FirstActionableFrame": "-",
    "BaseDamage": "5",
    "Angle": "50",
    "BaseKnockBackSetKnockback": "40",
    "LandingLag": null,
    "AutoCancel": null,
    "KnockbackGrowth": "90",
    "MoveType": "special",
    "IsWeightDependent": false,
    "Links": [
      {
        "Rel": "self",
        "Href": "http://beta-api-kuroganehammer.azurewebsites.net/api/moves/59812ae94696593ccc99cead"
      },
      {
        "Rel": "character",
        "Href": "http://beta-api-kuroganehammer.azurewebsites.net/api/characters/name/PAC-MAN"
      }
    ]
  },
  {
    "InstanceId": "59812ae94696593ccc99ceae",
    "Name": "Fire Hydrant",
    "OwnerId": 38,
    "Owner": "PAC-MAN",
    "HitboxActive": "Hydrant Appears: 12",
    "FirstActionableFrame": "40",
    "BaseDamage": "-",
    "Angle": "-",
    "BaseKnockBackSetKnockback": "-",
    "LandingLag": null,
    "AutoCancel": null,
    "KnockbackGrowth": "-",
    "MoveType": "special",
    "IsWeightDependent": false,
    "Links": [
      {
        "Rel": "self",
        "Href": "http://beta-api-kuroganehammer.azurewebsites.net/api/moves/59812ae94696593ccc99ceae"
      },
      {
        "Rel": "character",
        "Href": "http://beta-api-kuroganehammer.azurewebsites.net/api/characters/name/PAC-MAN"
      }
    ]
  },
  {
    "InstanceId": "59812ae94696593ccc99ceaf",
    "Name": "Fire Hydrant (Air)",
    "OwnerId": 38,
    "Owner": "PAC-MAN",
    "HitboxActive": "Hydrant Appears: 9",
    "FirstActionableFrame": "35",
    "BaseDamage": "-",
    "Angle": "-",
    "BaseKnockBackSetKnockback": "-",
    "LandingLag": null,
    "AutoCancel": null,
    "KnockbackGrowth": "-",
    "MoveType": "special",
    "IsWeightDependent": false,
    "Links": [
      {
        "Rel": "self",
        "Href": "http://beta-api-kuroganehammer.azurewebsites.net/api/moves/59812ae94696593ccc99ceaf"
      },
      {
        "Rel": "character",
        "Href": "http://beta-api-kuroganehammer.azurewebsites.net/api/characters/name/PAC-MAN"
      }
    ]
  },
  {
    "InstanceId": "59812ae94696593ccc99ceb0",
    "Name": "Fire Hydrant (Drop Hitbox)",
    "OwnerId": 38,
    "Owner": "PAC-MAN",
    "HitboxActive": "12-",
    "FirstActionableFrame": "-",
    "BaseDamage": "9",
    "Angle": "60",
    "BaseKnockBackSetKnockback": "60",
    "LandingLag": null,
    "AutoCancel": null,
    "KnockbackGrowth": "80",
    "MoveType": "special",
    "IsWeightDependent": false,
    "Links": [
      {
        "Rel": "self",
        "Href": "http://beta-api-kuroganehammer.azurewebsites.net/api/moves/59812ae94696593ccc99ceb0"
      },
      {
        "Rel": "character",
        "Href": "http://beta-api-kuroganehammer.azurewebsites.net/api/characters/name/PAC-MAN"
      }
    ]
  },
  {
    "InstanceId": "59812ae94696593ccc99ceb1",
    "Name": "Fire Hydrant (Damaged Hitbox)",
    "OwnerId": 38,
    "Owner": "PAC-MAN",
    "HitboxActive": "1-",
    "FirstActionableFrame": "-",
    "BaseDamage": "13",
    "Angle": "45",
    "BaseKnockBackSetKnockback": "30",
    "LandingLag": null,
    "AutoCancel": null,
    "KnockbackGrowth": "90",
    "MoveType": "special",
    "IsWeightDependent": false,
    "Links": [
      {
        "Rel": "self",
        "Href": "http://beta-api-kuroganehammer.azurewebsites.net/api/moves/59812ae94696593ccc99ceb1"
      },
      {
        "Rel": "character",
        "Href": "http://beta-api-kuroganehammer.azurewebsites.net/api/characters/name/PAC-MAN"
      }
    ]
  },
  {
    "InstanceId": "59812ae94696593ccc99ceb2",
    "Name": "Fire Hydrant (Horizontal Water)",
    "OwnerId": 38,
    "Owner": "PAC-MAN",
    "HitboxActive": "1- (Unblockable)",
    "FirstActionableFrame": "-",
    "BaseDamage": "0",
    "Angle": "361",
    "BaseKnockBackSetKnockback": "W: 45",
    "LandingLag": null,
    "AutoCancel": null,
    "KnockbackGrowth": "135",
    "MoveType": "special",
    "IsWeightDependent": false,
    "Links": [
      {
        "Rel": "self",
        "Href": "http://beta-api-kuroganehammer.azurewebsites.net/api/moves/59812ae94696593ccc99ceb2"
      },
      {
        "Rel": "character",
        "Href": "http://beta-api-kuroganehammer.azurewebsites.net/api/characters/name/PAC-MAN"
      }
    ]
  },
  {
    "InstanceId": "59812ae94696593ccc99ceb3",
    "Name": "Fire Hydrant (Vertical Water)",
    "OwnerId": 38,
    "Owner": "PAC-MAN",
    "HitboxActive": "1- (Unblockable)",
    "FirstActionableFrame": "-",
    "BaseDamage": "0",
    "Angle": "90",
    "BaseKnockBackSetKnockback": "W: 45",
    "LandingLag": null,
    "AutoCancel": null,
    "KnockbackGrowth": "135",
    "MoveType": "special",
    "IsWeightDependent": false,
    "Links": [
      {
        "Rel": "self",
        "Href": "http://beta-api-kuroganehammer.azurewebsites.net/api/moves/59812ae94696593ccc99ceb3"
      },
      {
        "Rel": "character",
        "Href": "http://beta-api-kuroganehammer.azurewebsites.net/api/characters/name/PAC-MAN"
      }
    ]
  },
  {
    "InstanceId": "59812ae94696593ccc99ceb4",
    "Name": "Fthrow",
    "OwnerId": 38,
    "Owner": "PAC-MAN",
    "HitboxActive": null,
    "FirstActionableFrame": null,
    "BaseDamage": "6",
    "Angle": "58",
    "BaseKnockBackSetKnockback": "48",
    "LandingLag": null,
    "AutoCancel": null,
    "KnockbackGrowth": "65",
    "MoveType": "throw",
    "IsWeightDependent": true,
    "Links": [
      {
        "Rel": "self",
        "Href": "http://beta-api-kuroganehammer.azurewebsites.net/api/moves/59812ae94696593ccc99ceb4"
      },
      {
        "Rel": "character",
        "Href": "http://beta-api-kuroganehammer.azurewebsites.net/api/characters/name/PAC-MAN"
      }
    ]
  },
  {
    "InstanceId": "59812ae94696593ccc99ceb5",
    "Name": "Bthrow",
    "OwnerId": 38,
    "Owner": "PAC-MAN",
    "HitboxActive": null,
    "FirstActionableFrame": null,
    "BaseDamage": "11",
    "Angle": "45",
    "BaseKnockBackSetKnockback": "70",
    "LandingLag": null,
    "AutoCancel": null,
    "KnockbackGrowth": "61",
    "MoveType": "throw",
    "IsWeightDependent": true,
    "Links": [
      {
        "Rel": "self",
        "Href": "http://beta-api-kuroganehammer.azurewebsites.net/api/moves/59812ae94696593ccc99ceb5"
      },
      {
        "Rel": "character",
        "Href": "http://beta-api-kuroganehammer.azurewebsites.net/api/characters/name/PAC-MAN"
      }
    ]
  },
  {
    "InstanceId": "59812ae94696593ccc99ceb6",
    "Name": "Uthrow",
    "OwnerId": 38,
    "Owner": "PAC-MAN",
    "HitboxActive": null,
    "FirstActionableFrame": null,
    "BaseDamage": "5",
    "Angle": "89",
    "BaseKnockBackSetKnockback": "60",
    "LandingLag": null,
    "AutoCancel": null,
    "KnockbackGrowth": "100",
    "MoveType": "throw",
    "IsWeightDependent": true,
    "Links": [
      {
        "Rel": "self",
        "Href": "http://beta-api-kuroganehammer.azurewebsites.net/api/moves/59812ae94696593ccc99ceb6"
      },
      {
        "Rel": "character",
        "Href": "http://beta-api-kuroganehammer.azurewebsites.net/api/characters/name/PAC-MAN"
      }
    ]
  },
  {
    "InstanceId": "59812ae94696593ccc99ceb7",
    "Name": "Dthrow",
    "OwnerId": 38,
    "Owner": "PAC-MAN",
    "HitboxActive": null,
    "FirstActionableFrame": null,
    "BaseDamage": "1.5&#37;&#215;3, 6",
    "Angle": "45",
    "BaseKnockBackSetKnockback": "60",
    "LandingLag": null,
    "AutoCancel": null,
    "KnockbackGrowth": "55",
    "MoveType": "throw",
    "IsWeightDependent": false,
    "Links": [
      {
        "Rel": "self",
        "Href": "http://beta-api-kuroganehammer.azurewebsites.net/api/moves/59812ae94696593ccc99ceb7"
      },
      {
        "Rel": "character",
        "Href": "http://beta-api-kuroganehammer.azurewebsites.net/api/characters/name/PAC-MAN"
      }
    ]
  }
]