[
  {
    "InstanceId": "5968210346965952fcb50c35",
    "Name": "AirDeceleration",
    "OwnerId": 4,
    "Owner": "CaptainFalcon",
    "Values": [
      {
        "Value": "0.01",
        "Owner": "CaptainFalcon",
        "OwnerId": 4,
        "Name": "VALUE"
      }
    ],
    "Links": [
      {
        "Rel": "self",
        "Href": "http://beta-api-kuroganehammer.azurewebsites.net/api/characterattributes/5968210346965952fcb50c35",
        "Title": ""
      },
      {
        "Rel": "character",
        "Href": "http://beta-api-kuroganehammer.azurewebsites.net/api/characters/name/CaptainFalcon",
        "Title": ""
      }
    ]
  },
  {
    "InstanceId": "5968210346965952fcb50c36",
    "Name": "AirFriction",
    "OwnerId": 4,
    "Owner": "CaptainFalcon",
    "Values": [
      {
        "Value": "0.015",
        "Owner": "CaptainFalcon",
        "OwnerId": 4,
        "Name": "VALUE"
      }
    ],
    "Links": [
      {
        "Rel": "self",
        "Href": "http://beta-api-kuroganehammer.azurewebsites.net/api/characterattributes/5968210346965952fcb50c36",
        "Title": ""
      },
      {
        "Rel": "character",
        "Href": "http://beta-api-kuroganehammer.azurewebsites.net/api/characters/name/CaptainFalcon",
        "Title": ""
      }
    ]
  },
  {
    "InstanceId": "5968210346965952fcb50c37",
    "Name": "DashLength",
    "OwnerId": 4,
    "Owner": "CaptainFalcon",
    "Values": [
      {
        "Value": "11",
        "Owner": "CaptainFalcon",
        "OwnerId": 4,
        "Name": "LENGTH IN FRAMES"
      }
    ],
    "Links": [
      {
        "Rel": "self",
        "Href": "http://beta-api-kuroganehammer.azurewebsites.net/api/characterattributes/5968210346965952fcb50c37",
        "Title": ""
      },
      {
        "Rel": "character",
        "Href": "http://beta-api-kuroganehammer.azurewebsites.net/api/characters/name/CaptainFalcon",
        "Title": ""
      }
    ]
  }
]