[{"HitboxActive":{"Frames":"3-27","Adv":"","SD":"","ShieldstunMultiplier":"","RehitRate":"","FacingRestrict":"","SuperArmor":"","HeadMultiplier":"","Intangible":"","SetWeight":false,"GroundOnly":false},"BaseDamage":{"Normal":"","OneVOne":""},"InstanceId":"e62a4c3124f14d5e976d5098333a14d6","Name":"Airdodge","OwnerId":47,"Owner":"Ryu","FirstActionableFrame":"50","Angle":"","BaseKnockBackSetKnockback":"","LandingLag":null,"AutoCancel":null,"KnockbackGrowth":"","MoveType":"ground","IsWeightDependent":false,"Game":"Ultimate","Related":{"Smash4":{"Character":"http://test-khapi.frannsoft.com/api/characters/name/Ryu?game=smash4"},"Ultimate":{"Character":"http://test-khapi.frannsoft.com/api/characters/name/Ryu?game=ultimate","Self":"http://test-khapi.frannsoft.com/api/moves/e62a4c3124f14d5e976d5098333a14d6?game=ultimate"}},"Links":[{"Rel":"self","Href":"http://test-khapi.frannsoft.com/api/moves/e62a4c3124f14d5e976d5098333a14d6?game=ultimate"},{"Rel":"character","Href":"http://test-khapi.frannsoft.com/api/characters/name/Ryu?game=ultimate"}]},{"HitboxActive":{"Frames":"5-16","Adv":"","SD":"","ShieldstunMultiplier":"","RehitRate":"","FacingRestrict":"","SuperArmor":"","HeadMultiplier":"","Intangible":"","SetWeight":false,"GroundOnly":false},"BaseDamage":{"Normal":"","OneVOne":""},"InstanceId":"59ce88678c004137a294bd4117b7eae5","Name":"Back Roll","OwnerId":47,"Owner":"Ryu","FirstActionableFrame":"36","Angle":"","BaseKnockBackSetKnockback":"","LandingLag":null,"AutoCancel":null,"KnockbackGrowth":"","MoveType":"ground","IsWeightDependent":false,"Game":"Ultimate","Related":{"Smash4":{"Character":"http://test-khapi.frannsoft.com/api/characters/name/Ryu?game=smash4"},"Ultimate":{"Character":"http://test-khapi.frannsoft.com/api/characters/name/Ryu?game=ultimate","Self":"http://test-khapi.frannsoft.com/api/moves/59ce88678c004137a294bd4117b7eae5?game=ultimate"}},"Links":[{"Rel":"self","Href":"http://test-khapi.frannsoft.com/api/moves/59ce88678c004137a294bd4117b7eae5?game=ultimate"},{"Rel":"character","Href":"http://test-khapi.frannsoft.com/api/characters/name/Ryu?game=ultimate"}]},{"HitboxActive":{"Frames":"8-9","Adv":"-4","SD":"","ShieldstunMultiplier":"","RehitRate":"","FacingRestrict":"4","SuperArmor":"","HeadMultiplier":"","Intangible":"","SetWeight":false,"GroundOnly":false},"BaseDamage":{"Normal":"16/13","OneVOne":"19.2/15.6"},"InstanceId":"3a2ff084ec6645b4a7ab1929ae6fac3b","Name":"Bair","OwnerId":47,"Owner":"Ryu","FirstActionableFrame":"42","Angle":"361","BaseKnockBackSetKnockback":"21","LandingLag":"10","AutoCancel":"","KnockbackGrowth":"90","MoveType":"aerial","IsWeightDependent":false,"Game":"Ultimate","Related":{"Smash4":{"Character":"http://test-khapi.frannsoft.com/api/characters/name/Ryu?game=smash4"},"Ultimate":{"Character":"http://test-khapi.frannsoft.com/api/characters/name/Ryu?game=ultimate","Self":"http://test-khapi.frannsoft.com/api/moves/3a2ff084ec6645b4a7ab1929ae6fac3b?game=ultimate"}},"Links":[{"Rel":"self","Href":"http://test-khapi.frannsoft.com/api/moves/3a2ff084ec6645b4a7ab1929ae6fac3b?game=ultimate"},{"Rel":"character","Href":"http://test-khapi.frannsoft.com/api/characters/name/Ryu?game=ultimate"}]},{"HitboxActive":null,"BaseDamage":{"Normal":"12","OneVOne":"14.4"},"InstanceId":"e97b3be278fa43f2abaf7b28fe447d25","Name":"Bthrow","OwnerId":47,"Owner":"Ryu","FirstActionableFrame":null,"Angle":"52","BaseKnockBackSetKnockback":"75","LandingLag":null,"AutoCancel":null,"KnockbackGrowth":"45","MoveType":"throw","IsWeightDependent":false,"Game":"Ultimate","Related":{"Smash4":{"Character":"http://test-khapi.frannsoft.com/api/characters/name/Ryu?game=smash4"},"Ultimate":{"Character":"http://test-khapi.frannsoft.com/api/characters/name/Ryu?game=ultimate","Self":"http://test-khapi.frannsoft.com/api/moves/e97b3be278fa43f2abaf7b28fe447d25?game=ultimate"}},"Links":[{"Rel":"self","Href":"http://test-khapi.frannsoft.com/api/moves/e97b3be278fa43f2abaf7b28fe447d25?game=ultimate"},{"Rel":"character","Href":"http://test-khapi.frannsoft.com/api/characters/name/Ryu?game=ultimate"}]},{"HitboxActive":{"Frames":"4-5","Adv":"-19","SD":"","ShieldstunMultiplier":"","RehitRate":"","FacingRestrict":"","SuperArmor":"","HeadMultiplier":"","Intangible":"","SetWeight":false,"GroundOnly":false},"BaseDamage":{"Normal":"6","OneVOne":"7.2"},"InstanceId":"75df3acc2daa4017b1861bcda2e8609a","Name":"Close Ftilt","OwnerId":47,"Owner":"Ryu","FirstActionableFrame":"31","Angle":"180/75","BaseKnockBackSetKnockback":"F: 20/B: 16","LandingLag":null,"AutoCancel":null,"KnockbackGrowth":"100/23","MoveType":"ground","IsWeightDependent":false,"Game":"Ultimate","Related":{"Smash4":{"Character":"http://test-khapi.frannsoft.com/api/characters/name/Ryu?game=smash4"},"Ultimate":{"Character":"http://test-khapi.frannsoft.com/api/characters/name/Ryu?game=ultimate","Self":"http://test-khapi.frannsoft.com/api/moves/75df3acc2daa4017b1861bcda2e8609a?game=ultimate"}},"Links":[{"Rel":"self","Href":"http://test-khapi.frannsoft.com/api/moves/75df3acc2daa4017b1861bcda2e8609a?game=ultimate"},{"Rel":"character","Href":"http://test-khapi.frannsoft.com/api/characters/name/Ryu?game=ultimate"}]},{"HitboxActive":{"Frames":"8-12","Adv":"-9","SD":"","ShieldstunMultiplier":"","RehitRate":"","FacingRestrict":"","SuperArmor":"","HeadMultiplier":"","Intangible":"","SetWeight":false,"GroundOnly":false},"BaseDamage":{"Normal":"15","OneVOne":"18/14.4/13.2"},"InstanceId":"d7082b6ab21e406abed83c081d924817","Name":"Dair","OwnerId":47,"Owner":"Ryu","FirstActionableFrame":"46","Angle":"300/84/48","BaseKnockBackSetKnockback":"10/60/20","LandingLag":"15","AutoCancel":"","KnockbackGrowth":"80/14/80","MoveType":"aerial","IsWeightDependent":false,"Game":"Ultimate","Related":{"Smash4":{"Character":"http://test-khapi.frannsoft.com/api/characters/name/Ryu?game=smash4"},"Ultimate":{"Character":"http://test-khapi.frannsoft.com/api/characters/name/Ryu?game=ultimate","Self":"http://test-khapi.frannsoft.com/api/moves/d7082b6ab21e406abed83c081d924817?game=ultimate"}},"Links":[{"Rel":"self","Href":"http://test-khapi.frannsoft.com/api/moves/d7082b6ab21e406abed83c081d924817?game=ultimate"},{"Rel":"character","Href":"http://test-khapi.frannsoft.com/api/characters/name/Ryu?game=ultimate"}]},{"HitboxActive":{"Frames":"7-9","Adv":"-21","SD":"+2","ShieldstunMultiplier":"","RehitRate":"","FacingRestrict":"","SuperArmor":"","HeadMultiplier":"","Intangible":"","SetWeight":false,"GroundOnly":false},"BaseDamage":{"Normal":"12","OneVOne":"14.4"},"InstanceId":"77947190b5f7421a83fc3acda492c460","Name":"Dash Attack","OwnerId":47,"Owner":"Ryu","FirstActionableFrame":"41","Angle":"50","BaseKnockBackSetKnockback":"80","LandingLag":null,"AutoCancel":null,"KnockbackGrowth":"65","MoveType":"ground","IsWeightDependent":false,"Game":"Ultimate","Related":{"Smash4":{"Character":"http://test-khapi.frannsoft.com/api/characters/name/Ryu?game=smash4"},"Ultimate":{"Character":"http://test-khapi.frannsoft.com/api/characters/name/Ryu?game=ultimate","Self":"http://test-khapi.frannsoft.com/api/moves/77947190b5f7421a83fc3acda492c460?game=ultimate"}},"Links":[{"Rel":"self","Href":"http://test-khapi.frannsoft.com/api/moves/77947190b5f7421a83fc3acda492c460?game=ultimate"},{"Rel":"character","Href":"http://test-khapi.frannsoft.com/api/characters/name/Ryu?game=ultimate"}]},{"HitboxActive":{"Frames":"10-15","Adv":"","SD":"+2","ShieldstunMultiplier":"","RehitRate":"","FacingRestrict":"","SuperArmor":"","HeadMultiplier":"","Intangible":"","SetWeight":false,"GroundOnly":false},"BaseDamage":{"Normal":"8","OneVOne":"9.6"},"InstanceId":"5d56c7a6a08b4c5cb4a3c18541f043f8","Name":"Dash Attack (Late)","OwnerId":47,"Owner":"Ryu","FirstActionableFrame":"-","Angle":"80","BaseKnockBackSetKnockback":"80","LandingLag":null,"AutoCancel":null,"KnockbackGrowth":"60","MoveType":"ground","IsWeightDependent":false,"Game":"Ultimate","Related":{"Smash4":{"Character":"http://test-khapi.frannsoft.com/api/characters/name/Ryu?game=smash4"},"Ultimate":{"Character":"http://test-khapi.frannsoft.com/api/characters/name/Ryu?game=ultimate","Self":"http://test-khapi.frannsoft.com/api/moves/5d56c7a6a08b4c5cb4a3c18541f043f8?game=ultimate"}},"Links":[{"Rel":"self","Href":"http://test-khapi.frannsoft.com/api/moves/5d56c7a6a08b4c5cb4a3c18541f043f8?game=ultimate"},{"Rel":"character","Href":"http://test-khapi.frannsoft.com/api/characters/name/Ryu?game=ultimate"}]},{"HitboxActive":{"Frames":"9-10","Adv":"","SD":"","ShieldstunMultiplier":"","RehitRate":"","FacingRestrict":"","SuperArmor":"","HeadMultiplier":"","Intangible":"","SetWeight":false,"GroundOnly":false},"BaseDamage":{"Normal":"","OneVOne":""},"InstanceId":"87d4ebf049464d79aa38dca8fdc85189","Name":"Dash Grab","OwnerId":47,"Owner":"Ryu","FirstActionableFrame":"43","Angle":"","BaseKnockBackSetKnockback":"","LandingLag":null,"AutoCancel":null,"KnockbackGrowth":"","MoveType":"ground","IsWeightDependent":false,"Game":"Ultimate","Related":{"Smash4":{"Character":"http://test-khapi.frannsoft.com/api/characters/name/Ryu?game=smash4"},"Ultimate":{"Character":"http://test-khapi.frannsoft.com/api/characters/name/Ryu?game=ultimate","Self":"http://test-khapi.frannsoft.com/api/moves/87d4ebf049464d79aa38dca8fdc85189?game=ultimate"}},"Links":[{"Rel":"self","Href":"http://test-khapi.frannsoft.com/api/moves/87d4ebf049464d79aa38dca8fdc85189?game=ultimate"},{"Rel":"character","Href":"http://test-khapi.frannsoft.com/api/characters/name/Ryu?game=ultimate"}]},{"HitboxActive":{"Frames":"3-21","Adv":"","SD":"","ShieldstunMultiplier":"","RehitRate":"","FacingRestrict":"","SuperArmor":"","HeadMultiplier":"","Intangible":"","SetWeight":false,"GroundOnly":false},"BaseDamage":{"Normal":"","OneVOne":""},"InstanceId":"c3aae78c633a41d1ae6ccb634e66a170","Name":"Directional Airdodge (D)","OwnerId":47,"Owner":"Ryu","FirstActionableFrame":"68","Angle":"","BaseKnockBackSetKnockback":"","LandingLag":null,"AutoCancel":null,"KnockbackGrowth":"","MoveType":"ground","IsWeightDependent":false,"Game":"Ultimate","Related":{"Smash4":{"Character":"http://test-khapi.frannsoft.com/api/characters/name/Ryu?game=smash4"},"Ultimate":{"Character":"http://test-khapi.frannsoft.com/api/characters/name/Ryu?game=ultimate","Self":"http://test-khapi.frannsoft.com/api/moves/c3aae78c633a41d1ae6ccb634e66a170?game=ultimate"}},"Links":[{"Rel":"self","Href":"http://test-khapi.frannsoft.com/api/moves/c3aae78c633a41d1ae6ccb634e66a170?game=ultimate"},{"Rel":"character","Href":"http://test-khapi.frannsoft.com/api/characters/name/Ryu?game=ultimate"}]},{"HitboxActive":{"Frames":"3-21","Adv":"","SD":"","ShieldstunMultiplier":"","RehitRate":"","FacingRestrict":"","SuperArmor":"","HeadMultiplier":"","Intangible":"","SetWeight":false,"GroundOnly":false},"BaseDamage":{"Normal":"","OneVOne":""},"InstanceId":"3c8deb5aed3448a9b34ff636f13a93d3","Name":"Directional Airdodge (F/B)","OwnerId":47,"Owner":"Ryu","FirstActionableFrame":"81","Angle":"","BaseKnockBackSetKnockback":"","LandingLag":null,"AutoCancel":null,"KnockbackGrowth":"","MoveType":"ground","IsWeightDependent":false,"Game":"Ultimate","Related":{"Smash4":{"Character":"http://test-khapi.frannsoft.com/api/characters/name/Ryu?game=smash4"},"Ultimate":{"Character":"http://test-khapi.frannsoft.com/api/characters/name/Ryu?game=ultimate","Self":"http://test-khapi.frannsoft.com/api/moves/3c8deb5aed3448a9b34ff636f13a93d3?game=ultimate"}},"Links":[{"Rel":"self","Href":"http://test-khapi.frannsoft.com/api/moves/3c8deb5aed3448a9b34ff636f13a93d3?game=ultimate"},{"Rel":"character","Href":"http://test-khapi.frannsoft.com/api/characters/name/Ryu?game=ultimate"}]},{"HitboxActive":{"Frames":"3-21","Adv":"","SD":"","ShieldstunMultiplier":"","RehitRate":"","FacingRestrict":"","SuperArmor":"","HeadMultiplier":"","Intangible":"","SetWeight":false,"GroundOnly":false},"BaseDamage":{"Normal":"","OneVOne":""},"InstanceId":"3461d4300566467bb7889db4c49f2781","Name":"Directional Airdodge (U)","OwnerId":47,"Owner":"Ryu","FirstActionableFrame":"103","Angle":"","BaseKnockBackSetKnockback":"","LandingLag":null,"AutoCancel":null,"KnockbackGrowth":"","MoveType":"ground","IsWeightDependent":false,"Game":"Ultimate","Related":{"Smash4":{"Character":"http://test-khapi.frannsoft.com/api/characters/name/Ryu?game=smash4"},"Ultimate":{"Character":"http://test-khapi.frannsoft.com/api/characters/name/Ryu?game=ultimate","Self":"http://test-khapi.frannsoft.com/api/moves/3461d4300566467bb7889db4c49f2781?game=ultimate"}},"Links":[{"Rel":"self","Href":"http://test-khapi.frannsoft.com/api/moves/3461d4300566467bb7889db4c49f2781?game=ultimate"},{"Rel":"character","Href":"http://test-khapi.frannsoft.com/api/characters/name/Ryu?game=ultimate"}]},{"HitboxActive":{"Frames":"5-6","Adv":"-25","SD":"","ShieldstunMultiplier":"","RehitRate":"","FacingRestrict":"","SuperArmor":"","HeadMultiplier":"","Intangible":"","SetWeight":false,"GroundOnly":false},"BaseDamage":{"Normal":"16/12/12","OneVOne":"19.2/14.4/14.4"},"InstanceId":"0be812e14d22490fbf57c089599b87e0","Name":"Dsmash","OwnerId":47,"Owner":"Ryu","FirstActionableFrame":"42","Angle":"35/80/80","BaseKnockBackSetKnockback":"50","LandingLag":null,"AutoCancel":null,"KnockbackGrowth":"47/50/50","MoveType":"ground","IsWeightDependent":false,"Game":"Ultimate","Related":{"Smash4":{"Character":"http://test-khapi.frannsoft.com/api/characters/name/Ryu?game=smash4"},"Ultimate":{"Character":"http://test-khapi.frannsoft.com/api/characters/name/Ryu?game=ultimate","Self":"http://test-khapi.frannsoft.com/api/moves/0be812e14d22490fbf57c089599b87e0?game=ultimate"}},"Links":[{"Rel":"self","Href":"http://test-khapi.frannsoft.com/api/moves/0be812e14d22490fbf57c089599b87e0?game=ultimate"},{"Rel":"character","Href":"http://test-khapi.frannsoft.com/api/characters/name/Ryu?game=ultimate"}]},{"HitboxActive":null,"BaseDamage":{"Normal":"3, 3","OneVOne":"3.6, 3.6"},"InstanceId":"d5b2a805265443e094d76397db2b132b","Name":"Dthrow","OwnerId":47,"Owner":"Ryu","FirstActionableFrame":null,"Angle":"76","BaseKnockBackSetKnockback":"50","LandingLag":null,"AutoCancel":null,"KnockbackGrowth":"157","MoveType":"throw","IsWeightDependent":false,"Game":"Ultimate","Related":{"Smash4":{"Character":"http://test-khapi.frannsoft.com/api/characters/name/Ryu?game=smash4"},"Ultimate":{"Character":"http://test-khapi.frannsoft.com/api/characters/name/Ryu?game=ultimate","Self":"http://test-khapi.frannsoft.com/api/moves/d5b2a805265443e094d76397db2b132b?game=ultimate"}},"Links":[{"Rel":"self","Href":"http://test-khapi.frannsoft.com/api/moves/d5b2a805265443e094d76397db2b132b?game=ultimate"},{"Rel":"character","Href":"http://test-khapi.frannsoft.com/api/characters/name/Ryu?game=ultimate"}]},{"HitboxActive":{"Frames":"8-9","Adv":"-6","SD":"","ShieldstunMultiplier":"","RehitRate":"","FacingRestrict":"","SuperArmor":"","HeadMultiplier":"","Intangible":"","SetWeight":false,"GroundOnly":false},"BaseDamage":{"Normal":"14/9","OneVOne":"16.8/10.8"},"InstanceId":"4d46abd9045243ef9030acbe7dba258b","Name":"Fair","OwnerId":47,"Owner":"Ryu","FirstActionableFrame":"37","Angle":"61/70","BaseKnockBackSetKnockback":"82/65","LandingLag":"11","AutoCancel":"","KnockbackGrowth":"56/25","MoveType":"aerial","IsWeightDependent":false,"Game":"Ultimate","Related":{"Smash4":{"Character":"http://test-khapi.frannsoft.com/api/characters/name/Ryu?game=smash4"},"Ultimate":{"Character":"http://test-khapi.frannsoft.com/api/characters/name/Ryu?game=ultimate","Self":"http://test-khapi.frannsoft.com/api/moves/4d46abd9045243ef9030acbe7dba258b?game=ultimate"}},"Links":[{"Rel":"self","Href":"http://test-khapi.frannsoft.com/api/moves/4d46abd9045243ef9030acbe7dba258b?game=ultimate"},{"Rel":"character","Href":"http://test-khapi.frannsoft.com/api/characters/name/Ryu?game=ultimate"}]},{"HitboxActive":{"Frames":"10-14","Adv":"","SD":"","ShieldstunMultiplier":"","RehitRate":"","FacingRestrict":"","SuperArmor":"","HeadMultiplier":"","Intangible":"","SetWeight":false,"GroundOnly":false},"BaseDamage":{"Normal":"12/8","OneVOne":"14.4/9.6"},"InstanceId":"17e97aa01d7d409497d373e735cf7c8c","Name":"Fair (Late)","OwnerId":47,"Owner":"Ryu","FirstActionableFrame":"-","Angle":"61/70","BaseKnockBackSetKnockback":"82/65","LandingLag":"-","AutoCancel":"-","KnockbackGrowth":"56/25","MoveType":"aerial","IsWeightDependent":false,"Game":"Ultimate","Related":{"Smash4":{"Character":"http://test-khapi.frannsoft.com/api/characters/name/Ryu?game=smash4"},"Ultimate":{"Character":"http://test-khapi.frannsoft.com/api/characters/name/Ryu?game=ultimate","Self":"http://test-khapi.frannsoft.com/api/moves/17e97aa01d7d409497d373e735cf7c8c?game=ultimate"}},"Links":[{"Rel":"self","Href":"http://test-khapi.frannsoft.com/api/moves/17e97aa01d7d409497d373e735cf7c8c?game=ultimate"},{"Rel":"character","Href":"http://test-khapi.frannsoft.com/api/characters/name/Ryu?game=ultimate"}]},{"HitboxActive":{"Frames":"Damage Based Armor: 1-69, 14%-28?%, Dash Cancelable from 26","Adv":"","SD":"","ShieldstunMultiplier":"","RehitRate":"","FacingRestrict":"","SuperArmor":"","HeadMultiplier":"","Intangible":"","SetWeight":false,"GroundOnly":false},"BaseDamage":{"Normal":"-","OneVOne":""},"InstanceId":"b140457474734249ab36e9256fd19db9","Name":"Focus Attack","OwnerId":47,"Owner":"Ryu","FirstActionableFrame":"-","Angle":"-","BaseKnockBackSetKnockback":"-","LandingLag":null,"AutoCancel":null,"KnockbackGrowth":"-","MoveType":"special","IsWeightDependent":false,"Game":"Ultimate","Related":{"Smash4":{"Character":"http://test-khapi.frannsoft.com/api/characters/name/Ryu?game=smash4"},"Ultimate":{"Character":"http://test-khapi.frannsoft.com/api/characters/name/Ryu?game=ultimate","Self":"http://test-khapi.frannsoft.com/api/moves/b140457474734249ab36e9256fd19db9?game=ultimate"}},"Links":[{"Rel":"self","Href":"http://test-khapi.frannsoft.com/api/moves/b140457474734249ab36e9256fd19db9?game=ultimate"},{"Rel":"character","Href":"http://test-khapi.frannsoft.com/api/characters/name/Ryu?game=ultimate"}]},{"HitboxActive":{"Frames":"32-33","Adv":"-32","SD":"+15","ShieldstunMultiplier":"","RehitRate":"","FacingRestrict":"","SuperArmor":"","HeadMultiplier":"","Intangible":"","SetWeight":false,"GroundOnly":false},"BaseDamage":{"Normal":"12","OneVOne":"14.4"},"InstanceId":"fd0e938aaa424ddb8879e115303ebad7","Name":"Focus Attack (Stage 1)","OwnerId":47,"Owner":"Ryu","FirstActionableFrame":"77","Angle":"60","BaseKnockBackSetKnockback":"100","LandingLag":null,"AutoCancel":null,"KnockbackGrowth":"10","MoveType":"special","IsWeightDependent":false,"Game":"Ultimate","Related":{"Smash4":{"Character":"http://test-khapi.frannsoft.com/api/characters/name/Ryu?game=smash4"},"Ultimate":{"Character":"http://test-khapi.frannsoft.com/api/characters/name/Ryu?game=ultimate","Self":"http://test-khapi.frannsoft.com/api/moves/fd0e938aaa424ddb8879e115303ebad7?game=ultimate"}},"Links":[{"Rel":"self","Href":"http://test-khapi.frannsoft.com/api/moves/fd0e938aaa424ddb8879e115303ebad7?game=ultimate"},{"Rel":"character","Href":"http://test-khapi.frannsoft.com/api/characters/name/Ryu?game=ultimate"}]},{"HitboxActive":{"Frames":"42-43","Adv":"-34","SD":"+22","ShieldstunMultiplier":"","RehitRate":"","FacingRestrict":"","SuperArmor":"","HeadMultiplier":"","Intangible":"","SetWeight":false,"GroundOnly":false},"BaseDamage":{"Normal":"10","OneVOne":"12"},"InstanceId":"ed52fb0b41da41729cc50b493258f88a","Name":"Focus Attack (Stage 2)","OwnerId":47,"Owner":"Ryu","FirstActionableFrame":"87","Angle":"60","BaseKnockBackSetKnockback":"0","LandingLag":null,"AutoCancel":null,"KnockbackGrowth":"100","MoveType":"special","IsWeightDependent":false,"Game":"Ultimate","Related":{"Smash4":{"Character":"http://test-khapi.frannsoft.com/api/characters/name/Ryu?game=smash4"},"Ultimate":{"Character":"http://test-khapi.frannsoft.com/api/characters/name/Ryu?game=ultimate","Self":"http://test-khapi.frannsoft.com/api/moves/ed52fb0b41da41729cc50b493258f88a?game=ultimate"}},"Links":[{"Rel":"self","Href":"http://test-khapi.frannsoft.com/api/moves/ed52fb0b41da41729cc50b493258f88a?game=ultimate"},{"Rel":"character","Href":"http://test-khapi.frannsoft.com/api/characters/name/Ryu?game=ultimate"}]},{"HitboxActive":{"Frames":"70-71","Adv":"","SD":"","ShieldstunMultiplier":"","RehitRate":"","FacingRestrict":"","SuperArmor":"","HeadMultiplier":"","Intangible":"","SetWeight":false,"GroundOnly":false},"BaseDamage":{"Normal":"17","OneVOne":"20.4"},"InstanceId":"3fb0f81feed34828b6c55532f7d85ea7","Name":"Focus Attack (Stage 3)","OwnerId":47,"Owner":"Ryu","FirstActionableFrame":"115","Angle":"60","BaseKnockBackSetKnockback":"0","LandingLag":null,"AutoCancel":null,"KnockbackGrowth":"100","MoveType":"special","IsWeightDependent":false,"Game":"Ultimate","Related":{"Smash4":{"Character":"http://test-khapi.frannsoft.com/api/characters/name/Ryu?game=smash4"},"Ultimate":{"Character":"http://test-khapi.frannsoft.com/api/characters/name/Ryu?game=ultimate","Self":"http://test-khapi.frannsoft.com/api/moves/3fb0f81feed34828b6c55532f7d85ea7?game=ultimate"}},"Links":[{"Rel":"self","Href":"http://test-khapi.frannsoft.com/api/moves/3fb0f81feed34828b6c55532f7d85ea7?game=ultimate"},{"Rel":"character","Href":"http://test-khapi.frannsoft.com/api/characters/name/Ryu?game=ultimate"}]},{"HitboxActive":{"Frames":"4-15","Adv":"","SD":"","ShieldstunMultiplier":"","RehitRate":"","FacingRestrict":"","SuperArmor":"","HeadMultiplier":"","Intangible":"","SetWeight":false,"GroundOnly":false},"BaseDamage":{"Normal":"","OneVOne":""},"InstanceId":"947451f498774e3882466b084429230c","Name":"Forward Roll","OwnerId":47,"Owner":"Ryu","FirstActionableFrame":"31","Angle":"","BaseKnockBackSetKnockback":"","LandingLag":null,"AutoCancel":null,"KnockbackGrowth":"","MoveType":"ground","IsWeightDependent":false,"Game":"Ultimate","Related":{"Smash4":{"Character":"http://test-khapi.frannsoft.com/api/characters/name/Ryu?game=smash4"},"Ultimate":{"Character":"http://test-khapi.frannsoft.com/api/characters/name/Ryu?game=ultimate","Self":"http://test-khapi.frannsoft.com/api/moves/947451f498774e3882466b084429230c?game=ultimate"}},"Links":[{"Rel":"self","Href":"http://test-khapi.frannsoft.com/api/moves/947451f498774e3882466b084429230c?game=ultimate"},{"Rel":"character","Href":"http://test-khapi.frannsoft.com/api/characters/name/Ryu?game=ultimate"}]},{"HitboxActive":{"Frames":"15-17","Adv":"-18","SD":"","ShieldstunMultiplier":"","RehitRate":"","FacingRestrict":"","SuperArmor":"","HeadMultiplier":"","Intangible":"","SetWeight":false,"GroundOnly":false},"BaseDamage":{"Normal":"16/16/17.5","OneVOne":"19.2/19.2/21"},"InstanceId":"d4ceefd39d4847079fd999030d1c56ee","Name":"Fsmash","OwnerId":47,"Owner":"Ryu","FirstActionableFrame":"46","Angle":"361","BaseKnockBackSetKnockback":"26","LandingLag":null,"AutoCancel":null,"KnockbackGrowth":"98","MoveType":"ground","IsWeightDependent":false,"Game":"Ultimate","Related":{"Smash4":{"Character":"http://test-khapi.frannsoft.com/api/characters/name/Ryu?game=smash4"},"Ultimate":{"Character":"http://test-khapi.frannsoft.com/api/characters/name/Ryu?game=ultimate","Self":"http://test-khapi.frannsoft.com/api/moves/d4ceefd39d4847079fd999030d1c56ee?game=ultimate"}},"Links":[{"Rel":"self","Href":"http://test-khapi.frannsoft.com/api/moves/d4ceefd39d4847079fd999030d1c56ee?game=ultimate"},{"Rel":"character","Href":"http://test-khapi.frannsoft.com/api/characters/name/Ryu?game=ultimate"}]},{"HitboxActive":null,"BaseDamage":{"Normal":"9","OneVOne":"10.8"},"InstanceId":"54584a9b7634402d8a4eac70aee3f486","Name":"Fthrow","OwnerId":47,"Owner":"Ryu","FirstActionableFrame":null,"Angle":"50","BaseKnockBackSetKnockback":"75","LandingLag":null,"AutoCancel":null,"KnockbackGrowth":"45","MoveType":"throw","IsWeightDependent":false,"Game":"Ultimate","Related":{"Smash4":{"Character":"http://test-khapi.frannsoft.com/api/characters/name/Ryu?game=smash4"},"Ultimate":{"Character":"http://test-khapi.frannsoft.com/api/characters/name/Ryu?game=ultimate","Self":"http://test-khapi.frannsoft.com/api/moves/54584a9b7634402d8a4eac70aee3f486?game=ultimate"}},"Links":[{"Rel":"self","Href":"http://test-khapi.frannsoft.com/api/moves/54584a9b7634402d8a4eac70aee3f486?game=ultimate"},{"Rel":"character","Href":"http://test-khapi.frannsoft.com/api/characters/name/Ryu?game=ultimate"}]},{"HitboxActive":{"Frames":"-","Adv":"","SD":"","ShieldstunMultiplier":"","RehitRate":"","FacingRestrict":"","SuperArmor":"","HeadMultiplier":"","Intangible":"","SetWeight":false,"GroundOnly":false},"BaseDamage":{"Normal":"Multiplier: 1.25","OneVOne":""},"InstanceId":"60734f2ab5e14188a485c6b19447dfcb","Name":"Hadoken (Command, All Versions)","OwnerId":47,"Owner":"Ryu","FirstActionableFrame":"58","Angle":"-","BaseKnockBackSetKnockback":"-","LandingLag":null,"AutoCancel":null,"KnockbackGrowth":"-","MoveType":"special","IsWeightDependent":false,"Game":"Ultimate","Related":{"Smash4":{"Character":"http://test-khapi.frannsoft.com/api/characters/name/Ryu?game=smash4"},"Ultimate":{"Character":"http://test-khapi.frannsoft.com/api/characters/name/Ryu?game=ultimate","Self":"http://test-khapi.frannsoft.com/api/moves/60734f2ab5e14188a485c6b19447dfcb?game=ultimate"}},"Links":[{"Rel":"self","Href":"http://test-khapi.frannsoft.com/api/moves/60734f2ab5e14188a485c6b19447dfcb?game=ultimate"},{"Rel":"character","Href":"http://test-khapi.frannsoft.com/api/characters/name/Ryu?game=ultimate"}]},{"HitboxActive":{"Frames":"13-17","Adv":"","SD":"","ShieldstunMultiplier":"","RehitRate":"","FacingRestrict":"","SuperArmor":"","HeadMultiplier":"","Intangible":"","SetWeight":false,"GroundOnly":false},"BaseDamage":{"Normal":"7","OneVOne":"8.4"},"InstanceId":"29a5168272ae4e5aa2cb2aef1cfb9217","Name":"Heavy Hadouken","OwnerId":47,"Owner":"Ryu","FirstActionableFrame":"-","Angle":"0/60","BaseKnockBackSetKnockback":"65","LandingLag":null,"AutoCancel":null,"KnockbackGrowth":"10","MoveType":"special","IsWeightDependent":false,"Game":"Ultimate","Related":{"Smash4":{"Character":"http://test-khapi.frannsoft.com/api/characters/name/Ryu?game=smash4"},"Ultimate":{"Character":"http://test-khapi.frannsoft.com/api/characters/name/Ryu?game=ultimate","Self":"http://test-khapi.frannsoft.com/api/moves/29a5168272ae4e5aa2cb2aef1cfb9217?game=ultimate"}},"Links":[{"Rel":"self","Href":"http://test-khapi.frannsoft.com/api/moves/29a5168272ae4e5aa2cb2aef1cfb9217?game=ultimate"},{"Rel":"character","Href":"http://test-khapi.frannsoft.com/api/characters/name/Ryu?game=ultimate"}]},{"HitboxActive":{"Frames":"18-60","Adv":"","SD":"","ShieldstunMultiplier":"","RehitRate":"","FacingRestrict":"","SuperArmor":"","HeadMultiplier":"","Intangible":"","SetWeight":false,"GroundOnly":false},"BaseDamage":{"Normal":"7","OneVOne":"8.4"},"InstanceId":"67c34433274d48f4bd29ff6e6cd75862","Name":"Heavy Hadouken (Late)","OwnerId":47,"Owner":"Ryu","FirstActionableFrame":"-","Angle":"0/60","BaseKnockBackSetKnockback":"55","LandingLag":null,"AutoCancel":null,"KnockbackGrowth":"10","MoveType":"special","IsWeightDependent":false,"Game":"Ultimate","Related":{"Smash4":{"Character":"http://test-khapi.frannsoft.com/api/characters/name/Ryu?game=smash4"},"Ultimate":{"Character":"http://test-khapi.frannsoft.com/api/characters/name/Ryu?game=ultimate","Self":"http://test-khapi.frannsoft.com/api/moves/67c34433274d48f4bd29ff6e6cd75862?game=ultimate"}},"Links":[{"Rel":"self","Href":"http://test-khapi.frannsoft.com/api/moves/67c34433274d48f4bd29ff6e6cd75862?game=ultimate"},{"Rel":"character","Href":"http://test-khapi.frannsoft.com/api/characters/name/Ryu?game=ultimate"}]},{"HitboxActive":{"Frames":"13-55 (Rehit rate: 1)","Adv":"","SD":"","ShieldstunMultiplier":"","RehitRate":"","FacingRestrict":"","SuperArmor":"","HeadMultiplier":"","Intangible":"","SetWeight":false,"GroundOnly":false},"BaseDamage":{"Normal":"1.1","OneVOne":"1.32"},"InstanceId":"ec10d05bba12486b839edb4ba54ca3ca","Name":"Heavy Shakunetsu Hadouken","OwnerId":47,"Owner":"Ryu","FirstActionableFrame":"-","Angle":"0","BaseKnockBackSetKnockback":"17","LandingLag":null,"AutoCancel":null,"KnockbackGrowth":"10","MoveType":"special","IsWeightDependent":false,"Game":"Ultimate","Related":{"Smash4":{"Character":"http://test-khapi.frannsoft.com/api/characters/name/Ryu?game=smash4"},"Ultimate":{"Character":"http://test-khapi.frannsoft.com/api/characters/name/Ryu?game=ultimate","Self":"http://test-khapi.frannsoft.com/api/moves/ec10d05bba12486b839edb4ba54ca3ca?game=ultimate"}},"Links":[{"Rel":"self","Href":"http://test-khapi.frannsoft.com/api/moves/ec10d05bba12486b839edb4ba54ca3ca?game=ultimate"},{"Rel":"character","Href":"http://test-khapi.frannsoft.com/api/characters/name/Ryu?game=ultimate"}]},{"HitboxActive":{"Frames":"6","Adv":"","SD":"","ShieldstunMultiplier":"","RehitRate":"","FacingRestrict":"","SuperArmor":"","HeadMultiplier":"","Intangible":"","SetWeight":false,"GroundOnly":false},"BaseDamage":{"Normal":"14","OneVOne":"16.8"},"InstanceId":"c04a78f1f75047d89c98f628502e8ccb","Name":"Heavy Shoryuken (Aerial, Early)","OwnerId":47,"Owner":"Ryu","FirstActionableFrame":"-","Angle":"80","BaseKnockBackSetKnockback":"80","LandingLag":null,"AutoCancel":null,"KnockbackGrowth":"60","MoveType":"special","IsWeightDependent":false,"Game":"Ultimate","Related":{"Smash4":{"Character":"http://test-khapi.frannsoft.com/api/characters/name/Ryu?game=smash4"},"Ultimate":{"Character":"http://test-khapi.frannsoft.com/api/characters/name/Ryu?game=ultimate","Self":"http://test-khapi.frannsoft.com/api/moves/c04a78f1f75047d89c98f628502e8ccb?game=ultimate"}},"Links":[{"Rel":"self","Href":"http://test-khapi.frannsoft.com/api/moves/c04a78f1f75047d89c98f628502e8ccb?game=ultimate"},{"Rel":"character","Href":"http://test-khapi.frannsoft.com/api/characters/name/Ryu?game=ultimate"}]},{"HitboxActive":{"Frames":"6","Adv":"","SD":"","ShieldstunMultiplier":"","RehitRate":"","FacingRestrict":"","SuperArmor":"","HeadMultiplier":"","Intangible":"","SetWeight":false,"GroundOnly":false},"BaseDamage":{"Normal":"15","OneVOne":"18"},"InstanceId":"08c9b8feb98b44ad96438c67325b80aa","Name":"Heavy Shoryuken (Grounded, Early)","OwnerId":47,"Owner":"Ryu","FirstActionableFrame":"-","Angle":"80","BaseKnockBackSetKnockback":"80","LandingLag":null,"AutoCancel":null,"KnockbackGrowth":"69","MoveType":"special","IsWeightDependent":false,"Game":"Ultimate","Related":{"Smash4":{"Character":"http://test-khapi.frannsoft.com/api/characters/name/Ryu?game=smash4"},"Ultimate":{"Character":"http://test-khapi.frannsoft.com/api/characters/name/Ryu?game=ultimate","Self":"http://test-khapi.frannsoft.com/api/moves/08c9b8feb98b44ad96438c67325b80aa?game=ultimate"}},"Links":[{"Rel":"self","Href":"http://test-khapi.frannsoft.com/api/moves/08c9b8feb98b44ad96438c67325b80aa?game=ultimate"},{"Rel":"character","Href":"http://test-khapi.frannsoft.com/api/characters/name/Ryu?game=ultimate"}]},{"HitboxActive":{"Frames":"21-23, 37-39","Adv":"","SD":"","ShieldstunMultiplier":"","RehitRate":"","FacingRestrict":"","SuperArmor":"","HeadMultiplier":"","Intangible":"","SetWeight":false,"GroundOnly":false},"BaseDamage":{"Normal":"10","OneVOne":"12"},"InstanceId":"92ed3a72dc4b4975aff0abda88472f5d","Name":"Heavy Tatsumaki Senpukyaku (Aerial)","OwnerId":47,"Owner":"Ryu","FirstActionableFrame":"-","Angle":"50","BaseKnockBackSetKnockback":"80","LandingLag":null,"AutoCancel":null,"KnockbackGrowth":"65","MoveType":"special","IsWeightDependent":false,"Game":"Ultimate","Related":{"Smash4":{"Character":"http://test-khapi.frannsoft.com/api/characters/name/Ryu?game=smash4"},"Ultimate":{"Character":"http://test-khapi.frannsoft.com/api/characters/name/Ryu?game=ultimate","Self":"http://test-khapi.frannsoft.com/api/moves/92ed3a72dc4b4975aff0abda88472f5d?game=ultimate"}},"Links":[{"Rel":"self","Href":"http://test-khapi.frannsoft.com/api/moves/92ed3a72dc4b4975aff0abda88472f5d?game=ultimate"},{"Rel":"character","Href":"http://test-khapi.frannsoft.com/api/characters/name/Ryu?game=ultimate"}]},{"HitboxActive":{"Frames":"13-15, 29-31","Adv":"","SD":"","ShieldstunMultiplier":"","RehitRate":"","FacingRestrict":"","SuperArmor":"","HeadMultiplier":"","Intangible":"13-44","SetWeight":false,"GroundOnly":false},"BaseDamage":{"Normal":"10","OneVOne":"12"},"InstanceId":"a5b37e037ff84b7f8760859dccdf3d02","Name":"Heavy Tatsumaki Senpukyaku (Aerial)","OwnerId":47,"Owner":"Ryu","FirstActionableFrame":"80","Angle":"70","BaseKnockBackSetKnockback":"80","LandingLag":null,"AutoCancel":null,"KnockbackGrowth":"75","MoveType":"special","IsWeightDependent":false,"Game":"Ultimate","Related":{"Smash4":{"Character":"http://test-khapi.frannsoft.com/api/characters/name/Ryu?game=smash4"},"Ultimate":{"Character":"http://test-khapi.frannsoft.com/api/characters/name/Ryu?game=ultimate","Self":"http://test-khapi.frannsoft.com/api/moves/a5b37e037ff84b7f8760859dccdf3d02?game=ultimate"}},"Links":[{"Rel":"self","Href":"http://test-khapi.frannsoft.com/api/moves/a5b37e037ff84b7f8760859dccdf3d02?game=ultimate"},{"Rel":"character","Href":"http://test-khapi.frannsoft.com/api/characters/name/Ryu?game=ultimate"}]},{"HitboxActive":{"Frames":"21-23, 37-39, 53-55","Adv":"","SD":"","ShieldstunMultiplier":"","RehitRate":"","FacingRestrict":"","SuperArmor":"","HeadMultiplier":"","Intangible":"","SetWeight":false,"GroundOnly":false},"BaseDamage":{"Normal":"11","OneVOne":"13.2"},"InstanceId":"ff09fe57b46a4ee9840b623b6806091a","Name":"Heavy Tatsumaki Senpukyaku (Grounded)","OwnerId":47,"Owner":"Ryu","FirstActionableFrame":"-","Angle":"50","BaseKnockBackSetKnockback":"80","LandingLag":null,"AutoCancel":null,"KnockbackGrowth":"65","MoveType":"special","IsWeightDependent":false,"Game":"Ultimate","Related":{"Smash4":{"Character":"http://test-khapi.frannsoft.com/api/characters/name/Ryu?game=smash4"},"Ultimate":{"Character":"http://test-khapi.frannsoft.com/api/characters/name/Ryu?game=ultimate","Self":"http://test-khapi.frannsoft.com/api/moves/ff09fe57b46a4ee9840b623b6806091a?game=ultimate"}},"Links":[{"Rel":"self","Href":"http://test-khapi.frannsoft.com/api/moves/ff09fe57b46a4ee9840b623b6806091a?game=ultimate"},{"Rel":"character","Href":"http://test-khapi.frannsoft.com/api/characters/name/Ryu?game=ultimate"}]},{"HitboxActive":{"Frames":"13-15, 29-31, 45-47","Adv":"","SD":"","ShieldstunMultiplier":"","RehitRate":"","FacingRestrict":"","SuperArmor":"","HeadMultiplier":"","Intangible":"13-60","SetWeight":false,"GroundOnly":false},"BaseDamage":{"Normal":"11","OneVOne":"13.2"},"InstanceId":"4c5f41e5b8504f94b889d70bbc2275c6","Name":"Heavy Tatsumaki Senpukyaku (Grounded)","OwnerId":47,"Owner":"Ryu","FirstActionableFrame":"91","Angle":"70","BaseKnockBackSetKnockback":"80","LandingLag":null,"AutoCancel":null,"KnockbackGrowth":"75","MoveType":"special","IsWeightDependent":false,"Game":"Ultimate","Related":{"Smash4":{"Character":"http://test-khapi.frannsoft.com/api/characters/name/Ryu?game=smash4"},"Ultimate":{"Character":"http://test-khapi.frannsoft.com/api/characters/name/Ryu?game=ultimate","Self":"http://test-khapi.frannsoft.com/api/moves/4c5f41e5b8504f94b889d70bbc2275c6?game=ultimate"}},"Links":[{"Rel":"self","Href":"http://test-khapi.frannsoft.com/api/moves/4c5f41e5b8504f94b889d70bbc2275c6?game=ultimate"},{"Rel":"character","Href":"http://test-khapi.frannsoft.com/api/characters/name/Ryu?game=ultimate"}]},{"HitboxActive":{"Frames":"9-10","Adv":"-13","SD":"","ShieldstunMultiplier":"","RehitRate":"","FacingRestrict":"","SuperArmor":"","HeadMultiplier":"","Intangible":"","SetWeight":false,"GroundOnly":false},"BaseDamage":{"Normal":"10","OneVOne":"12"},"InstanceId":"729318001ac54e98a1206b6dda364cf4","Name":"Jab 1 (Held, Far)","OwnerId":47,"Owner":"Ryu","FirstActionableFrame":"33","Angle":"50","BaseKnockBackSetKnockback":"40","LandingLag":null,"AutoCancel":null,"KnockbackGrowth":"110","MoveType":"ground","IsWeightDependent":false,"Game":"Ultimate","Related":{"Smash4":{"Character":"http://test-khapi.frannsoft.com/api/characters/name/Ryu?game=smash4"},"Ultimate":{"Character":"http://test-khapi.frannsoft.com/api/characters/name/Ryu?game=ultimate","Self":"http://test-khapi.frannsoft.com/api/moves/729318001ac54e98a1206b6dda364cf4?game=ultimate"}},"Links":[{"Rel":"self","Href":"http://test-khapi.frannsoft.com/api/moves/729318001ac54e98a1206b6dda364cf4?game=ultimate"},{"Rel":"character","Href":"http://test-khapi.frannsoft.com/api/characters/name/Ryu?game=ultimate"}]},{"HitboxActive":{"Frames":"3-4","Adv":"-21","SD":"","ShieldstunMultiplier":"","RehitRate":"","FacingRestrict":"","SuperArmor":"","HeadMultiplier":"","Intangible":"","SetWeight":false,"GroundOnly":false},"BaseDamage":{"Normal":"1.5","OneVOne":"1.8"},"InstanceId":"2d349e385f7444f6b3b36cd6325fa3af","Name":"Jab 2","OwnerId":47,"Owner":"Ryu","FirstActionableFrame":"28","Angle":"361","BaseKnockBackSetKnockback":"25/20","LandingLag":null,"AutoCancel":null,"KnockbackGrowth":"25","MoveType":"ground","IsWeightDependent":false,"Game":"Ultimate","Related":{"Smash4":{"Character":"http://test-khapi.frannsoft.com/api/characters/name/Ryu?game=smash4"},"Ultimate":{"Character":"http://test-khapi.frannsoft.com/api/characters/name/Ryu?game=ultimate","Self":"http://test-khapi.frannsoft.com/api/moves/2d349e385f7444f6b3b36cd6325fa3af?game=ultimate"}},"Links":[{"Rel":"self","Href":"http://test-khapi.frannsoft.com/api/moves/2d349e385f7444f6b3b36cd6325fa3af?game=ultimate"},{"Rel":"character","Href":"http://test-khapi.frannsoft.com/api/characters/name/Ryu?game=ultimate"}]},{"HitboxActive":{"Frames":"8-10","Adv":"-21","SD":"","ShieldstunMultiplier":"","RehitRate":"","FacingRestrict":"","SuperArmor":"","HeadMultiplier":"","Intangible":"","SetWeight":false,"GroundOnly":false},"BaseDamage":{"Normal":"5","OneVOne":"6"},"InstanceId":"b5c44941f52f4547b92ea3f44f493192","Name":"Jab 3","OwnerId":47,"Owner":"Ryu","FirstActionableFrame":"36","Angle":"45","BaseKnockBackSetKnockback":"70","LandingLag":null,"AutoCancel":null,"KnockbackGrowth":"50","MoveType":"ground","IsWeightDependent":false,"Game":"Ultimate","Related":{"Smash4":{"Character":"http://test-khapi.frannsoft.com/api/characters/name/Ryu?game=smash4"},"Ultimate":{"Character":"http://test-khapi.frannsoft.com/api/characters/name/Ryu?game=ultimate","Self":"http://test-khapi.frannsoft.com/api/moves/b5c44941f52f4547b92ea3f44f493192?game=ultimate"}},"Links":[{"Rel":"self","Href":"http://test-khapi.frannsoft.com/api/moves/b5c44941f52f4547b92ea3f44f493192?game=ultimate"},{"Rel":"character","Href":"http://test-khapi.frannsoft.com/api/characters/name/Ryu?game=ultimate"}]},{"HitboxActive":{"Frames":"3-4","Adv":"-9","SD":"","ShieldstunMultiplier":"","RehitRate":"","FacingRestrict":"","SuperArmor":"","HeadMultiplier":"","Intangible":"","SetWeight":false,"GroundOnly":false},"BaseDamage":{"Normal":"1.6","OneVOne":"1.92"},"InstanceId":"2c98e845b2024dbabb960c731a458fb6","Name":"Light Dtilt","OwnerId":47,"Owner":"Ryu","FirstActionableFrame":"16","Angle":"65/65/60","BaseKnockBackSetKnockback":"F: 9/11/5","LandingLag":null,"AutoCancel":null,"KnockbackGrowth":"100","MoveType":"ground","IsWeightDependent":false,"Game":"Ultimate","Related":{"Smash4":{"Character":"http://test-khapi.frannsoft.com/api/characters/name/Ryu?game=smash4"},"Ultimate":{"Character":"http://test-khapi.frannsoft.com/api/characters/name/Ryu?game=ultimate","Self":"http://test-khapi.frannsoft.com/api/moves/2c98e845b2024dbabb960c731a458fb6?game=ultimate"}},"Links":[{"Rel":"self","Href":"http://test-khapi.frannsoft.com/api/moves/2c98e845b2024dbabb960c731a458fb6?game=ultimate"},{"Rel":"character","Href":"http://test-khapi.frannsoft.com/api/characters/name/Ryu?game=ultimate"}]},{"HitboxActive":{"Frames":"9-12","Adv":"-8","SD":"","ShieldstunMultiplier":"","RehitRate":"","FacingRestrict":"","SuperArmor":"","HeadMultiplier":"","Intangible":"","SetWeight":false,"GroundOnly":false},"BaseDamage":{"Normal":"6.8","OneVOne":"8.16"},"InstanceId":"df84b153288e4943939e1642fba5498f","Name":"Light Ftilt","OwnerId":47,"Owner":"Ryu","FirstActionableFrame":"25","Angle":"55/72","BaseKnockBackSetKnockback":"66","LandingLag":null,"AutoCancel":null,"KnockbackGrowth":"46","MoveType":"ground","IsWeightDependent":false,"Game":"Ultimate","Related":{"Smash4":{"Character":"http://test-khapi.frannsoft.com/api/characters/name/Ryu?game=smash4"},"Ultimate":{"Character":"http://test-khapi.frannsoft.com/api/characters/name/Ryu?game=ultimate","Self":"http://test-khapi.frannsoft.com/api/moves/df84b153288e4943939e1642fba5498f?game=ultimate"}},"Links":[{"Rel":"self","Href":"http://test-khapi.frannsoft.com/api/moves/df84b153288e4943939e1642fba5498f?game=ultimate"},{"Rel":"character","Href":"http://test-khapi.frannsoft.com/api/characters/name/Ryu?game=ultimate"}]},{"HitboxActive":{"Frames":"13-19","Adv":"","SD":"","ShieldstunMultiplier":"","RehitRate":"","FacingRestrict":"","SuperArmor":"","HeadMultiplier":"","Intangible":"","SetWeight":false,"GroundOnly":false},"BaseDamage":{"Normal":"6","OneVOne":"7.2"},"InstanceId":"b56c222fcf474e0ca449c8f5eb8512bc","Name":"Light Hadouken","OwnerId":47,"Owner":"Ryu","FirstActionableFrame":"-","Angle":"0/60","BaseKnockBackSetKnockback":"65","LandingLag":null,"AutoCancel":null,"KnockbackGrowth":"10","MoveType":"special","IsWeightDependent":false,"Game":"Ultimate","Related":{"Smash4":{"Character":"http://test-khapi.frannsoft.com/api/characters/name/Ryu?game=smash4"},"Ultimate":{"Character":"http://test-khapi.frannsoft.com/api/characters/name/Ryu?game=ultimate","Self":"http://test-khapi.frannsoft.com/api/moves/b56c222fcf474e0ca449c8f5eb8512bc?game=ultimate"}},"Links":[{"Rel":"self","Href":"http://test-khapi.frannsoft.com/api/moves/b56c222fcf474e0ca449c8f5eb8512bc?game=ultimate"},{"Rel":"character","Href":"http://test-khapi.frannsoft.com/api/characters/name/Ryu?game=ultimate"}]},{"HitboxActive":{"Frames":"20-75","Adv":"","SD":"","ShieldstunMultiplier":"","RehitRate":"","FacingRestrict":"","SuperArmor":"","HeadMultiplier":"","Intangible":"","SetWeight":false,"GroundOnly":false},"BaseDamage":{"Normal":"6","OneVOne":"7.2"},"InstanceId":"3ef1e181d051452580c2994412c0b6ed","Name":"Light Hadouken (Late)","OwnerId":47,"Owner":"Ryu","FirstActionableFrame":"58","Angle":"0/60","BaseKnockBackSetKnockback":"55","LandingLag":null,"AutoCancel":null,"KnockbackGrowth":"10","MoveType":"special","IsWeightDependent":false,"Game":"Ultimate","Related":{"Smash4":{"Character":"http://test-khapi.frannsoft.com/api/characters/name/Ryu?game=smash4"},"Ultimate":{"Character":"http://test-khapi.frannsoft.com/api/characters/name/Ryu?game=ultimate","Self":"http://test-khapi.frannsoft.com/api/moves/3ef1e181d051452580c2994412c0b6ed?game=ultimate"}},"Links":[{"Rel":"self","Href":"http://test-khapi.frannsoft.com/api/moves/3ef1e181d051452580c2994412c0b6ed?game=ultimate"},{"Rel":"character","Href":"http://test-khapi.frannsoft.com/api/characters/name/Ryu?game=ultimate"}]},{"HitboxActive":{"Frames":"3-4","Adv":"-10","SD":"","ShieldstunMultiplier":"","RehitRate":"","FacingRestrict":"","SuperArmor":"","HeadMultiplier":"","Intangible":"","SetWeight":false,"GroundOnly":false},"BaseDamage":{"Normal":"1.5","OneVOne":"1.8"},"InstanceId":"34c96ad4bb9b47ed955ff1222eb318dd","Name":"Light Jab 1","OwnerId":47,"Owner":"Ryu","FirstActionableFrame":"17","Angle":"180/361/361/361","BaseKnockBackSetKnockback":"20/30/25/20","LandingLag":null,"AutoCancel":null,"KnockbackGrowth":"20/30/28/20","MoveType":"ground","IsWeightDependent":false,"Game":"Ultimate","Related":{"Smash4":{"Character":"http://test-khapi.frannsoft.com/api/characters/name/Ryu?game=smash4"},"Ultimate":{"Character":"http://test-khapi.frannsoft.com/api/characters/name/Ryu?game=ultimate","Self":"http://test-khapi.frannsoft.com/api/moves/34c96ad4bb9b47ed955ff1222eb318dd?game=ultimate"}},"Links":[{"Rel":"self","Href":"http://test-khapi.frannsoft.com/api/moves/34c96ad4bb9b47ed955ff1222eb318dd?game=ultimate"},{"Rel":"character","Href":"http://test-khapi.frannsoft.com/api/characters/name/Ryu?game=ultimate"}]},{"HitboxActive":{"Frames":"13-68 (Rehit rate: 1)","Adv":"","SD":"","ShieldstunMultiplier":"","RehitRate":"","FacingRestrict":"","SuperArmor":"","HeadMultiplier":"","Intangible":"","SetWeight":false,"GroundOnly":false},"BaseDamage":{"Normal":"1.1","OneVOne":"1.32"},"InstanceId":"db2adbe4e8b64190b345154493cb316f","Name":"Light Shakunetsu Hadouken","OwnerId":47,"Owner":"Ryu","FirstActionableFrame":"-","Angle":"0","BaseKnockBackSetKnockback":"17","LandingLag":null,"AutoCancel":null,"KnockbackGrowth":"10","MoveType":"special","IsWeightDependent":false,"Game":"Ultimate","Related":{"Smash4":{"Character":"http://test-khapi.frannsoft.com/api/characters/name/Ryu?game=smash4"},"Ultimate":{"Character":"http://test-khapi.frannsoft.com/api/characters/name/Ryu?game=ultimate","Self":"http://test-khapi.frannsoft.com/api/moves/db2adbe4e8b64190b345154493cb316f?game=ultimate"}},"Links":[{"Rel":"self","Href":"http://test-khapi.frannsoft.com/api/moves/db2adbe4e8b64190b345154493cb316f?game=ultimate"},{"Rel":"character","Href":"http://test-khapi.frannsoft.com/api/characters/name/Ryu?game=ultimate"}]},{"HitboxActive":{"Frames":"6","Adv":"","SD":"","ShieldstunMultiplier":"","RehitRate":"","FacingRestrict":"","SuperArmor":"","HeadMultiplier":"","Intangible":"","SetWeight":false,"GroundOnly":false},"BaseDamage":{"Normal":"12","OneVOne":"14.4"},"InstanceId":"3f0f3e9b9d7d44fea1e87f5c15c1e875","Name":"Light Shoryuken (Aerial, Early)","OwnerId":47,"Owner":"Ryu","FirstActionableFrame":"-","Angle":"80","BaseKnockBackSetKnockback":"80","LandingLag":null,"AutoCancel":null,"KnockbackGrowth":"49","MoveType":"special","IsWeightDependent":false,"Game":"Ultimate","Related":{"Smash4":{"Character":"http://test-khapi.frannsoft.com/api/characters/name/Ryu?game=smash4"},"Ultimate":{"Character":"http://test-khapi.frannsoft.com/api/characters/name/Ryu?game=ultimate","Self":"http://test-khapi.frannsoft.com/api/moves/3f0f3e9b9d7d44fea1e87f5c15c1e875?game=ultimate"}},"Links":[{"Rel":"self","Href":"http://test-khapi.frannsoft.com/api/moves/3f0f3e9b9d7d44fea1e87f5c15c1e875?game=ultimate"},{"Rel":"character","Href":"http://test-khapi.frannsoft.com/api/characters/name/Ryu?game=ultimate"}]},{"HitboxActive":{"Frames":"6","Adv":"","SD":"","ShieldstunMultiplier":"","RehitRate":"","FacingRestrict":"","SuperArmor":"","HeadMultiplier":"","Intangible":"","SetWeight":false,"GroundOnly":false},"BaseDamage":{"Normal":"13","OneVOne":"15.6"},"InstanceId":"a2bacdfcd7b94515bbee1c0eb2430208","Name":"Light Shoryuken (Grounded, Early)","OwnerId":47,"Owner":"Ryu","FirstActionableFrame":"-","Angle":"80","BaseKnockBackSetKnockback":"80","LandingLag":null,"AutoCancel":null,"KnockbackGrowth":"58","MoveType":"special","IsWeightDependent":false,"Game":"Ultimate","Related":{"Smash4":{"Character":"http://test-khapi.frannsoft.com/api/characters/name/Ryu?game=smash4"},"Ultimate":{"Character":"http://test-khapi.frannsoft.com/api/characters/name/Ryu?game=ultimate","Self":"http://test-khapi.frannsoft.com/api/moves/a2bacdfcd7b94515bbee1c0eb2430208?game=ultimate"}},"Links":[{"Rel":"self","Href":"http://test-khapi.frannsoft.com/api/moves/a2bacdfcd7b94515bbee1c0eb2430208?game=ultimate"},{"Rel":"character","Href":"http://test-khapi.frannsoft.com/api/characters/name/Ryu?game=ultimate"}]},{"HitboxActive":{"Frames":"21-23, 37-39","Adv":"","SD":"","ShieldstunMultiplier":"","RehitRate":"","FacingRestrict":"","SuperArmor":"","HeadMultiplier":"","Intangible":"","SetWeight":false,"GroundOnly":false},"BaseDamage":{"Normal":"7","OneVOne":"8.4"},"InstanceId":"1e9c7f7cb0eb4e42bc5839b6860aee29","Name":"Light Tatsumaki Senpukyaku (Aerial)","OwnerId":47,"Owner":"Ryu","FirstActionableFrame":"-","Angle":"50","BaseKnockBackSetKnockback":"80","LandingLag":null,"AutoCancel":null,"KnockbackGrowth":"50","MoveType":"special","IsWeightDependent":false,"Game":"Ultimate","Related":{"Smash4":{"Character":"http://test-khapi.frannsoft.com/api/characters/name/Ryu?game=smash4"},"Ultimate":{"Character":"http://test-khapi.frannsoft.com/api/characters/name/Ryu?game=ultimate","Self":"http://test-khapi.frannsoft.com/api/moves/1e9c7f7cb0eb4e42bc5839b6860aee29?game=ultimate"}},"Links":[{"Rel":"self","Href":"http://test-khapi.frannsoft.com/api/moves/1e9c7f7cb0eb4e42bc5839b6860aee29?game=ultimate"},{"Rel":"character","Href":"http://test-khapi.frannsoft.com/api/characters/name/Ryu?game=ultimate"}]},{"HitboxActive":{"Frames":"13-15, 29-31","Adv":"","SD":"","ShieldstunMultiplier":"","RehitRate":"","FacingRestrict":"","SuperArmor":"","HeadMultiplier":"","Intangible":"13-44","SetWeight":false,"GroundOnly":false},"BaseDamage":{"Normal":"8","OneVOne":"9.6"},"InstanceId":"97e9a0c42c754f2983382d168a3e6fbd","Name":"Light Tatsumaki Senpukyaku (Aerial)","OwnerId":47,"Owner":"Ryu","FirstActionableFrame":"80","Angle":"55","BaseKnockBackSetKnockback":"80","LandingLag":null,"AutoCancel":null,"KnockbackGrowth":"60","MoveType":"special","IsWeightDependent":false,"Game":"Ultimate","Related":{"Smash4":{"Character":"http://test-khapi.frannsoft.com/api/characters/name/Ryu?game=smash4"},"Ultimate":{"Character":"http://test-khapi.frannsoft.com/api/characters/name/Ryu?game=ultimate","Self":"http://test-khapi.frannsoft.com/api/moves/97e9a0c42c754f2983382d168a3e6fbd?game=ultimate"}},"Links":[{"Rel":"self","Href":"http://test-khapi.frannsoft.com/api/moves/97e9a0c42c754f2983382d168a3e6fbd?game=ultimate"},{"Rel":"character","Href":"http://test-khapi.frannsoft.com/api/characters/name/Ryu?game=ultimate"}]},{"HitboxActive":{"Frames":"21-23","Adv":"","SD":"","ShieldstunMultiplier":"","RehitRate":"","FacingRestrict":"","SuperArmor":"","HeadMultiplier":"","Intangible":"","SetWeight":false,"GroundOnly":false},"BaseDamage":{"Normal":"8","OneVOne":"9.6"},"InstanceId":"3172383919af42f7910e9cc3c59970d7","Name":"Light Tatsumaki Senpukyaku (Grounded)","OwnerId":47,"Owner":"Ryu","FirstActionableFrame":"-","Angle":"50","BaseKnockBackSetKnockback":"80","LandingLag":null,"AutoCancel":null,"KnockbackGrowth":"50","MoveType":"special","IsWeightDependent":false,"Game":"Ultimate","Related":{"Smash4":{"Character":"http://test-khapi.frannsoft.com/api/characters/name/Ryu?game=smash4"},"Ultimate":{"Character":"http://test-khapi.frannsoft.com/api/characters/name/Ryu?game=ultimate","Self":"http://test-khapi.frannsoft.com/api/moves/3172383919af42f7910e9cc3c59970d7?game=ultimate"}},"Links":[{"Rel":"self","Href":"http://test-khapi.frannsoft.com/api/moves/3172383919af42f7910e9cc3c59970d7?game=ultimate"},{"Rel":"character","Href":"http://test-khapi.frannsoft.com/api/characters/name/Ryu?game=ultimate"}]},{"HitboxActive":{"Frames":"13-15","Adv":"","SD":"","ShieldstunMultiplier":"","RehitRate":"","FacingRestrict":"","SuperArmor":"","HeadMultiplier":"","Intangible":"13-28","SetWeight":false,"GroundOnly":false},"BaseDamage":{"Normal":"9","OneVOne":"10.8"},"InstanceId":"722d4ce2009846449a9b8b097171c1dd","Name":"Light Tatsumaki Senpukyaku (Grounded)","OwnerId":47,"Owner":"Ryu","FirstActionableFrame":"59","Angle":"55","BaseKnockBackSetKnockback":"80","LandingLag":null,"AutoCancel":null,"KnockbackGrowth":"60","MoveType":"special","IsWeightDependent":false,"Game":"Ultimate","Related":{"Smash4":{"Character":"http://test-khapi.frannsoft.com/api/characters/name/Ryu?game=smash4"},"Ultimate":{"Character":"http://test-khapi.frannsoft.com/api/characters/name/Ryu?game=ultimate","Self":"http://test-khapi.frannsoft.com/api/moves/722d4ce2009846449a9b8b097171c1dd?game=ultimate"}},"Links":[{"Rel":"self","Href":"http://test-khapi.frannsoft.com/api/moves/722d4ce2009846449a9b8b097171c1dd?game=ultimate"},{"Rel":"character","Href":"http://test-khapi.frannsoft.com/api/characters/name/Ryu?game=ultimate"}]},{"HitboxActive":{"Frames":"4-7","Adv":"-8","SD":"","ShieldstunMultiplier":"","RehitRate":"","FacingRestrict":"","SuperArmor":"","HeadMultiplier":"","Intangible":"","SetWeight":false,"GroundOnly":false},"BaseDamage":{"Normal":"2","OneVOne":"2.4"},"InstanceId":"64724c3044934849abb4ecad9a46ee99","Name":"Light Utilt","OwnerId":47,"Owner":"Ryu","FirstActionableFrame":"16","Angle":"90/90/66/66","BaseKnockBackSetKnockback":"19","LandingLag":null,"AutoCancel":null,"KnockbackGrowth":"75","MoveType":"ground","IsWeightDependent":false,"Game":"Ultimate","Related":{"Smash4":{"Character":"http://test-khapi.frannsoft.com/api/characters/name/Ryu?game=smash4"},"Ultimate":{"Character":"http://test-khapi.frannsoft.com/api/characters/name/Ryu?game=ultimate","Self":"http://test-khapi.frannsoft.com/api/moves/64724c3044934849abb4ecad9a46ee99?game=ultimate"}},"Links":[{"Rel":"self","Href":"http://test-khapi.frannsoft.com/api/moves/64724c3044934849abb4ecad9a46ee99?game=ultimate"},{"Rel":"character","Href":"http://test-khapi.frannsoft.com/api/characters/name/Ryu?game=ultimate"}]},{"HitboxActive":{"Frames":"6-7","Adv":"-14","SD":"","ShieldstunMultiplier":"","RehitRate":"","FacingRestrict":"","SuperArmor":"","HeadMultiplier":"","Intangible":"","SetWeight":false,"GroundOnly":false},"BaseDamage":{"Normal":"7/5.5","OneVOne":"8.4/6.6"},"InstanceId":"e508e42da9664e43b6f35674d9affcd3","Name":"Medium Dtilt","OwnerId":47,"Owner":"Ryu","FirstActionableFrame":"28","Angle":"64","BaseKnockBackSetKnockback":"70","LandingLag":null,"AutoCancel":null,"KnockbackGrowth":"23","MoveType":"ground","IsWeightDependent":false,"Game":"Ultimate","Related":{"Smash4":{"Character":"http://test-khapi.frannsoft.com/api/characters/name/Ryu?game=smash4"},"Ultimate":{"Character":"http://test-khapi.frannsoft.com/api/characters/name/Ryu?game=ultimate","Self":"http://test-khapi.frannsoft.com/api/moves/e508e42da9664e43b6f35674d9affcd3?game=ultimate"}},"Links":[{"Rel":"self","Href":"http://test-khapi.frannsoft.com/api/moves/e508e42da9664e43b6f35674d9affcd3?game=ultimate"},{"Rel":"character","Href":"http://test-khapi.frannsoft.com/api/characters/name/Ryu?game=ultimate"}]},{"HitboxActive":{"Frames":"16","Adv":"","SD":"+8","ShieldstunMultiplier":"","RehitRate":"","FacingRestrict":"","SuperArmor":"","HeadMultiplier":"","Intangible":"","SetWeight":false,"GroundOnly":false},"BaseDamage":{"Normal":"3","OneVOne":"3.6"},"InstanceId":"39dca29a59bf4852875d6e6e7b7d63a1","Name":"Medium Ftilt (Hit 1)","OwnerId":47,"Owner":"Ryu","FirstActionableFrame":"38","Angle":"270","BaseKnockBackSetKnockback":"F: 15","LandingLag":null,"AutoCancel":null,"KnockbackGrowth":"100","MoveType":"ground","IsWeightDependent":false,"Game":"Ultimate","Related":{"Smash4":{"Character":"http://test-khapi.frannsoft.com/api/characters/name/Ryu?game=smash4"},"Ultimate":{"Character":"http://test-khapi.frannsoft.com/api/characters/name/Ryu?game=ultimate","Self":"http://test-khapi.frannsoft.com/api/moves/39dca29a59bf4852875d6e6e7b7d63a1?game=ultimate"}},"Links":[{"Rel":"self","Href":"http://test-khapi.frannsoft.com/api/moves/39dca29a59bf4852875d6e6e7b7d63a1?game=ultimate"},{"Rel":"character","Href":"http://test-khapi.frannsoft.com/api/characters/name/Ryu?game=ultimate"}]},{"HitboxActive":{"Frames":"18-19","Adv":"-12","SD":"+20","ShieldstunMultiplier":"","RehitRate":"","FacingRestrict":"","SuperArmor":"","HeadMultiplier":"","Intangible":"","SetWeight":false,"GroundOnly":false},"BaseDamage":{"Normal":"6","OneVOne":"7.2"},"InstanceId":"e68a4ea1309a43529cc9056e6983377c","Name":"Medium Ftilt (Hit 2)","OwnerId":47,"Owner":"Ryu","FirstActionableFrame":"-","Angle":"46","BaseKnockBackSetKnockback":"60","LandingLag":null,"AutoCancel":null,"KnockbackGrowth":"90","MoveType":"ground","IsWeightDependent":false,"Game":"Ultimate","Related":{"Smash4":{"Character":"http://test-khapi.frannsoft.com/api/characters/name/Ryu?game=smash4"},"Ultimate":{"Character":"http://test-khapi.frannsoft.com/api/characters/name/Ryu?game=ultimate","Self":"http://test-khapi.frannsoft.com/api/moves/e68a4ea1309a43529cc9056e6983377c?game=ultimate"}},"Links":[{"Rel":"self","Href":"http://test-khapi.frannsoft.com/api/moves/e68a4ea1309a43529cc9056e6983377c?game=ultimate"},{"Rel":"character","Href":"http://test-khapi.frannsoft.com/api/characters/name/Ryu?game=ultimate"}]},{"HitboxActive":{"Frames":"13-18","Adv":"","SD":"","ShieldstunMultiplier":"","RehitRate":"","FacingRestrict":"","SuperArmor":"","HeadMultiplier":"","Intangible":"","SetWeight":false,"GroundOnly":false},"BaseDamage":{"Normal":"6.5","OneVOne":"7.8"},"InstanceId":"4ad74f6085154c309ba5a09ee3a6c1c6","Name":"Medium Hadouken","OwnerId":47,"Owner":"Ryu","FirstActionableFrame":"-","Angle":"0/60","BaseKnockBackSetKnockback":"65","LandingLag":null,"AutoCancel":null,"KnockbackGrowth":"10","MoveType":"special","IsWeightDependent":false,"Game":"Ultimate","Related":{"Smash4":{"Character":"http://test-khapi.frannsoft.com/api/characters/name/Ryu?game=smash4"},"Ultimate":{"Character":"http://test-khapi.frannsoft.com/api/characters/name/Ryu?game=ultimate","Self":"http://test-khapi.frannsoft.com/api/moves/4ad74f6085154c309ba5a09ee3a6c1c6?game=ultimate"}},"Links":[{"Rel":"self","Href":"http://test-khapi.frannsoft.com/api/moves/4ad74f6085154c309ba5a09ee3a6c1c6?game=ultimate"},{"Rel":"character","Href":"http://test-khapi.frannsoft.com/api/characters/name/Ryu?game=ultimate"}]},{"HitboxActive":{"Frames":"19-67","Adv":"","SD":"","ShieldstunMultiplier":"","RehitRate":"","FacingRestrict":"","SuperArmor":"","HeadMultiplier":"","Intangible":"","SetWeight":false,"GroundOnly":false},"BaseDamage":{"Normal":"6.5","OneVOne":"7.8"},"InstanceId":"5d0f7a58feef41749ceff83473902a12","Name":"Medium Hadouken (Late)","OwnerId":47,"Owner":"Ryu","FirstActionableFrame":"-","Angle":"0/60","BaseKnockBackSetKnockback":"55/65","LandingLag":null,"AutoCancel":null,"KnockbackGrowth":"10","MoveType":"special","IsWeightDependent":false,"Game":"Ultimate","Related":{"Smash4":{"Character":"http://test-khapi.frannsoft.com/api/characters/name/Ryu?game=smash4"},"Ultimate":{"Character":"http://test-khapi.frannsoft.com/api/characters/name/Ryu?game=ultimate","Self":"http://test-khapi.frannsoft.com/api/moves/5d0f7a58feef41749ceff83473902a12?game=ultimate"}},"Links":[{"Rel":"self","Href":"http://test-khapi.frannsoft.com/api/moves/5d0f7a58feef41749ceff83473902a12?game=ultimate"},{"Rel":"character","Href":"http://test-khapi.frannsoft.com/api/characters/name/Ryu?game=ultimate"}]},{"HitboxActive":{"Frames":"7","Adv":"-18","SD":"","ShieldstunMultiplier":"","RehitRate":"","FacingRestrict":"","SuperArmor":"","HeadMultiplier":"","Intangible":"4-10","SetWeight":false,"GroundOnly":false},"BaseDamage":{"Normal":"12/12/12/8","OneVOne":"14.4/14.4/14.4/9.6"},"InstanceId":"054f3142d7cd428d95a9427aadc5f5e4","Name":"Medium Jab 1","OwnerId":47,"Owner":"Ryu","FirstActionableFrame":"38","Angle":"85","BaseKnockBackSetKnockback":"70","LandingLag":null,"AutoCancel":null,"KnockbackGrowth":"70","MoveType":"ground","IsWeightDependent":false,"Game":"Ultimate","Related":{"Smash4":{"Character":"http://test-khapi.frannsoft.com/api/characters/name/Ryu?game=smash4"},"Ultimate":{"Character":"http://test-khapi.frannsoft.com/api/characters/name/Ryu?game=ultimate","Self":"http://test-khapi.frannsoft.com/api/moves/054f3142d7cd428d95a9427aadc5f5e4?game=ultimate"}},"Links":[{"Rel":"self","Href":"http://test-khapi.frannsoft.com/api/moves/054f3142d7cd428d95a9427aadc5f5e4?game=ultimate"},{"Rel":"character","Href":"http://test-khapi.frannsoft.com/api/characters/name/Ryu?game=ultimate"}]},{"HitboxActive":{"Frames":"8-11","Adv":"","SD":"","ShieldstunMultiplier":"","RehitRate":"","FacingRestrict":"","SuperArmor":"","HeadMultiplier":"","Intangible":"","SetWeight":false,"GroundOnly":false},"BaseDamage":{"Normal":"12","OneVOne":"14.4"},"InstanceId":"6bdb0492789540dba11a3387a92914bb","Name":"Medium Jab 1 (Late)","OwnerId":47,"Owner":"Ryu","FirstActionableFrame":"-","Angle":"85","BaseKnockBackSetKnockback":"70","LandingLag":null,"AutoCancel":null,"KnockbackGrowth":"70","MoveType":"ground","IsWeightDependent":false,"Game":"Ultimate","Related":{"Smash4":{"Character":"http://test-khapi.frannsoft.com/api/characters/name/Ryu?game=smash4"},"Ultimate":{"Character":"http://test-khapi.frannsoft.com/api/characters/name/Ryu?game=ultimate","Self":"http://test-khapi.frannsoft.com/api/moves/6bdb0492789540dba11a3387a92914bb?game=ultimate"}},"Links":[{"Rel":"self","Href":"http://test-khapi.frannsoft.com/api/moves/6bdb0492789540dba11a3387a92914bb?game=ultimate"},{"Rel":"character","Href":"http://test-khapi.frannsoft.com/api/characters/name/Ryu?game=ultimate"}]},{"HitboxActive":{"Frames":"13-61 (Rehit rate: 1)","Adv":"","SD":"","ShieldstunMultiplier":"","RehitRate":"","FacingRestrict":"","SuperArmor":"","HeadMultiplier":"","Intangible":"","SetWeight":false,"GroundOnly":false},"BaseDamage":{"Normal":"1.1","OneVOne":"1.32"},"InstanceId":"9afa345f811d483bbca684b01fb4bcb0","Name":"Medium Shakunetsu Hadouken","OwnerId":47,"Owner":"Ryu","FirstActionableFrame":"-","Angle":"0","BaseKnockBackSetKnockback":"17","LandingLag":null,"AutoCancel":null,"KnockbackGrowth":"10","MoveType":"special","IsWeightDependent":false,"Game":"Ultimate","Related":{"Smash4":{"Character":"http://test-khapi.frannsoft.com/api/characters/name/Ryu?game=smash4"},"Ultimate":{"Character":"http://test-khapi.frannsoft.com/api/characters/name/Ryu?game=ultimate","Self":"http://test-khapi.frannsoft.com/api/moves/9afa345f811d483bbca684b01fb4bcb0?game=ultimate"}},"Links":[{"Rel":"self","Href":"http://test-khapi.frannsoft.com/api/moves/9afa345f811d483bbca684b01fb4bcb0?game=ultimate"},{"Rel":"character","Href":"http://test-khapi.frannsoft.com/api/characters/name/Ryu?game=ultimate"}]},{"HitboxActive":{"Frames":"6","Adv":"","SD":"","ShieldstunMultiplier":"","RehitRate":"","FacingRestrict":"","SuperArmor":"","HeadMultiplier":"","Intangible":"","SetWeight":false,"GroundOnly":false},"BaseDamage":{"Normal":"13","OneVOne":"15.6"},"InstanceId":"aee46619fdbb470e94d0afd3faa83f8a","Name":"Medium Shoryuken (Aerial, Early)","OwnerId":47,"Owner":"Ryu","FirstActionableFrame":"-","Angle":"80","BaseKnockBackSetKnockback":"80","LandingLag":null,"AutoCancel":null,"KnockbackGrowth":"54","MoveType":"special","IsWeightDependent":false,"Game":"Ultimate","Related":{"Smash4":{"Character":"http://test-khapi.frannsoft.com/api/characters/name/Ryu?game=smash4"},"Ultimate":{"Character":"http://test-khapi.frannsoft.com/api/characters/name/Ryu?game=ultimate","Self":"http://test-khapi.frannsoft.com/api/moves/aee46619fdbb470e94d0afd3faa83f8a?game=ultimate"}},"Links":[{"Rel":"self","Href":"http://test-khapi.frannsoft.com/api/moves/aee46619fdbb470e94d0afd3faa83f8a?game=ultimate"},{"Rel":"character","Href":"http://test-khapi.frannsoft.com/api/characters/name/Ryu?game=ultimate"}]},{"HitboxActive":{"Frames":"6","Adv":"","SD":"","ShieldstunMultiplier":"","RehitRate":"","FacingRestrict":"","SuperArmor":"","HeadMultiplier":"","Intangible":"","SetWeight":false,"GroundOnly":false},"BaseDamage":{"Normal":"14","OneVOne":"16.8"},"InstanceId":"da90044ce8314a1a98bc783c63100469","Name":"Medium Shoryuken (Grounded, Early)","OwnerId":47,"Owner":"Ryu","FirstActionableFrame":"-","Angle":"80","BaseKnockBackSetKnockback":"80","LandingLag":null,"AutoCancel":null,"KnockbackGrowth":"64","MoveType":"special","IsWeightDependent":false,"Game":"Ultimate","Related":{"Smash4":{"Character":"http://test-khapi.frannsoft.com/api/characters/name/Ryu?game=smash4"},"Ultimate":{"Character":"http://test-khapi.frannsoft.com/api/characters/name/Ryu?game=ultimate","Self":"http://test-khapi.frannsoft.com/api/moves/da90044ce8314a1a98bc783c63100469?game=ultimate"}},"Links":[{"Rel":"self","Href":"http://test-khapi.frannsoft.com/api/moves/da90044ce8314a1a98bc783c63100469?game=ultimate"},{"Rel":"character","Href":"http://test-khapi.frannsoft.com/api/characters/name/Ryu?game=ultimate"}]},{"HitboxActive":{"Frames":"21-23, 37-39","Adv":"","SD":"","ShieldstunMultiplier":"","RehitRate":"","FacingRestrict":"","SuperArmor":"","HeadMultiplier":"","Intangible":"","SetWeight":false,"GroundOnly":false},"BaseDamage":{"Normal":"8.5","OneVOne":"10.2"},"InstanceId":"b5bc08a7b56449eca35a2616f20d58ae","Name":"Medium Tatsumaki Senpukyaku (Aerial)","OwnerId":47,"Owner":"Ryu","FirstActionableFrame":"-","Angle":"50","BaseKnockBackSetKnockback":"80","LandingLag":null,"AutoCancel":null,"KnockbackGrowth":"57","MoveType":"special","IsWeightDependent":false,"Game":"Ultimate","Related":{"Smash4":{"Character":"http://test-khapi.frannsoft.com/api/characters/name/Ryu?game=smash4"},"Ultimate":{"Character":"http://test-khapi.frannsoft.com/api/characters/name/Ryu?game=ultimate","Self":"http://test-khapi.frannsoft.com/api/moves/b5bc08a7b56449eca35a2616f20d58ae?game=ultimate"}},"Links":[{"Rel":"self","Href":"http://test-khapi.frannsoft.com/api/moves/b5bc08a7b56449eca35a2616f20d58ae?game=ultimate"},{"Rel":"character","Href":"http://test-khapi.frannsoft.com/api/characters/name/Ryu?game=ultimate"}]},{"HitboxActive":{"Frames":"13-15, 29-31","Adv":"","SD":"","ShieldstunMultiplier":"","RehitRate":"","FacingRestrict":"","SuperArmor":"","HeadMultiplier":"","Intangible":"13-44","SetWeight":false,"GroundOnly":false},"BaseDamage":{"Normal":"9","OneVOne":"10.8"},"InstanceId":"9d1198bde08145dd9901e151a93e5242","Name":"Medium Tatsumaki Senpukyaku (Aerial)","OwnerId":47,"Owner":"Ryu","FirstActionableFrame":"80","Angle":"62","BaseKnockBackSetKnockback":"80","LandingLag":null,"AutoCancel":null,"KnockbackGrowth":"67","MoveType":"special","IsWeightDependent":false,"Game":"Ultimate","Related":{"Smash4":{"Character":"http://test-khapi.frannsoft.com/api/characters/name/Ryu?game=smash4"},"Ultimate":{"Character":"http://test-khapi.frannsoft.com/api/characters/name/Ryu?game=ultimate","Self":"http://test-khapi.frannsoft.com/api/moves/9d1198bde08145dd9901e151a93e5242?game=ultimate"}},"Links":[{"Rel":"self","Href":"http://test-khapi.frannsoft.com/api/moves/9d1198bde08145dd9901e151a93e5242?game=ultimate"},{"Rel":"character","Href":"http://test-khapi.frannsoft.com/api/characters/name/Ryu?game=ultimate"}]},{"HitboxActive":{"Frames":"21-23, 37-39, 53-55","Adv":"","SD":"","ShieldstunMultiplier":"","RehitRate":"","FacingRestrict":"","SuperArmor":"","HeadMultiplier":"","Intangible":"","SetWeight":false,"GroundOnly":false},"BaseDamage":{"Normal":"9.5","OneVOne":"11.4"},"InstanceId":"e79ef69cba4242c196751e36b8cf53ed","Name":"Medium Tatsumaki Senpukyaku (Grounded)","OwnerId":47,"Owner":"Ryu","FirstActionableFrame":"-","Angle":"50","BaseKnockBackSetKnockback":"80","LandingLag":null,"AutoCancel":null,"KnockbackGrowth":"57","MoveType":"special","IsWeightDependent":false,"Game":"Ultimate","Related":{"Smash4":{"Character":"http://test-khapi.frannsoft.com/api/characters/name/Ryu?game=smash4"},"Ultimate":{"Character":"http://test-khapi.frannsoft.com/api/characters/name/Ryu?game=ultimate","Self":"http://test-khapi.frannsoft.com/api/moves/e79ef69cba4242c196751e36b8cf53ed?game=ultimate"}},"Links":[{"Rel":"self","Href":"http://test-khapi.frannsoft.com/api/moves/e79ef69cba4242c196751e36b8cf53ed?game=ultimate"},{"Rel":"character","Href":"http://test-khapi.frannsoft.com/api/characters/name/Ryu?game=ultimate"}]},{"HitboxActive":{"Frames":"13-15, 29-31, 45-47","Adv":"","SD":"","ShieldstunMultiplier":"","RehitRate":"","FacingRestrict":"","SuperArmor":"","HeadMultiplier":"","Intangible":"13-60","SetWeight":false,"GroundOnly":false},"BaseDamage":{"Normal":"10","OneVOne":"12"},"InstanceId":"75d60e6006474eba8ae5419c14c2046a","Name":"Medium Tatsumaki Senpukyaku (Grounded)","OwnerId":47,"Owner":"Ryu","FirstActionableFrame":"91","Angle":"62","BaseKnockBackSetKnockback":"80","LandingLag":null,"AutoCancel":null,"KnockbackGrowth":"67","MoveType":"special","IsWeightDependent":false,"Game":"Ultimate","Related":{"Smash4":{"Character":"http://test-khapi.frannsoft.com/api/characters/name/Ryu?game=smash4"},"Ultimate":{"Character":"http://test-khapi.frannsoft.com/api/characters/name/Ryu?game=ultimate","Self":"http://test-khapi.frannsoft.com/api/moves/75d60e6006474eba8ae5419c14c2046a?game=ultimate"}},"Links":[{"Rel":"self","Href":"http://test-khapi.frannsoft.com/api/moves/75d60e6006474eba8ae5419c14c2046a?game=ultimate"},{"Rel":"character","Href":"http://test-khapi.frannsoft.com/api/characters/name/Ryu?game=ultimate"}]},{"HitboxActive":{"Frames":"7","Adv":"-18","SD":"","ShieldstunMultiplier":"","RehitRate":"","FacingRestrict":"","SuperArmor":"","HeadMultiplier":"","Intangible":"4-10","SetWeight":false,"GroundOnly":false},"BaseDamage":{"Normal":"12/12/12/8","OneVOne":"14.4/14.4/14.4/9.6"},"InstanceId":"dd7ffce13ada417d84b7db630e3530a1","Name":"Medium Utilt","OwnerId":47,"Owner":"Ryu","FirstActionableFrame":"38","Angle":"80","BaseKnockBackSetKnockback":"70","LandingLag":null,"AutoCancel":null,"KnockbackGrowth":"70","MoveType":"ground","IsWeightDependent":false,"Game":"Ultimate","Related":{"Smash4":{"Character":"http://test-khapi.frannsoft.com/api/characters/name/Ryu?game=smash4"},"Ultimate":{"Character":"http://test-khapi.frannsoft.com/api/characters/name/Ryu?game=ultimate","Self":"http://test-khapi.frannsoft.com/api/moves/dd7ffce13ada417d84b7db630e3530a1?game=ultimate"}},"Links":[{"Rel":"self","Href":"http://test-khapi.frannsoft.com/api/moves/dd7ffce13ada417d84b7db630e3530a1?game=ultimate"},{"Rel":"character","Href":"http://test-khapi.frannsoft.com/api/characters/name/Ryu?game=ultimate"}]},{"HitboxActive":{"Frames":"8-11","Adv":"","SD":"","ShieldstunMultiplier":"","RehitRate":"","FacingRestrict":"","SuperArmor":"","HeadMultiplier":"","Intangible":"","SetWeight":false,"GroundOnly":false},"BaseDamage":{"Normal":"12","OneVOne":"14.4"},"InstanceId":"6814442ec93d4d8b85a488e4191cde24","Name":"Medium Utilt (Late)","OwnerId":47,"Owner":"Ryu","FirstActionableFrame":"-","Angle":"80","BaseKnockBackSetKnockback":"70","LandingLag":null,"AutoCancel":null,"KnockbackGrowth":"70","MoveType":"ground","IsWeightDependent":false,"Game":"Ultimate","Related":{"Smash4":{"Character":"http://test-khapi.frannsoft.com/api/characters/name/Ryu?game=smash4"},"Ultimate":{"Character":"http://test-khapi.frannsoft.com/api/characters/name/Ryu?game=ultimate","Self":"http://test-khapi.frannsoft.com/api/moves/6814442ec93d4d8b85a488e4191cde24?game=ultimate"}},"Links":[{"Rel":"self","Href":"http://test-khapi.frannsoft.com/api/moves/6814442ec93d4d8b85a488e4191cde24?game=ultimate"},{"Rel":"character","Href":"http://test-khapi.frannsoft.com/api/characters/name/Ryu?game=ultimate"}]},{"HitboxActive":{"Frames":"4-6","Adv":"-1","SD":"","ShieldstunMultiplier":"","RehitRate":"","FacingRestrict":"","SuperArmor":"","HeadMultiplier":"","Intangible":"","SetWeight":false,"GroundOnly":false},"BaseDamage":{"Normal":"8","OneVOne":"9.6"},"InstanceId":"92e8e56f9ace42d6927ad29e0680aa87","Name":"Nair","OwnerId":47,"Owner":"Ryu","FirstActionableFrame":"36","Angle":"361","BaseKnockBackSetKnockback":"20","LandingLag":"5","AutoCancel":"","KnockbackGrowth":"100","MoveType":"aerial","IsWeightDependent":false,"Game":"Ultimate","Related":{"Smash4":{"Character":"http://test-khapi.frannsoft.com/api/characters/name/Ryu?game=smash4"},"Ultimate":{"Character":"http://test-khapi.frannsoft.com/api/characters/name/Ryu?game=ultimate","Self":"http://test-khapi.frannsoft.com/api/moves/92e8e56f9ace42d6927ad29e0680aa87?game=ultimate"}},"Links":[{"Rel":"self","Href":"http://test-khapi.frannsoft.com/api/moves/92e8e56f9ace42d6927ad29e0680aa87?game=ultimate"},{"Rel":"character","Href":"http://test-khapi.frannsoft.com/api/characters/name/Ryu?game=ultimate"}]},{"HitboxActive":{"Frames":"7-31","Adv":"","SD":"","ShieldstunMultiplier":"","RehitRate":"","FacingRestrict":"","SuperArmor":"","HeadMultiplier":"","Intangible":"","SetWeight":false,"GroundOnly":false},"BaseDamage":{"Normal":"4.5","OneVOne":"5.4"},"InstanceId":"debd00fb7df34e72815e77b736dd97fe","Name":"Nair (Late)","OwnerId":47,"Owner":"Ryu","FirstActionableFrame":"-","Angle":"361","BaseKnockBackSetKnockback":"13","LandingLag":"-","AutoCancel":"-","KnockbackGrowth":"90","MoveType":"aerial","IsWeightDependent":false,"Game":"Ultimate","Related":{"Smash4":{"Character":"http://test-khapi.frannsoft.com/api/characters/name/Ryu?game=smash4"},"Ultimate":{"Character":"http://test-khapi.frannsoft.com/api/characters/name/Ryu?game=ultimate","Self":"http://test-khapi.frannsoft.com/api/moves/debd00fb7df34e72815e77b736dd97fe?game=ultimate"}},"Links":[{"Rel":"self","Href":"http://test-khapi.frannsoft.com/api/moves/debd00fb7df34e72815e77b736dd97fe?game=ultimate"},{"Rel":"character","Href":"http://test-khapi.frannsoft.com/api/characters/name/Ryu?game=ultimate"}]},{"HitboxActive":{"Frames":"10-11","Adv":"","SD":"","ShieldstunMultiplier":"","RehitRate":"","FacingRestrict":"","SuperArmor":"","HeadMultiplier":"","Intangible":"","SetWeight":false,"GroundOnly":false},"BaseDamage":{"Normal":"","OneVOne":""},"InstanceId":"db00e94d50674edbb33c6abe98c68326","Name":"Pivot Grab","OwnerId":47,"Owner":"Ryu","FirstActionableFrame":"38","Angle":"","BaseKnockBackSetKnockback":"","LandingLag":null,"AutoCancel":null,"KnockbackGrowth":"","MoveType":"ground","IsWeightDependent":false,"Game":"Ultimate","Related":{"Smash4":{"Character":"http://test-khapi.frannsoft.com/api/characters/name/Ryu?game=smash4"},"Ultimate":{"Character":"http://test-khapi.frannsoft.com/api/characters/name/Ryu?game=ultimate","Self":"http://test-khapi.frannsoft.com/api/moves/db00e94d50674edbb33c6abe98c68326?game=ultimate"}},"Links":[{"Rel":"self","Href":"http://test-khapi.frannsoft.com/api/moves/db00e94d50674edbb33c6abe98c68326?game=ultimate"},{"Rel":"character","Href":"http://test-khapi.frannsoft.com/api/characters/name/Ryu?game=ultimate"}]},{"HitboxActive":{"Frames":"-","Adv":"","SD":"","ShieldstunMultiplier":"","RehitRate":"","FacingRestrict":"","SuperArmor":"","HeadMultiplier":"","Intangible":"","SetWeight":false,"GroundOnly":false},"BaseDamage":{"Normal":"5","OneVOne":"6"},"InstanceId":"407a1e412055419a8a4e62789fbaeb7e","Name":"Shakunetsu Hadouken (Final Hit)","OwnerId":47,"Owner":"Ryu","FirstActionableFrame":"-","Angle":"55","BaseKnockBackSetKnockback":"60","LandingLag":null,"AutoCancel":null,"KnockbackGrowth":"60","MoveType":"special","IsWeightDependent":false,"Game":"Ultimate","Related":{"Smash4":{"Character":"http://test-khapi.frannsoft.com/api/characters/name/Ryu?game=smash4"},"Ultimate":{"Character":"http://test-khapi.frannsoft.com/api/characters/name/Ryu?game=ultimate","Self":"http://test-khapi.frannsoft.com/api/moves/407a1e412055419a8a4e62789fbaeb7e?game=ultimate"}},"Links":[{"Rel":"self","Href":"http://test-khapi.frannsoft.com/api/moves/407a1e412055419a8a4e62789fbaeb7e?game=ultimate"},{"Rel":"character","Href":"http://test-khapi.frannsoft.com/api/characters/name/Ryu?game=ultimate"}]},{"HitboxActive":{"Frames":"9-19","Adv":"","SD":"","ShieldstunMultiplier":"","RehitRate":"","FacingRestrict":"","SuperArmor":"","HeadMultiplier":"","Intangible":"","SetWeight":false,"GroundOnly":false},"BaseDamage":{"Normal":"7","OneVOne":"8.4"},"InstanceId":"cec60c802c6443529cbd58f95c757a5f","Name":"Shoryuken (Aerial, Late)","OwnerId":47,"Owner":"Ryu","FirstActionableFrame":"-","Angle":"70","BaseKnockBackSetKnockback":"60","LandingLag":null,"AutoCancel":null,"KnockbackGrowth":"70","MoveType":"special","IsWeightDependent":false,"Game":"Ultimate","Related":{"Smash4":{"Character":"http://test-khapi.frannsoft.com/api/characters/name/Ryu?game=smash4"},"Ultimate":{"Character":"http://test-khapi.frannsoft.com/api/characters/name/Ryu?game=ultimate","Self":"http://test-khapi.frannsoft.com/api/moves/cec60c802c6443529cbd58f95c757a5f?game=ultimate"}},"Links":[{"Rel":"self","Href":"http://test-khapi.frannsoft.com/api/moves/cec60c802c6443529cbd58f95c757a5f?game=ultimate"},{"Rel":"character","Href":"http://test-khapi.frannsoft.com/api/characters/name/Ryu?game=ultimate"}]},{"HitboxActive":{"Frames":"7-8","Adv":"","SD":"","ShieldstunMultiplier":"","RehitRate":"","FacingRestrict":"","SuperArmor":"","HeadMultiplier":"","Intangible":"","SetWeight":false,"GroundOnly":false},"BaseDamage":{"Normal":"10","OneVOne":"12"},"InstanceId":"1618b2d271ab4de3bf201d1c6bf1f8ca","Name":"Shoryuken (Aerial)","OwnerId":47,"Owner":"Ryu","FirstActionableFrame":"-","Angle":"80","BaseKnockBackSetKnockback":"80","LandingLag":null,"AutoCancel":null,"KnockbackGrowth":"57","MoveType":"special","IsWeightDependent":false,"Game":"Ultimate","Related":{"Smash4":{"Character":"http://test-khapi.frannsoft.com/api/characters/name/Ryu?game=smash4"},"Ultimate":{"Character":"http://test-khapi.frannsoft.com/api/characters/name/Ryu?game=ultimate","Self":"http://test-khapi.frannsoft.com/api/moves/1618b2d271ab4de3bf201d1c6bf1f8ca?game=ultimate"}},"Links":[{"Rel":"self","Href":"http://test-khapi.frannsoft.com/api/moves/1618b2d271ab4de3bf201d1c6bf1f8ca?game=ultimate"},{"Rel":"character","Href":"http://test-khapi.frannsoft.com/api/characters/name/Ryu?game=ultimate"}]},{"HitboxActive":{"Frames":"Intangible: 5","Adv":"","SD":"","ShieldstunMultiplier":"","RehitRate":"","FacingRestrict":"","SuperArmor":"","HeadMultiplier":"","Intangible":"","SetWeight":false,"GroundOnly":false},"BaseDamage":{"Normal":"-","OneVOne":""},"InstanceId":"9e55db9b10394e77bac2db6d75d6cb72","Name":"Shoryuken (All Versions)","OwnerId":47,"Owner":"Ryu","FirstActionableFrame":"-","Angle":"-","BaseKnockBackSetKnockback":"-","LandingLag":null,"AutoCancel":null,"KnockbackGrowth":"-","MoveType":"special","IsWeightDependent":false,"Game":"Ultimate","Related":{"Smash4":{"Character":"http://test-khapi.frannsoft.com/api/characters/name/Ryu?game=smash4"},"Ultimate":{"Character":"http://test-khapi.frannsoft.com/api/characters/name/Ryu?game=ultimate","Self":"http://test-khapi.frannsoft.com/api/moves/9e55db9b10394e77bac2db6d75d6cb72?game=ultimate"}},"Links":[{"Rel":"self","Href":"http://test-khapi.frannsoft.com/api/moves/9e55db9b10394e77bac2db6d75d6cb72?game=ultimate"},{"Rel":"character","Href":"http://test-khapi.frannsoft.com/api/characters/name/Ryu?game=ultimate"}]},{"HitboxActive":{"Frames":"Right Arm Intangible: 1-3, 7-14, Intangible: 4-6","Adv":"","SD":"","ShieldstunMultiplier":"","RehitRate":"","FacingRestrict":"","SuperArmor":"","HeadMultiplier":"","Intangible":"","SetWeight":false,"GroundOnly":false},"BaseDamage":{"Normal":"Multiplier: 1.2","OneVOne":""},"InstanceId":"4d3e67b2f434434a892048f77987f9a6","Name":"Shoryuken (Command, All Versions)","OwnerId":47,"Owner":"Ryu","FirstActionableFrame":"-","Angle":"-","BaseKnockBackSetKnockback":"-","LandingLag":null,"AutoCancel":null,"KnockbackGrowth":"-","MoveType":"special","IsWeightDependent":false,"Game":"Ultimate","Related":{"Smash4":{"Character":"http://test-khapi.frannsoft.com/api/characters/name/Ryu?game=smash4"},"Ultimate":{"Character":"http://test-khapi.frannsoft.com/api/characters/name/Ryu?game=ultimate","Self":"http://test-khapi.frannsoft.com/api/moves/4d3e67b2f434434a892048f77987f9a6?game=ultimate"}},"Links":[{"Rel":"self","Href":"http://test-khapi.frannsoft.com/api/moves/4d3e67b2f434434a892048f77987f9a6?game=ultimate"},{"Rel":"character","Href":"http://test-khapi.frannsoft.com/api/characters/name/Ryu?game=ultimate"}]},{"HitboxActive":{"Frames":"9-19","Adv":"","SD":"","ShieldstunMultiplier":"","RehitRate":"","FacingRestrict":"","SuperArmor":"","HeadMultiplier":"","Intangible":"","SetWeight":false,"GroundOnly":false},"BaseDamage":{"Normal":"7","OneVOne":"8.4"},"InstanceId":"35ddb9ab7931453b9f361d9da50cbde1","Name":"Shoryuken (Grounded, Late)","OwnerId":47,"Owner":"Ryu","FirstActionableFrame":"-","Angle":"70","BaseKnockBackSetKnockback":"60","LandingLag":null,"AutoCancel":null,"KnockbackGrowth":"90","MoveType":"special","IsWeightDependent":false,"Game":"Ultimate","Related":{"Smash4":{"Character":"http://test-khapi.frannsoft.com/api/characters/name/Ryu?game=smash4"},"Ultimate":{"Character":"http://test-khapi.frannsoft.com/api/characters/name/Ryu?game=ultimate","Self":"http://test-khapi.frannsoft.com/api/moves/35ddb9ab7931453b9f361d9da50cbde1?game=ultimate"}},"Links":[{"Rel":"self","Href":"http://test-khapi.frannsoft.com/api/moves/35ddb9ab7931453b9f361d9da50cbde1?game=ultimate"},{"Rel":"character","Href":"http://test-khapi.frannsoft.com/api/characters/name/Ryu?game=ultimate"}]},{"HitboxActive":{"Frames":"7-8","Adv":"","SD":"","ShieldstunMultiplier":"","RehitRate":"","FacingRestrict":"","SuperArmor":"","HeadMultiplier":"","Intangible":"","SetWeight":false,"GroundOnly":false},"BaseDamage":{"Normal":"12","OneVOne":"14.4"},"InstanceId":"525198d136e046e8ab49545a318ef1c5","Name":"Shoryuken (Grounded)","OwnerId":47,"Owner":"Ryu","FirstActionableFrame":"-","Angle":"80","BaseKnockBackSetKnockback":"80","LandingLag":null,"AutoCancel":null,"KnockbackGrowth":"64","MoveType":"special","IsWeightDependent":false,"Game":"Ultimate","Related":{"Smash4":{"Character":"http://test-khapi.frannsoft.com/api/characters/name/Ryu?game=smash4"},"Ultimate":{"Character":"http://test-khapi.frannsoft.com/api/characters/name/Ryu?game=ultimate","Self":"http://test-khapi.frannsoft.com/api/moves/525198d136e046e8ab49545a318ef1c5?game=ultimate"}},"Links":[{"Rel":"self","Href":"http://test-khapi.frannsoft.com/api/moves/525198d136e046e8ab49545a318ef1c5?game=ultimate"},{"Rel":"character","Href":"http://test-khapi.frannsoft.com/api/characters/name/Ryu?game=ultimate"}]},{"HitboxActive":{"Frames":"3-17","Adv":"","SD":"","ShieldstunMultiplier":"","RehitRate":"","FacingRestrict":"","SuperArmor":"","HeadMultiplier":"","Intangible":"","SetWeight":false,"GroundOnly":false},"BaseDamage":{"Normal":"","OneVOne":""},"InstanceId":"9b59f9df2c974c7d9f6952a6b17182b0","Name":"Spotdodge","OwnerId":47,"Owner":"Ryu","FirstActionableFrame":"27","Angle":"","BaseKnockBackSetKnockback":"","LandingLag":null,"AutoCancel":null,"KnockbackGrowth":"","MoveType":"ground","IsWeightDependent":false,"Game":"Ultimate","Related":{"Smash4":{"Character":"http://test-khapi.frannsoft.com/api/characters/name/Ryu?game=smash4"},"Ultimate":{"Character":"http://test-khapi.frannsoft.com/api/characters/name/Ryu?game=ultimate","Self":"http://test-khapi.frannsoft.com/api/moves/9b59f9df2c974c7d9f6952a6b17182b0?game=ultimate"}},"Links":[{"Rel":"self","Href":"http://test-khapi.frannsoft.com/api/moves/9b59f9df2c974c7d9f6952a6b17182b0?game=ultimate"},{"Rel":"character","Href":"http://test-khapi.frannsoft.com/api/characters/name/Ryu?game=ultimate"}]},{"HitboxActive":{"Frames":"6-7","Adv":"","SD":"","ShieldstunMultiplier":"","RehitRate":"","FacingRestrict":"","SuperArmor":"","HeadMultiplier":"","Intangible":"","SetWeight":false,"GroundOnly":false},"BaseDamage":{"Normal":"","OneVOne":""},"InstanceId":"ffdc7aea419f48aea5a01ddd2ad95e5f","Name":"Standing Grab","OwnerId":47,"Owner":"Ryu","FirstActionableFrame":"35","Angle":"","BaseKnockBackSetKnockback":"","LandingLag":null,"AutoCancel":null,"KnockbackGrowth":"","MoveType":"ground","IsWeightDependent":false,"Game":"Ultimate","Related":{"Smash4":{"Character":"http://test-khapi.frannsoft.com/api/characters/name/Ryu?game=smash4"},"Ultimate":{"Character":"http://test-khapi.frannsoft.com/api/characters/name/Ryu?game=ultimate","Self":"http://test-khapi.frannsoft.com/api/moves/ffdc7aea419f48aea5a01ddd2ad95e5f?game=ultimate"}},"Links":[{"Rel":"self","Href":"http://test-khapi.frannsoft.com/api/moves/ffdc7aea419f48aea5a01ddd2ad95e5f?game=ultimate"},{"Rel":"character","Href":"http://test-khapi.frannsoft.com/api/characters/name/Ryu?game=ultimate"}]},{"HitboxActive":{"Frames":"-","Adv":"","SD":"","ShieldstunMultiplier":"","RehitRate":"","FacingRestrict":"","SuperArmor":"","HeadMultiplier":"","Intangible":"","SetWeight":false,"GroundOnly":false},"BaseDamage":{"Normal":"Multiplier: 1.16","OneVOne":""},"InstanceId":"9d10bc982a9d4fd9bb2f25fbbcf82c49","Name":"Tatsumaki Senpukyaku (Command, All Versions)","OwnerId":47,"Owner":"Ryu","FirstActionableFrame":"-","Angle":"-","BaseKnockBackSetKnockback":"-","LandingLag":null,"AutoCancel":null,"KnockbackGrowth":"-","MoveType":"special","IsWeightDependent":false,"Game":"Ultimate","Related":{"Smash4":{"Character":"http://test-khapi.frannsoft.com/api/characters/name/Ryu?game=smash4"},"Ultimate":{"Character":"http://test-khapi.frannsoft.com/api/characters/name/Ryu?game=ultimate","Self":"http://test-khapi.frannsoft.com/api/moves/9d10bc982a9d4fd9bb2f25fbbcf82c49?game=ultimate"}},"Links":[{"Rel":"self","Href":"http://test-khapi.frannsoft.com/api/moves/9d10bc982a9d4fd9bb2f25fbbcf82c49?game=ultimate"},{"Rel":"character","Href":"http://test-khapi.frannsoft.com/api/characters/name/Ryu?game=ultimate"}]},{"HitboxActive":{"Frames":"8-9","Adv":"","SD":"","ShieldstunMultiplier":"","RehitRate":"","FacingRestrict":"","SuperArmor":"","HeadMultiplier":"","Intangible":"","SetWeight":false,"GroundOnly":false},"BaseDamage":{"Normal":"9","OneVOne":"10.8"},"InstanceId":"2f1076445bee46ef97f91de6fa0f1b7c","Name":"Tatsumaki Senpukyaku (Grounded, Early)","OwnerId":47,"Owner":"Ryu","FirstActionableFrame":"-","Angle":"75","BaseKnockBackSetKnockback":"87","LandingLag":null,"AutoCancel":null,"KnockbackGrowth":"80","MoveType":"special","IsWeightDependent":false,"Game":"Ultimate","Related":{"Smash4":{"Character":"http://test-khapi.frannsoft.com/api/characters/name/Ryu?game=smash4"},"Ultimate":{"Character":"http://test-khapi.frannsoft.com/api/characters/name/Ryu?game=ultimate","Self":"http://test-khapi.frannsoft.com/api/moves/2f1076445bee46ef97f91de6fa0f1b7c?game=ultimate"}},"Links":[{"Rel":"self","Href":"http://test-khapi.frannsoft.com/api/moves/2f1076445bee46ef97f91de6fa0f1b7c?game=ultimate"},{"Rel":"character","Href":"http://test-khapi.frannsoft.com/api/characters/name/Ryu?game=ultimate"}]},{"HitboxActive":{"Frames":"6","Adv":"-8","SD":"","ShieldstunMultiplier":"","RehitRate":"","FacingRestrict":"","SuperArmor":"","HeadMultiplier":"","Intangible":"","SetWeight":false,"GroundOnly":false},"BaseDamage":{"Normal":"5","OneVOne":"6"},"InstanceId":"b6bf1c872d504aff9e626e81e6cec80d","Name":"Uair (Hit 1)","OwnerId":47,"Owner":"Ryu","FirstActionableFrame":"36","Angle":"366","BaseKnockBackSetKnockback":"F: 20","LandingLag":"11","AutoCancel":"","KnockbackGrowth":"100","MoveType":"aerial","IsWeightDependent":false,"Game":"Ultimate","Related":{"Smash4":{"Character":"http://test-khapi.frannsoft.com/api/characters/name/Ryu?game=smash4"},"Ultimate":{"Character":"http://test-khapi.frannsoft.com/api/characters/name/Ryu?game=ultimate","Self":"http://test-khapi.frannsoft.com/api/moves/b6bf1c872d504aff9e626e81e6cec80d?game=ultimate"}},"Links":[{"Rel":"self","Href":"http://test-khapi.frannsoft.com/api/moves/b6bf1c872d504aff9e626e81e6cec80d?game=ultimate"},{"Rel":"character","Href":"http://test-khapi.frannsoft.com/api/characters/name/Ryu?game=ultimate"}]},{"HitboxActive":{"Frames":"10","Adv":"","SD":"","ShieldstunMultiplier":"","RehitRate":"","FacingRestrict":"","SuperArmor":"","HeadMultiplier":"","Intangible":"","SetWeight":false,"GroundOnly":false},"BaseDamage":{"Normal":"6","OneVOne":"7.2"},"InstanceId":"4e206ce314ec49ae9647fac6d824bf24","Name":"Uair (Hit 2)","OwnerId":47,"Owner":"Ryu","FirstActionableFrame":"-","Angle":"75","BaseKnockBackSetKnockback":"0","LandingLag":"-","AutoCancel":"-","KnockbackGrowth":"172","MoveType":"aerial","IsWeightDependent":false,"Game":"Ultimate","Related":{"Smash4":{"Character":"http://test-khapi.frannsoft.com/api/characters/name/Ryu?game=smash4"},"Ultimate":{"Character":"http://test-khapi.frannsoft.com/api/characters/name/Ryu?game=ultimate","Self":"http://test-khapi.frannsoft.com/api/moves/4e206ce314ec49ae9647fac6d824bf24?game=ultimate"}},"Links":[{"Rel":"self","Href":"http://test-khapi.frannsoft.com/api/moves/4e206ce314ec49ae9647fac6d824bf24?game=ultimate"},{"Rel":"character","Href":"http://test-khapi.frannsoft.com/api/characters/name/Ryu?game=ultimate"}]},{"HitboxActive":{"Frames":"9","Adv":"-23","SD":"","ShieldstunMultiplier":"","RehitRate":"","FacingRestrict":"","SuperArmor":"","HeadMultiplier":"","Intangible":"9-12","SetWeight":false,"GroundOnly":false},"BaseDamage":{"Normal":"17","OneVOne":"20.4"},"InstanceId":"0847dedc531d40fcaa8665597caa6c0b","Name":"Usmash","OwnerId":47,"Owner":"Ryu","FirstActionableFrame":"45","Angle":"83","BaseKnockBackSetKnockback":"32","LandingLag":null,"AutoCancel":null,"KnockbackGrowth":"82","MoveType":"ground","IsWeightDependent":false,"Game":"Ultimate","Related":{"Smash4":{"Character":"http://test-khapi.frannsoft.com/api/characters/name/Ryu?game=smash4"},"Ultimate":{"Character":"http://test-khapi.frannsoft.com/api/characters/name/Ryu?game=ultimate","Self":"http://test-khapi.frannsoft.com/api/moves/0847dedc531d40fcaa8665597caa6c0b?game=ultimate"}},"Links":[{"Rel":"self","Href":"http://test-khapi.frannsoft.com/api/moves/0847dedc531d40fcaa8665597caa6c0b?game=ultimate"},{"Rel":"character","Href":"http://test-khapi.frannsoft.com/api/characters/name/Ryu?game=ultimate"}]},{"HitboxActive":{"Frames":"10-12","Adv":"","SD":"","ShieldstunMultiplier":"","RehitRate":"","FacingRestrict":"","SuperArmor":"","HeadMultiplier":"","Intangible":"","SetWeight":false,"GroundOnly":false},"BaseDamage":{"Normal":"13.5","OneVOne":"16.2"},"InstanceId":"eb597a6ff01a43bdb8904ec08e9a9732","Name":"Usmash (Late)","OwnerId":47,"Owner":"Ryu","FirstActionableFrame":"-","Angle":"83","BaseKnockBackSetKnockback":"32","LandingLag":null,"AutoCancel":null,"KnockbackGrowth":"86","MoveType":"ground","IsWeightDependent":false,"Game":"Ultimate","Related":{"Smash4":{"Character":"http://test-khapi.frannsoft.com/api/characters/name/Ryu?game=smash4"},"Ultimate":{"Character":"http://test-khapi.frannsoft.com/api/characters/name/Ryu?game=ultimate","Self":"http://test-khapi.frannsoft.com/api/moves/eb597a6ff01a43bdb8904ec08e9a9732?game=ultimate"}},"Links":[{"Rel":"self","Href":"http://test-khapi.frannsoft.com/api/moves/eb597a6ff01a43bdb8904ec08e9a9732?game=ultimate"},{"Rel":"character","Href":"http://test-khapi.frannsoft.com/api/characters/name/Ryu?game=ultimate"}]},{"HitboxActive":null,"BaseDamage":{"Normal":"8","OneVOne":"9.6"},"InstanceId":"6161b120aad84b1ab006f492daa3a1fe","Name":"Uthrow","OwnerId":47,"Owner":"Ryu","FirstActionableFrame":null,"Angle":"88","BaseKnockBackSetKnockback":"55","LandingLag":null,"AutoCancel":null,"KnockbackGrowth":"75","MoveType":"throw","IsWeightDependent":false,"Game":"Ultimate","Related":{"Smash4":{"Character":"http://test-khapi.frannsoft.com/api/characters/name/Ryu?game=smash4"},"Ultimate":{"Character":"http://test-khapi.frannsoft.com/api/characters/name/Ryu?game=ultimate","Self":"http://test-khapi.frannsoft.com/api/moves/6161b120aad84b1ab006f492daa3a1fe?game=ultimate"}},"Links":[{"Rel":"self","Href":"http://test-khapi.frannsoft.com/api/moves/6161b120aad84b1ab006f492daa3a1fe?game=ultimate"},{"Rel":"character","Href":"http://test-khapi.frannsoft.com/api/characters/name/Ryu?game=ultimate"}]}]